Workbook
Name HPvalue: PROFICIENCYVALUES!$B$7
Name WeaponWS: PROFICIENCYVALUES!$B$17
Name CLASSNUMBERFINDER: PROFICIENCYVALUES!$A$24:$B$47
Name CLASSLIST: PROFICIENCYVALUES!$C$24:$E$47
Name Expert: PROFICIENCYVALUES!$B$4
Name CLASSPROFILEHEADERS: CLASSPROFILES!$A$2:$A$25
Name CLASSNAMEHEADERS: CLASSDATA!$F$3:$BA$3
Name RangeWeaponGroups: PROFICIENCYVALUES!$A$59:$A$75
Name CLASSPICKER: PROFICIENCYVALUES!$A$24:$A$47
Name RangeClassProfiles: PROFICIENCYVALUES!$A$51:$A$56
Name CLASSPROFILEDATA: CLASSPROFILES!$B$2:$G$25
Name SpellSlot: PROFICIENCYVALUES!$B$13
Name RangeSkillNames: PROFICIENCYVALUES!$A$86:$A$102
Name AlchemicalFormula: PROFICIENCYVALUES!$B$15
Name SkillFeat: PROFICIENCYVALUES!$B$9
Name Trained: PROFICIENCYVALUES!$B$3
Name CantripLearned: PROFICIENCYVALUES!$B$10
Name Master: PROFICIENCYVALUES!$B$5
Name RangeAbilityScores: PROFICIENCYVALUES!$A$78:$A$83
Name WeaponCS: PROFICIENCYVALUES!$B$16
Name CLASSFEATUREHEADERS: CLASSDATA!$A$5:$A$279
Name Untrained: PROFICIENCYVALUES!$B$2
Name ALLCLASSDATA: CLASSDATA!$F$5:$BA$279
Name Legendary: PROFICIENCYVALUES!$B$6
Name ProficiencyValues: PROFICIENCYVALUES!$A$2:$B$6
Name ArmorAS: PROFICIENCYVALUES!$B$19
Name SkillIncrease: PROFICIENCYVALUES!$B$8
Name SpellSlotS10: PROFICIENCYVALUES!$B$14
Name CantripSlot: PROFICIENCYVALUES!$B$11
Name SpellLearned: PROFICIENCYVALUES!$B$12
Name WeaponGWS: PROFICIENCYVALUES!$B$18
Name CLASSPROFILENAMES: CLASSPROFILES!$B$1:$G$1

Sheet Table of Contents and Version N
A2: BALANCED CORE SYSTEM
A3: https://www.reddit.com/r/OpenBCS/ | C3: Author: Lazarus Dark
A5: TABLE OF CONTENTS:
A6: Sheet Name/Link | C6: Sheet description
A7: PROFICIENCYVALUES | C7: These are the base point values of the BCS and some basic information, includes defined ranges to use in formulas throughout this document.
A8: CLASSPROFILES | C8: This is where class profile information is stored, it may be tweaked over time, these profiles are not set in stone but should also be very good starter points.
A9: CLASSDATA | C9: This is where the official classes are broken down into their point values.
A10: CLASSTOTALS | C10: Using filters, this sheet makes it easier to compare the values of the official classes (and even compare them to your custom class). DO NOT EDIT THIS SHEET. Only change values on the CLASSDATA sheet to see changes here.
A11: SPECIALCLASSDATA | C11: A sheet for random class data just for reference, such as class archetype values and eidolon proficiencies.
A12: Class-Archetype Values | C12: This sheet shows the breakdown where the class archetype values were derived for SPECIALCLASSDATA sheet.
A13: MinMax for Profiles-Design Guides | C13: This data was used to help create the Profile system and also includes various class design guidelines based on research and analysis.
A14: Profile Analysis | C14: This is a different way to look at the classtotals. Incomplete.
A15: Save Analysis | C15: Used to evaluate save progression across classes in detail.
A16: Original Save Analysis | C16: The original save evaluation, in a more condensed format which is still good for comparing saves in a different way.
A17: Original Classes Compared | C17: The earliest version of the BCS for comparing class abilities and proficiencies. It can still be useful for comparing classes in a different way.
A18: old CLASSTOTALS | C18: An earlier version of CLASSTOTALS, arranged a little differently, some may prefer this arrangement so it is left here for that reason.
A19: Ancestries (Incomplete) | B19: Incomplete | C19: Work-In-Progress: The BCS isn't just about Classes, its about all the core values. I have a "Core Theory" that a characters stats, including Ancestry, all make up one total character value. So it is necessary to evaluate the cost of an ancestry.
A20: DualClass Calculator | B20: (originally paid-only, now free!) | C20: This will allow you to see the total value of a dual class according to normal dual classing rules. You can also use this to calculate a dual class closer to 2100, though its almost impossible to get to 2100 for a dual class, at that point you are likely making more of a class-archetype than a dual class.
A21: Class Creator for mobile users | B21: Full functionality only available to BCSF Purchasers | C21: The BCS Class Creator form is very advanced and most mobile pdf readers do not support its many functions, therefore this sheet is provided for use on mobile devices that cannot use the form pdf. (The Chrome/Chrome OS pdf viewer supports all form features in testing except page three of the form, only Acrobat reader/pro on desktop supported all page three functions in testing).
A22: Experiments with Class-Archetypes | B22: Full functionality only available to BCSF Purchasers | C22: Experiment tabs are just that, experiments in using the BCS to create new things. This tab is all about creating a Class-Archetypes. It should not be taken as the only way or the right way, just an experiment in what might be one way.
A23: Levels 21-30 (alpha state) | B23: Full functionality only available to BCSF Purchasers | C23: This is only the beginning of trying to make "balanced" levels over 20. I don't want to go too far on this until the community has vetted some of the BCS, but this starter page uses the same principles already established in the BCS.
A24: Open Game License (OGL) | C24: OGL info for this entire document
A30: version | B30: final release date | C30: release notes
A31: 1 | B31: 44708 | C31: Initial public release.
A32: 1.1 | B32: 44772 | C32: made some notes, added CS to a couple classes where missing and rebalanced (they balanced better than before obviously)
A33: 1.2 | B33: 44781 | C33: decoded Psychic/Thaumaturge, update OGL for DA
A34: 1.3 | B34: 45137 | C34: added Kineticist Playtest and updated OGL for Playtest (which required a BCS version change) - added CRB 4th printing errata, especially for Alchemist and Clerics
A35: 1.4 | B35: in progress | C35: decoded final Kineticist, update OGL for RoE
A39: Glossary and terminology
A40: SPL# or S## | C40: Spell Slot level # (named spells use the format: [Spellname] Spell #) (C=Cantrip)
A41: LVL# or L## | C41: Character level
A42: ALC# | C42: Alchemy Level
A43: "Level n" vs "nth-Level" | C43: Character levels should be "Level 1 feature, Level 2 feat, etc" and spell levels should be "1st-Level slot, 2nd-Level cantrip, etc." This helps avoid confustion between character levels and spell levels.
A44: class-archetype | C44: using a hyphen helps distinguish "class-archetypes" from "archetypes for classes"
A45: "published classes" | C45: this refers to the classes which are broken down here which were used to reverse engineer the BCS values

Sheet PROFICIENCYVALUES
A1: PROFICIENCY | B1: VALUE OF PROF. | C1: CHANGING THESE VALUES WILL MAKE CHANGES ACROSS MANY TABS AND FORMULAS.
A2: Untrained | B2: 0
A3: Trained | B3: 10 | C3: For Advanced Weapons (group or full), they always stay one proficiency behind Unarmed/Simple/Martial. So, if you start at Trained in Advanced Full, you MUST start at Expert in Unarmed/Simple/Martial and pay the Expert cost. If you start at Trained in Advanced Group, you MUST start at Expert in Simple Limited/Martial Limited and pay the Expert cost. (Its possible that a custom class could get Unarmed Limited group proficiency for the Brawling Group, but that would be a very rare and specific class)
A4: Expert | B4: 50
A5: Master | B5: 110
A6: Legendary | B6: 190
A7: HP | B7: 10
A8: SkillIncrease | B8: 5
A9: SkillFeat | B9: 5
A10: CantripLearned | B10: 5
A11: CantripSlot | B11: 5
A12: SpellLearned | B12: 10
A13: SpellSlot | B13: 10
A14: SpellSlotS10 | B14: 190
A15: AlchemicalFormula | B15: 5
... A19: ArmorAS | B19: 50
A23: CLASSES | C23: CLASS | D23: KEYSCORE | E23: PROFILETYPE
A24: Champion | B24: 1 | C24: Champion | D24: {=INDEX(ALLCLASSDATA,MATCH("KEYABILITY",CLASSFEATUREHEADERS,0),MATCH(C24,CLASSNAMEHEADERS,0))} -> STR/DEX | E24: {=INDEX(ALLCLASSDATA,MATCH("ClassType",CLASSFEATUREHEADERS,0),MATCH(C24,CLASSNAMEHEADERS,0))} -> Soldier
A25: Monk | B25: 2 | C25: Monk | D25: {=INDEX(ALLCLASSDATA,MATCH("KEYABILITY",CLASSFEATUREHEADERS,0),MATCH(C25,CLASSNAMEHEADERS,0))} -> STR/DEX | E25: {=INDEX(ALLCLASSDATA,MATCH("ClassType",CLASSFEATUREHEADERS,0),MATCH(C25,CLASSNAMEHEADERS,0))} -> Skirmisher
A26: Fighter | B26: 3 | C26: Fighter | D26: {=INDEX(ALLCLASSDATA,MATCH("KEYABILITY",CLASSFEATUREHEADERS,0),MATCH(C26,CLASSNAMEHEADERS,0))} -> STR/DEX | E26: {=INDEX(ALLCLASSDATA,MATCH("ClassType",CLASSFEATUREHEADERS,0),MATCH(C26,CLASSNAMEHEADERS,0))} -> Soldier
A27: Barbarian | B27: 4 | C27: Barbarian | D27: {=INDEX(ALLCLASSDATA,MATCH("KEYABILITY",CLASSFEATUREHEADERS,0),MATCH(C27,CLASSNAMEHEADERS,0))} -> STR | E27: {=INDEX(ALLCLASSDATA,MATCH("ClassType",CLASSFEATUREHEADERS,0),MATCH(C27,CLASSNAMEHEADERS,0))} -> Brute
A28: Ranger | B28: 5 | C28: Ranger | D28: {=INDEX(ALLCLASSDATA,MATCH("KEYABILITY",CLASSFEATUREHEADERS,0),MATCH(C28,CLASSNAMEHEADERS,0))} -> STR/DEX | E28: {=INDEX(ALLCLASSDATA,MATCH("ClassType",CLASSFEATUREHEADERS,0),MATCH(C28,CLASSNAMEHEADERS,0))} -> Sniper
A29: Rogue | B29: 6 | C29: Rogue | D29: {=INDEX(ALLCLASSDATA,MATCH("KEYABILITY",CLASSFEATUREHEADERS,0),MATCH(C29,CLASSNAMEHEADERS,0))} -> DEX* | E29: {=INDEX(ALLCLASSDATA,MATCH("ClassType",CLASSFEATUREHEADERS,0),MATCH(C29,CLASSNAMEHEADERS,0))} -> Skill Paragon
A30: Investigator | B30: 7 | C30: Investigator | D30: {=INDEX(ALLCLASSDATA,MATCH("KEYABILITY",CLASSFEATUREHEADERS,0),MATCH(C30,CLASSNAMEHEADERS,0))} -> INT | E30: {=INDEX(ALLCLASSDATA,MATCH("ClassType",CLASSFEATUREHEADERS,0),MATCH(C30,CLASSNAMEHEADERS,0))} -> Skirmisher
A31: Thaumaturge | B31: 8 | C31: Thaumaturge | D31: {=INDEX(ALLCLASSDATA,MATCH("KEYABILITY",CLASSFEATUREHEADERS,0),MATCH(C31,CLASSNAMEHEADERS,0))} -> CHA | E31: {=INDEX(ALLCLASSDATA,MATCH("ClassType",CLASSFEATUREHEADERS,0),MATCH(C31,CLASSNAMEHEADERS,0))} -> Skill Paragon
A32: Swashbuckler | B32: 9 | C32: Swashbuckler | D32: {=INDEX(ALLCLASSDATA,MATCH("KEYABILITY",CLASSFEATUREHEADERS,0),MATCH(C32,CLASSNAMEHEADERS,0))} -> DEX | E32: {=INDEX(ALLCLASSDATA,MATCH("ClassType",CLASSFEATUREHEADERS,0),MATCH(C32,CLASSNAMEHEADERS,0))} -> Skill Paragon
A33: Gunslinger | B33: 10 | C33: Gunslinger | D33: {=INDEX(ALLCLASSDATA,MATCH("KEYABILITY",CLASSFEATUREHEADERS,0),MATCH(C33,CLASSNAMEHEADERS,0))} -> DEX | E33: {=INDEX(ALLCLASSDATA,MATCH("ClassType",CLASSFEATUREHEADERS,0),MATCH(C33,CLASSNAMEHEADERS,0))} -> Sniper
A34: Inventor | B34: 11 | C34: Inventor | D34: {=INDEX(ALLCLASSDATA,MATCH("KEYABILITY",CLASSFEATUREHEADERS,0),MATCH(C34,CLASSNAMEHEADERS,0))} -> INT | E34: {=INDEX(ALLCLASSDATA,MATCH("ClassType",CLASSFEATUREHEADERS,0),MATCH(C34,CLASSNAMEHEADERS,0))} -> Brute
A35: Alchemist | B35: 12 | C35: Alchemist | D35: {=INDEX(ALLCLASSDATA,MATCH("KEYABILITY",CLASSFEATUREHEADERS,0),MATCH(C35,CLASSNAMEHEADERS,0))} -> INT | E35: {=INDEX(ALLCLASSDATA,MATCH("ClassType",CLASSFEATUREHEADERS,0),MATCH(C35,CLASSNAMEHEADERS,0))} -> Brute
... A47: ptKineticist | B47: 24 | C47: ptKineticist | D47: {=INDEX(ALLCLASSDATA,MATCH("KEYABILITY",CLASSFEATUREHEADERS,0),MATCH(C47,CLASSNAMEHEADERS,0))} -> #N/A | E47: {=INDEX(ALLCLASSDATA,MATCH("ClassType",CLASSFEATUREHEADERS,0),MATCH(C47,CLASSNAMEHEADERS,0))} -> #N/A
A50: ClassProfiles:
A51: Martial
A52: Martial-Skilled
A53: Martial-Specialist
A54: Martial-Caster
A55: Caster-Specialist
A56: Caster
A58: Weapon Groups
A59: Axe
A60: Bomb
A61: Bow
A62: Brawling
... A105: FOCUS SPELL NAMES
A106: Classes with Focus Spells | B106: FOCUS SPELL NAMES | C106: FOCUS CANTRIP NAMES
A107: Bard | B107: "Composition Spells" | C107: "Composition Cantrips"
A108: Champion | B108: "Devotion Spells"
A109: Druid | B109: "Order Spells"
A110: Magus | B110: "Conflux Spells"
A111: Monk | B111: "Ki Spells"
A112: Oracle | B112: "Revelation Spells"
A113: Ranger | B113: "Warden Spells"
A114: Sorcerer | B114: "Bloodline Spells"
A115: Summoner | B115: "Link Spells" | C115: "Link Cantrips"
A116: Witch | B116: "Hex Spells" | C116: "Hex Cantrips"
A117: Wizard | B117: "School Spells"
A119: BASIC PROFICIENCY FEATURE NAMES AND DESCRIPTIONS
A120: Class Proficiency Increase | B120: Feature Name (occasionally varies) | C120: Feature Description (generic, sometimes varies)
A121: Perception Expert | B121: Alertness | C121: You remain alert to threats around you. Your proficiency rank for Perception increases to expert.
A122: Perception Master | B122: Vigilant Senses | C122: Through your adventures, you’ve developed keen awareness and attention to detail. Your proficiency rank for Perception increases to master.
A123: Perception Legendary | B123: Incredible Senses | C123: You notice things that are almost impossible for an ordinary person to detect. Your proficiency rank for Perception increases to legendary.
A124: Fortitude Expert | B124: Great Fortitude | C124: Your physique is incredibly hardy. Your proficiency rank for Fortitude saves increases to expert.
A125: Fortitude Master | B125: Juggernaut | C125: Your body has become accustomed to physical hazards and resistant to ailments. Your proficiency rank for Fortitude saves increases to master. When you roll a success on a Fortitude save, you get a critical success instead.
A126: Fortitude Legendary | B126: Greater Juggernaut | C126: You have a stalwart physiology. Your proficiency rank for Fortitude saves increases to legendary. When you roll a critical failure on a Fortitude save, you get a failure instead. When you roll a failure on a Fortitude save against an effect that deals damage, you halve the damage you take.
A127: Reflex Expert | B127: Lightning Reflexes | C127: Your reflexes are lightning fast. Your proficiency rank for Reflex saves increases to expert.
A128: Reflex Master | B128: Evasion | C128: You've learned to move quickly to avoid explosions, dragon's breath, and worse. Your proficiency rank for Reflex saves increases to master. When you roll a success on a Reflex save, you get a critical success instead.
A129: Reflex Legendary | B129: Improved Evasion | C129: Your ability to elude danger is matchless. Your proficiency rank for Reflex saves increases to legendary. When you roll a critical failure on a Reflex save, you get a failure instead. When you roll a failure on a Reflex save against a damaging effect, you take half damage.
A130: Will Expert | B130: Iron Will | C130: Your mental defenses are an iron fortress. Your proficiency rank for Will saves increases to expert.
A131: Will Master | B131: Resolve | C131: You've steeled your mind with resolve. Your proficiency rank for Will saves increases to master. When you roll a success on a Will save, you get a critical success instead.
... A141: Attack Legendary | B141: Weapon Legend | C141: [probably should be considered a Fighter exclusive feature]
A142: Critical Specialization: add to Weapon Expertise | C142: [add to Weapon Expertise description:] [must be customized to each class since its always specifically limited]
A143: Weapon Specialization | C143: You’ve learned how to inflict greater injuries with the weapons you know best. You deal 2 additional damage with weapons and unarmed attacks in which you are an expert. This damage increases to 3 if you’re a master, and 4 if you’re legendary.
A144: Greater Weapon Specialization | C144: Your damage from weapon specialization increases to 4 with weapons and unarmed attacks in which you’re an expert, 6 if you’re a master, and 8 if you’re legendary.
A145: Defense Expert | B145: Armor Expertise | C145: You’ve learned how to dodge while wearing [light/medium/heavy or] no armor. Your proficiency ranks for [armor types and] unarmored defense increase to expert.
A146: Armor Specialization: add this to Armor Expertise: | B146: Armor Specialization | C146: [add to Armor Expertise description:] You gain the armor specialization effects of medium and heavy armor.
A147: Defense Master | B147: Armor Mastery | C147: Your skill with [armor/unarmored defense] improves, increasing your ability to dodge blows. Your proficiency ranks for [armor types and] unarmored defense increase to master.
A148: Defense Legendary | B148: Armor Legend | C148: Your skill while [unarmored/wearing armor] is unmatched. Your proficiency ranks for [armor types and] unarmored defense increase to legendary.
A149: Shield Block as an initial class feature | B149: Shield Block | C149: You gain the Shield Block general feat, a reaction that lets you reduce damage with your shield.
A150: Skill increases at even levels: | B150: Skillful Increases | C150: You gain more skill increases than other classes. At 2nd level and every level thereafter, you gain a skill increase.
A151: Skill feats at odd levels: | B151: Skillful Feats | C151: You gain skill feats more often than others. At 1st level and every level thereafter, you gain a skill feat.
B158: new, based on Gunslinger:
A159: Weapon Adept (initial class feature) | B159: Weapon Adept Expertise | C159: Your focus on [weapon or weapon group] allows you to start with expert in that weapon [group and trained in advanced weapons in that group]. All other weapons must be one proficiency behind your focus weapon [group] even if you gain an ability that would increase your proficiency in one or more other weapons.
A160: Weapon Adept: replace Weapon Expertise: | B160: Weapon Adept Mastery | C160: Your prowess with your focus weapon[s] increases. Your proficiency rank increases to master with [weapon adept weapon or group]. Your proficiency for [advanced weapons in your weapon adept group] and simple and martial weapons and unarmed attacks increases to expert. [recommended: "You gain access to the critical specialization effects for [weapon or weapon group]"].
A161: Weapon Adept: replace Weapon Mastery: | B161: Weapon Adept Legend | C161: Your skill is unmatched with [weapon or weapon group]. Your proficiency rank increases to legendary with [simple and martial] [weapon adept weapon or group]. Your proficiency for [advanced weapons in your weapon adept group and] simple and martial weapons and unarmed attacks increases to master.
B162: new, based on Inventor crafting built in proficiency:
A163: Core Skill: level 3 feature | B163: Core Skill | C163: [SkillName] is your core granted skill. Your proficiency in [SkillName] increases to expert. At level 7 your proficiency automatically increases to master and at level 15 your proficiency automatically increases to legendary.
A164: Core Skill Feats: add to Core Skill | C164: [add to Core Skill description:] You also gain an extra skill feat at level 3, level 7, and level 15 for your core skill.

Sheet CLASSPROFILES
B1: Martial | C1: Martial-Skilled | D1: Martial-Specialist | E1: Martial-Caster | F1: Caster-Specialist | G1: Caster
A2: HP | B2: 10 (max 12) | C2: 8 (max 10) | D2: 8 (max 10) | E2: 8 (max 10) | F2: 8 HP | G2: 6 HP
A3: PerceptionExpert | B3: L11 | C3: L01 | D3: L13 | E3: L09 | F3: L11 | G3: L11
A4: PerceptionMaster | C4: L07
A5: PerceptionLegendary | C5: L13
A6: FortitudeExpert | B6: L01 | C6: L09 | D6: L01 | E6: L01 | F6: L09 | G6: L09
A7: FortitudeMaster | B7: L09 | D7: L17 | E7: L15
A8: FortitudeLegendary
A9: ReflexExpert | B9: L09 | C9: L01 | D9: L07 | E9: L11 | F9: L13 | G9: L09
A10: ReflexMaster | C10: L07
A11: ReflexLegendary | C11: L13
A12: WillExpert | B12: L03 | C12: L03 | D12: L07 | E12: L01 | F12: L01 | G12: L01
A13: WillMaster | E13: L15 | F13: L11 | G13: L17
A14: WillLegendary
A15: WeaponRecommendation | B15: Martial | C15: Martial | D15: Martial | E15: Martial | F15: Simple | G15: Simple
A16: WeaponExpert | B16: L05 | C16: L05 | D16: L05 | E16: L05 | F16: L11 | G16: L11
A17: WeaponMaster | B17: L13 | C17: L13 | D17: L13 | E17: L13
A18: WeaponLegendary
A19: ArmorRecommendation | B19: Medium | C19: Light | D19: Light | E19: Medium | F19: Light | G19: Unarmored
A20: ArmorExpert | B20: L13 | C20: L13 | D20: L13 | E20: L11 | F20: L13 | G20: L13
A21: ArmorMaster | B21: L19 | C21: L19 | D21: L19 | E21: L17
A22: ArmorLegendary
A23: DCExpert | B23: L09 | C23: L09 | D23: L09 | E23: L09 | F23: L07 | G23: L07
A24: DCMaster | B24: L17 | C24: L17 | D24: L17 | E24: L17 | F24: L15 | G24: L15
A25: DCLegendary | F25: L19 | G25: L19
A28: Profiles are not rigid, they are more like suggestions. They are not part of the reverse engineered published classes, but something created and layered on top in order to help categorize classes (very loosely) and to make new class creation streamlined by simply selecting a profile to get your new class started without having to figure out every proficiency before you begin designing a class.
A29: Profiles were determined through analysis on the ProfileAnalysis tab. Mostly by grouping HP, proficiencies and class commonalities
A30: • MARTIAL: Standard martial classes usually start with 10 HP (all other profiles except Caster start with 8 HP) and are largely focused on high damage attacks and occasionally high defenses.
A31: • MARTIAL-SKILLED: The skilled martials often have Legendary Perception and Reflex in addition to extra skill increases or skill feats.
A32: • MARTIAL-SPECIALIST: These tend to specialize in one particular area such as one type of weapon or one type of fighting style.
A33: • MARTIAL-CASTER: These hybrid martials and casters have bounded casting and usually have more Attack proficiency and/or Defense proficiency than full casters.
A34: • CASTER-SPECIALIST: These full casters have a little more variance in their theme or abilities beyond just casting spells.
A35: • CASTER: Standard full casters have 6 HP and are more directly focused on being a powerful caster of spells.

Sheet CLASSDATA
A1: WARNING, DON'T CHANGE ANYTHING OTHER THAN POINT VALUES! DON'T RENAME COLUMN OR ROW HEADERS, YOU WILL BREAK EVERYTHING! | P1: colorcode: | T1: reasonable but not totally certain | X1: blue is total guess, needs verifying | AB1: yellow is questionable | AG1: Errata | AS1: currently working on some new balancing concepts, so Druid numbers are a little off right now
D2: CLASS | E2: PTS | F2: CLASS | G2: PTS | H2: CLASS | I2: PTS | J2: CLASS | K2: PTS | L2: CLASS | M2: PTS | N2: CLASS | O2: PTS | P2: CLASS | Q2: PTS | R2: CLASS | S2: PTS | T2: CLASS | U2: PTS | V2: CLASS | W2: PTS | X2: CLASS | Y2: PTS | Z2: CLASS | AA2: PTS | AB2: CLASS | AC2: PTS | AD2: CLASS | AE2: PTS | AF2: CLASS | AG2: PTS | AH2: CLASS | AI2: PTS | AJ2: CLASS | AK2: PTS | AL2: CLASS | AM2: PTS | AN2: CLASS | AO2: PTS | AP2: CLASS | AQ2: PTS | AR2: CLASS | AS2: PTS | AT2: CLASS | AU2: PTS | AV2: CLASS | AW2: PTS | AX2: CLASS | AY2: PTS | AZ2: CLASS | BA2: PTS
A3: CLASS----> | B3: LVL | C3: SPL | D3: TESTCLASS | E3: TESTPOINTS | F3: Champion | G3: ChampionPoints | H3: Monk | I3: MonkPoints | J3: Fighter | K3: FighterPoints | L3: Barbarian | M3: BarbarianPoints | N3: Ranger | O3: RangerPoints | P3: Rogue | Q3: RoguePoints | R3: Investigator | S3: InvestigatorPoints | T3: Thaumaturge | U3: ThaumaturgePoints | V3: Swashbuckler | W3: SwashbucklerPoints | X3: Gunslinger | Y3: GunslingerPoints | Z3: Inventor | AA3: InventorPoints | AB3: Alchemist | AC3: AlchemistPoints | AD3: Kineticist | AE3: KineticistPoints | AF3: Summoner | AG3: SummonerPoints | AH3: Magus | AI3: MagusPoints | AJ3: Cleric Warpriest | AK3: Cleric WarpriestPoints | AL3: Cleric Cloistered | AM3: Cleric CloisteredPoints | AN3: Bard | AO3: BardPoints | AP3: Oracle | AQ3: OraclePoints | AR3: Druid | AS3: DruidPoints | AT3: Psychic | AU3: PsychicPoints | AV3: Wizard | AW3: WizardPoints | AX3: Witch | AY3: WitchPoints | AZ3: Sorcerer | BA3: SorcererPoints
A4: BALANCETOTAL: | E4: =SUM(E5:E11)+E12+E21+E39+E26+E101+E133+E151+E154+E175+E196+E203+E250 -> 6870 | G4: =SUM(G5:G11)+G12+G21+G39+G26+G101+G133+G151+G154+G175+G196+G203+G250 -> 2100 | I4: =SUM(I5:I11)+I12+I21+I39+I26+I101+I133+I151+I154+I175+I196+I203+I250 -> 2100 | K4: =SUM(K5:K11)+K12+K21+K39+K26+K101+K133+K151+K154+K175+K196+K203+K250 -> 2100 | M4: =SUM(M5:M11)+M12+M21+M39+M26+M101+M133+M151+M154+M175+M196+M203+M250 -> 2100 | O4: =SUM(O5:O11)+O12+O21+O39+O26+O101+O133+O151+O154+O175+O196+O203+O250 -> 2100 | Q4: =SUM(Q5:Q11)+Q12+Q21+Q39+Q26+Q101+Q133+Q151+Q154+Q175+Q196+Q203+Q250 -> 2100 | S4: =SUM(S5:S11)+S12+S21+S39+S26+S101+S133+S151+S154+S175+S196+S203+S250 -> 2100 | U4: =SUM(U5:U11)+U12+U21+U39+U26+U101+U133+U151+U154+U175+U196+U203+U250 -> 2100 | W4: =SUM(W5:W11)+W12+W21+W39+W26+W101+W133+W151+W154+W175+W196+W203+W250 -> 2100 | Y4: =SUM(Y5:Y11)+Y12+Y21+Y39+Y26+Y101+Y133+Y151+Y154+Y175+Y196+Y203+Y250 -> 2100 | AA4: =SUM(AA5:AA11)+AA12+AA21+AA39+AA26+AA101+AA133+AA151+AA154+AA175+AA196+AA203+AA250 -> 2100 | AC4: =SUM(AC5:AC11)+AC12+AC21+AC39+AC26+AC101+AC133+AC151+AC154+AC175+AC196+AC203+AC250 -> 2100 | AE4: =SUM(AE5:AE11)+AE12+AE21+AE39+AE26+AE101+AE133+AE151+AE154+AE175+AE196+AE203+AE250 -> 2100 | AG4: =SUM(AG5:AG11)+AG12+AG21+AG39+AG26+AG101+AG133+AG151+AG154+AG175+AG196+AG203+AG250 -> 2100 | AI4: =SUM(AI5:AI11)+AI12+AI21+AI39+AI26+AI101+AI133+AI151+AI154+AI175+AI196+AI203+AI250 -> 2100 | AK4: =SUM(AK5:AK11)+AK12+AK21+AK39+AK26+AK101+AK133+AK151+AK154+AK175+AK196+AK203+AK250 -> 2050 | AM4: =SUM(AM5:AM11)+AM12+AM21+AM39+AM26+AM101+AM133+AM151+AM154+AM175+AM196+AM203+AM250 -> 2100 | AO4: =SUM(AO5:AO11)+AO12+AO21+AO39+AO26+AO101+AO133+AO151+AO154+AO175+AO196+AO203+AO250 -> 2100 | AQ4: =SUM(AQ5:AQ11)+AQ12+AQ21+AQ39+AQ26+AQ101+AQ133+AQ151+AQ154+AQ175+AQ196+AQ203+AQ250 -> 2100 | AS4: =SUM(AS5:AS11)+AS12+AS21+AS39+AS26+AS101+AS133+AS151+AS154+AS175+AS196+AS203+AS250 -> 2080 | AU4: =SUM(AU5:AU11)+AU12+AU21+AU39+AU26+AU101+AU133+AU151+AU154+AU175+AU196+AU203+AU250 -> 2100 | AW4: =SUM(AW5:AW11)+AW12+AW21+AW39+AW26+AW101+AW133+AW151+AW154+AW175+AW196+AW203+AW250 -> 2100 | AY4: =SUM(AY5:AY11)+AY12+AY21+AY39+AY26+AY101+AY133+AY151+AY154+AY175+AY196+AY203+AY250 -> 2100 | BA4: =SUM(BA5:BA11)+BA12+BA21+BA39+BA26+BA101+BA133+BA151+BA154+BA175+BA196+BA203+BA250 -> 2100
A5: ClassType | B5: L00 | D5: Martial | F5: Soldier | H5: Skirmisher | J5: Soldier | L5: Brute | N5: Sniper | P5: Skill Paragon | R5: Skirmisher | T5: Skill Paragon | V5: Skill Paragon | X5: Sniper | Z5: Brute | AB5: Brute | AD5: Brute | AF5: Magical Striker | AH5: Magical Striker | AJ5: Magical Striker | AL5: Spellcaster | AN5: Spellcaster | AP5: Spellcaster | AR5: Spellcaster | AT5: Spellcaster | AV5: Spellcaster | AX5: Spellcaster | AZ5: Spellcaster
A6: KEYABILITY | B6: L00 | D6: STR | F6: STR/DEX | H6: STR/DEX | J6: STR/DEX | L6: STR | N6: STR/DEX | P6: DEX* | R6: INT | T6: CHA | V6: DEX | X6: DEX | Z6: INT | AB6: INT | AD6: CON | AF6: CHA | AH6: STR/DEX | AJ6: WIS | AL6: WIS | AN6: CHA | AP6: CHA | AR6: WIS | AT6: INT/CHA | AV6: INT | AX6: INT | AZ6: CHA
A7: HP | B7: L00 | D7: 6 | E7: =HPvalue*D7 -> 60 | F7: 10 | G7: =HPvalue*F7 -> 100 | H7: 10 | I7: =HPvalue*H7 -> 100 | J7: 10 | K7: =HPvalue*J7 -> 100 | L7: 12 | M7: =HPvalue*L7 -> 120 | N7: 10 | O7: =HPvalue*N7 -> 100 | P7: 8 | Q7: =HPvalue*P7 -> 80 | R7: 8 | S7: =HPvalue*R7 -> 80 | T7: 8 | U7: =HPvalue*T7 -> 80 | V7: 10 | W7: =HPvalue*V7 -> 100 | X7: 8 | Y7: =HPvalue*X7 -> 80 | Z7: 8 | AA7: =HPvalue*Z7 -> 80 | AB7: 8 | AC7: =HPvalue*AB7 -> 80 | AD7: 8 | AE7: =HPvalue*AD7 -> 80 | AF7: 10 | AG7: =HPvalue*AF7 -> 100 | AH7: 8 | AI7: =HPvalue*AH7 -> 80 | AJ7: 8 | AK7: =HPvalue*AJ7 -> 80 | AL7: 8 | AM7: =HPvalue*AL7 -> 80 | AN7: 8 | AO7: =HPvalue*AN7 -> 80 | AP7: 8 | AQ7: =HPvalue*AP7 -> 80 | AR7: 8 | AS7: =HPvalue*AR7 -> 80 | AT7: 6 | AU7: =HPvalue*AT7 -> 60 | AV7: 6 | AW7: =HPvalue*AV7 -> 60 | AX7: 6 | AY7: =HPvalue*AX7 -> 60 | AZ7: 6 | BA7: =HPvalue*AZ7 -> 60
A8: ClassFeatL01 | B8: L01 | D8: TRUE | E8: =If(D8=True,10,"") -> 10 | F8: TRUE | G8: =If(F8=True,10,"") -> 10 | H8: TRUE | I8: =If(H8=True,10,"") -> 10 | J8: TRUE | K8: =If(J8=True,10,"") -> 10 | L8: TRUE | M8: =If(L8=True,10,"") -> 10 | N8: TRUE | O8: =If(N8=True,10,"") -> 10 | P8: TRUE | Q8: =If(P8=True,10,"") -> 10 | R8: TRUE | S8: =If(R8=True,10,"") -> 10 | T8: TRUE | U8: =If(T8=True,10,"") -> 10 | V8: TRUE | W8: =If(V8=True,10,"") -> 10 | X8: TRUE | Y8: =If(X8=True,10,"") -> 10 | Z8: TRUE | AA8: =If(Z8=True,10,"") -> 10 | AB8: TRUE | AC8: =If(AB8=True,10,"") -> 10 | AD8: TRUE | AE8: =If(AD8=True,10,"") -> 10 | AF8: FALSE | AG8: =If(AF8=True,10,"") | AH8: FALSE | AI8: =If(AH8=True,10,"") | AJ8: FALSE | AK8: =If(AJ8=True,10,"") | AL8: TRUE | AM8: =If(AL8=True,10,"") -> 10 | AN8: TRUE | AO8: =If(AN8=True,10,"") -> 10 | AP8: FALSE | AQ8: =If(AP8=True,10,"") | AR8: TRUE | AS8: =If(AR8=True,10,"") -> 10 | AT8: FALSE | AU8: =If(AT8=True,10,"") | AV8: FALSE | AW8: =If(AV8=True,10,"") | AX8: FALSE | AY8: =If(AX8=True,10,"") | AZ8: FALSE | BA8: =If(AZ8=True,10,"")
A9: ShieldBlockL01 | B9: L01 | D9: TRUE | E9: =If(D9=True,10,"") -> 10 | F9: TRUE | G9: =If(F9=True,10,"") -> 10 | H9: FALSE | I9: =If(H9=True,10,"") | J9: TRUE | K9: =If(J9=True,10,"") -> 10 | L9: FALSE | M9: =If(L9=True,10,"") | N9: FALSE | O9: =If(N9=True,10,"") | P9: FALSE | Q9: =If(P9=True,10,"") | R9: FALSE | S9: =If(R9=True,10,"") | T9: FALSE | U9: =If(T9=True,10,"") | V9: FALSE | W9: =If(V9=True,10,"") | X9: FALSE | Y9: =If(X9=True,10,"") | Z9: TRUE | AA9: =If(Z9=True,10,"") -> 10 | AB9: FALSE | AC9: =If(AB9=True,10,"") | AD9: FALSE | AE9: =If(AD9=True,10,"") | AF9: FALSE | AG9: =If(AF9=True,10,"") | AH9: FALSE | AI9: =If(AH9=True,10,"") | AJ9: TRUE | AK9: =If(AJ9=True,10,"") -> 10 | AL9: FALSE | AM9: =If(AL9=True,10,"") | AN9: FALSE | AO9: =If(AN9=True,10,"") | AP9: FALSE | AQ9: =If(AP9=True,10,"") | AR9: TRUE | AS9: =If(AR9=True,10,"") -> 10 | AT9: FALSE | AU9: =If(AT9=True,10,"") | AV9: FALSE | AW9: =If(AV9=True,10,"") | AX9: FALSE | AY9: =If(AX9=True,10,"") | AZ9: FALSE | BA9: =If(AZ9=True,10,"")
A10: CasterType | AB10: Alchemy | AF10: Bounded Spontaneous | AH10: Bounded Prepared | AJ10: Prepared | AL10: Prepared | AN10: Spontaneous | AP10: Spontaneous | AR10: Prepared | AT10: Spontaneous | AV10: Prepared | AX10: Prepared | AZ10: Spontaneous
A11: SpellList | AF11: Subclass List | AH11: Arcane | AJ11: Divine (Full List) | AL11: Divine (Full List) | AN11: Occult | AP11: Divine | AR11: Primal (Full List) | AT11: Occult | AV11: Arcane | AX11: Subclass List | AZ11: Subclass List
A12: DC TOTAL: | E12: =sum(E13:E20) -> 720 | G12: =sum(G13:G20) -> 170 | I12: =sum(I13:I20) -> 170 | K12: =sum(K13:K20) -> 170 | M12: =sum(M13:M20) -> 170 | O12: =sum(O13:O20) -> 170 | Q12: =sum(Q13:Q20) -> 170 | S12: =sum(S13:S20) -> 170 | U12: =sum(U13:U20) -> 170 | W12: =sum(W13:W20) -> 170 | Y12: =sum(Y13:Y20) -> 170 | AA12: =sum(AA13:AA20) -> 170 | AC12: =sum(AC13:AC20) -> 170 | AE12: =sum(AE13:AE20) -> 360 | AG12: =sum(AG13:AG20) -> 170 | AI12: =sum(AI13:AI20) -> 170 | AK12: =sum(AK13:AK20) -> 170 | AM12: =sum(AM13:AM20) -> 360 | AO12: =sum(AO13:AO20) -> 360 | AQ12: =sum(AQ13:AQ20) -> 360 | AS12: =sum(AS13:AS20) -> 360 | AU12: =sum(AU13:AU20) -> 360 | AW12: =sum(AW13:AW20) -> 360 | AY12: =sum(AY13:AY20) -> 360 | BA12: =sum(BA13:BA20) -> 360
A13: ClassDCTrained | D13: 01 | E13: =IF((ISBLANK(D13)),"",Trained) -> 10 | F13: 01 | G13: =IF((ISBLANK(F13)),"",Trained) -> 10 | H13: 01 | I13: =IF((ISBLANK(H13)),"",Trained) -> 10 | J13: 01 | K13: =IF((ISBLANK(J13)),"",Trained) -> 10 | L13: 01 | M13: =IF((ISBLANK(L13)),"",Trained) -> 10 | N13: 01 | O13: =IF((ISBLANK(N13)),"",Trained) -> 10 | P13: 01 | Q13: =IF((ISBLANK(P13)),"",Trained) -> 10 | R13: 01 | S13: =IF((ISBLANK(R13)),"",Trained) -> 10 | T13: 01 | U13: =IF((ISBLANK(T13)),"",Trained) -> 10 | V13: 01 | W13: =IF((ISBLANK(V13)),"",Trained) -> 10 | X13: 01 | Y13: =IF((ISBLANK(X13)),"",Trained) -> 10 | Z13: 01 | AA13: =IF((ISBLANK(Z13)),"",Trained) -> 10 | AB13: 01 | AC13: =IF((ISBLANK(AB13)),"",Trained) -> 10 | AD13: 01 | AE13: =IF((ISBLANK(AD13)),"",Trained) -> 10 | AG13: =IF((ISBLANK(AF13)),"",Trained) | AI13: =IF((ISBLANK(AH13)),"",Trained) | AK13: =IF((ISBLANK(AJ13)),"",Trained) | AM13: =IF((ISBLANK(AL13)),"",Trained) | AO13: =IF((ISBLANK(AN13)),"",Trained) | AQ13: =IF((ISBLANK(AP13)),"",Trained) | AS13: =IF((ISBLANK(AR13)),"",Trained) | AU13: =IF((ISBLANK(AT13)),"",Trained) | AW13: =IF((ISBLANK(AV13)),"",Trained) | AY13: =IF((ISBLANK(AX13)),"",Trained) | BA13: =IF((ISBLANK(AZ13)),"",Trained)
A14: ClassDCExpert | D14: 03 | E14: =IF((ISBLANK(D14)),"",Expert) -> 50 | F14: 09 | G14: =IF((ISBLANK(F14)),"",Expert) -> 50 | H14: 09 | I14: =IF((ISBLANK(H14)),"",Expert) -> 50 | J14: 11 | K14: =IF((ISBLANK(J14)),"",Expert) -> 50 | L14: 11 | M14: =IF((ISBLANK(L14)),"",Expert) -> 50 | N14: 09 | O14: =IF((ISBLANK(N14)),"",Expert) -> 50 | P14: 11 | Q14: =IF((ISBLANK(P14)),"",Expert) -> 50 | R14: 11 | S14: =IF((ISBLANK(R14)),"",Expert) -> 50 | T14: 09 | U14: =IF((ISBLANK(T14)),"",Expert) -> 50 | V14: 09 | W14: =IF((ISBLANK(V14)),"",Expert) -> 50 | X14: 09 | Y14: =IF((ISBLANK(X14)),"",Expert) -> 50 | Z14: 09 | AA14: =IF((ISBLANK(Z14)),"",Expert) -> 50 | AB14: 09 | AC14: =IF((ISBLANK(AB14)),"",Expert) -> 50 | AD14: 07 | AE14: =IF((ISBLANK(AD14)),"",Expert) -> 50 | AG14: =IF((ISBLANK(AF14)),"",Expert) | AI14: =IF((ISBLANK(AH14)),"",Expert) | AK14: =IF((ISBLANK(AJ14)),"",Expert) | AM14: =IF((ISBLANK(AL14)),"",Expert) | AO14: =IF((ISBLANK(AN14)),"",Expert) | AQ14: =IF((ISBLANK(AP14)),"",Expert) | AS14: =IF((ISBLANK(AR14)),"",Expert) | AU14: =IF((ISBLANK(AT14)),"",Expert) | AW14: =IF((ISBLANK(AV14)),"",Expert) | AY14: =IF((ISBLANK(AX14)),"",Expert) | BA14: =IF((ISBLANK(AZ14)),"",Expert)
A15: ClassDCMaster | D15: 05 | E15: =IF((ISBLANK(D15)),"",Master) -> 110 | F15: 17 | G15: =IF((ISBLANK(F15)),"",Master) -> 110 | H15: 17 | I15: =IF((ISBLANK(H15)),"",Master) -> 110 | J15: 19 | K15: =IF((ISBLANK(J15)),"",Master) -> 110 | L15: 19 | M15: =IF((ISBLANK(L15)),"",Master) -> 110 | N15: 17 | O15: =IF((ISBLANK(N15)),"",Master) -> 110 | P15: 19 | Q15: =IF((ISBLANK(P15)),"",Master) -> 110 | R15: 19 | S15: =IF((ISBLANK(R15)),"",Master) -> 110 | T15: 17 | U15: =IF((ISBLANK(T15)),"",Master) -> 110 | V15: 19 | W15: =IF((ISBLANK(V15)),"",Master) -> 110 | X15: 17 | Y15: =IF((ISBLANK(X15)),"",Master) -> 110 | Z15: 17 | AA15: =IF((ISBLANK(Z15)),"",Master) -> 110 | AB15: 17 | AC15: =IF((ISBLANK(AB15)),"",Master) -> 110 | AD15: 15 | AE15: =IF((ISBLANK(AD15)),"",Master) -> 110 | AG15: =IF((ISBLANK(AF15)),"",Master) | AI15: =IF((ISBLANK(AH15)),"",Master) | AK15: =IF((ISBLANK(AJ15)),"",Master) | AM15: =IF((ISBLANK(AL15)),"",Master) | AO15: =IF((ISBLANK(AN15)),"",Master) | AQ15: =IF((ISBLANK(AP15)),"",Master) | AS15: =IF((ISBLANK(AR15)),"",Master) | AU15: =IF((ISBLANK(AT15)),"",Master) | AW15: =IF((ISBLANK(AV15)),"",Master) | AY15: =IF((ISBLANK(AX15)),"",Master) | BA15: =IF((ISBLANK(AZ15)),"",Master)
A16: ClassDCLegendary | D16: 07 | E16: =IF((ISBLANK(D16)),"",Legendary) -> 190 | G16: =IF((ISBLANK(F16)),"",Legendary) | I16: =IF((ISBLANK(H16)),"",Legendary) | K16: =IF((ISBLANK(J16)),"",Legendary) | M16: =IF((ISBLANK(L16)),"",Legendary) | O16: =IF((ISBLANK(N16)),"",Legendary) | Q16: =IF((ISBLANK(P16)),"",Legendary) | S16: =IF((ISBLANK(R16)),"",Legendary) | U16: =IF((ISBLANK(T16)),"",Legendary) | W16: =IF((ISBLANK(V16)),"",Legendary) | Y16: =IF((ISBLANK(X16)),"",Legendary) | AA16: =IF((ISBLANK(Z16)),"",Legendary) | AC16: =IF((ISBLANK(AB16)),"",Legendary) | AD16: 19 | AE16: =IF((ISBLANK(AD16)),"",Legendary) -> 190 | AG16: =IF((ISBLANK(AF16)),"",Legendary) | AI16: =IF((ISBLANK(AH16)),"",Legendary) | AK16: =IF((ISBLANK(AJ16)),"",Legendary) | AM16: =IF((ISBLANK(AL16)),"",Legendary) | AO16: =IF((ISBLANK(AN16)),"",Legendary) | AQ16: =IF((ISBLANK(AP16)),"",Legendary) | AS16: =IF((ISBLANK(AR16)),"",Legendary) | AU16: =IF((ISBLANK(AT16)),"",Legendary) | AW16: =IF((ISBLANK(AV16)),"",Legendary) | AY16: =IF((ISBLANK(AX16)),"",Legendary) | BA16: =IF((ISBLANK(AZ16)),"",Legendary)
A17: SpellDCTrained | D17: 01 | E17: =IF((ISBLANK(D17)),"",Trained) -> 10 | G17: =IF((ISBLANK(F17)),"",Trained) | I17: =IF((ISBLANK(H17)),"",Trained) | K17: =IF((ISBLANK(J17)),"",Trained) | M17: =IF((ISBLANK(L17)),"",Trained) | O17: =IF((ISBLANK(N17)),"",Trained) | Q17: =IF((ISBLANK(P17)),"",Trained) | S17: =IF((ISBLANK(R17)),"",Trained) | U17: =IF((ISBLANK(T17)),"",Trained) | W17: =IF((ISBLANK(V17)),"",Trained) | Y17: =IF((ISBLANK(X17)),"",Trained) | AA17: =IF((ISBLANK(Z17)),"",Trained) | AC17: =IF((ISBLANK(AB17)),"",Trained) | AE17: =IF((ISBLANK(AD17)),"",Trained) | AF17: 01 | AG17: =IF((ISBLANK(AF17)),"",Trained) -> 10 | AH17: 01 | AI17: =IF((ISBLANK(AH17)),"",Trained) -> 10 | AJ17: 01 | AK17: =IF((ISBLANK(AJ17)),"",Trained) -> 10 | AL17: 01 | AM17: =IF((ISBLANK(AL17)),"",Trained) -> 10 | AN17: 01 | AO17: =IF((ISBLANK(AN17)),"",Trained) -> 10 | AP17: 01 | AQ17: =IF((ISBLANK(AP17)),"",Trained) -> 10 | AR17: 01 | AS17: =IF((ISBLANK(AR17)),"",Trained) -> 10 | AT17: 01 | AU17: =IF((ISBLANK(AT17)),"",Trained) -> 10 | AV17: 01 | AW17: =IF((ISBLANK(AV17)),"",Trained) -> 10 | AX17: 01 | AY17: =IF((ISBLANK(AX17)),"",Trained) -> 10 | AZ17: 01 | BA17: =IF((ISBLANK(AZ17)),"",Trained) -> 10
A18: SpellDCExpert | D18: 03 | E18: =IF((ISBLANK(D18)),"",Expert) -> 50 | G18: =IF((ISBLANK(F18)),"",Expert) | I18: =IF((ISBLANK(H18)),"",Expert) | K18: =IF((ISBLANK(J18)),"",Expert) | M18: =IF((ISBLANK(L18)),"",Expert) | O18: =IF((ISBLANK(N18)),"",Expert) | Q18: =IF((ISBLANK(P18)),"",Expert) | S18: =IF((ISBLANK(R18)),"",Expert) | U18: =IF((ISBLANK(T18)),"",Expert) | W18: =IF((ISBLANK(V18)),"",Expert) | Y18: =IF((ISBLANK(X18)),"",Expert) | AA18: =IF((ISBLANK(Z18)),"",Expert) | AC18: =IF((ISBLANK(AB18)),"",Expert) | AE18: =IF((ISBLANK(AD18)),"",Expert) | AF18: 09 | AG18: =IF((ISBLANK(AF18)),"",Expert) -> 50 | AH18: 09 | AI18: =IF((ISBLANK(AH18)),"",Expert) -> 50 | AJ18: 11 | AK18: =IF((ISBLANK(AJ18)),"",Expert) -> 50 | AL18: 07 | AM18: =IF((ISBLANK(AL18)),"",Expert) -> 50 | AN18: 07 | AO18: =IF((ISBLANK(AN18)),"",Expert) -> 50 | AP18: 07 | AQ18: =IF((ISBLANK(AP18)),"",Expert) -> 50 | AR18: 07 | AS18: =IF((ISBLANK(AR18)),"",Expert) -> 50 | AT18: 07 | AU18: =IF((ISBLANK(AT18)),"",Expert) -> 50 | AV18: 07 | AW18: =IF((ISBLANK(AV18)),"",Expert) -> 50 | AX18: 07 | AY18: =IF((ISBLANK(AX18)),"",Expert) -> 50 | AZ18: 07 | BA18: =IF((ISBLANK(AZ18)),"",Expert) -> 50
A19: SpellDCMaster | D19: 05 | E19: =IF((ISBLANK(D19)),"",Master) -> 110 | G19: =IF((ISBLANK(F19)),"",Master) | I19: =IF((ISBLANK(H19)),"",Master) | K19: =IF((ISBLANK(J19)),"",Master) | M19: =IF((ISBLANK(L19)),"",Master) | O19: =IF((ISBLANK(N19)),"",Master) | Q19: =IF((ISBLANK(P19)),"",Master) | S19: =IF((ISBLANK(R19)),"",Master) | U19: =IF((ISBLANK(T19)),"",Master) | W19: =IF((ISBLANK(V19)),"",Master) | Y19: =IF((ISBLANK(X19)),"",Master) | AA19: =IF((ISBLANK(Z19)),"",Master) | AC19: =IF((ISBLANK(AB19)),"",Master) | AE19: =IF((ISBLANK(AD19)),"",Master) | AF19: 17 | AG19: =IF((ISBLANK(AF19)),"",Master) -> 110 | AH19: 17 | AI19: =IF((ISBLANK(AH19)),"",Master) -> 110 | AJ19: 19 | AK19: =IF((ISBLANK(AJ19)),"",Master) -> 110 | AL19: 15 | AM19: =IF((ISBLANK(AL19)),"",Master) -> 110 | AN19: 15 | AO19: =IF((ISBLANK(AN19)),"",Master) -> 110 | AP19: 15 | AQ19: =IF((ISBLANK(AP19)),"",Master) -> 110 | AR19: 15 | AS19: =IF((ISBLANK(AR19)),"",Master) -> 110 | AT19: 15 | AU19: =IF((ISBLANK(AT19)),"",Master) -> 110 | AV19: 15 | AW19: =IF((ISBLANK(AV19)),"",Master) -> 110 | AX19: 15 | AY19: =IF((ISBLANK(AX19)),"",Master) -> 110 | AZ19: 15 | BA19: =IF((ISBLANK(AZ19)),"",Master) -> 110
A20: SpellDCLegendary | D20: 07 | E20: =IF((ISBLANK(D20)),"",Legendary) -> 190 | G20: =IF((ISBLANK(F20)),"",Legendary) | I20: =IF((ISBLANK(H20)),"",Legendary) | K20: =IF((ISBLANK(J20)),"",Legendary) | M20: =IF((ISBLANK(L20)),"",Legendary) | O20: =IF((ISBLANK(N20)),"",Legendary) | Q20: =IF((ISBLANK(P20)),"",Legendary) | S20: =IF((ISBLANK(R20)),"",Legendary) | U20: =IF((ISBLANK(T20)),"",Legendary) | W20: =IF((ISBLANK(V20)),"",Legendary) | Y20: =IF((ISBLANK(X20)),"",Legendary) | AA20: =IF((ISBLANK(Z20)),"",Legendary) | AC20: =IF((ISBLANK(AB20)),"",Legendary) | AE20: =IF((ISBLANK(AD20)),"",Legendary) | AG20: =IF((ISBLANK(AF20)),"",Legendary) | AI20: =IF((ISBLANK(AH20)),"",Legendary) | AK20: =IF((ISBLANK(AJ20)),"",Legendary) | AL20: 19 | AM20: =IF((ISBLANK(AL20)),"",Legendary) -> 190 | AN20: 19 | AO20: =IF((ISBLANK(AN20)),"",Legendary) -> 190 | AP20: 19 | AQ20: =IF((ISBLANK(AP20)),"",Legendary) -> 190 | AR20: 19 | AS20: =IF((ISBLANK(AR20)),"",Legendary) -> 190 | AT20: 19 | AU20: =IF((ISBLANK(AT20)),"",Legendary) -> 190 | AV20: 19 | AW20: =IF((ISBLANK(AV20)),"",Legendary) -> 190 | AX20: 19 | AY20: =IF((ISBLANK(AX20)),"",Legendary) -> 190 | AZ20: 19 | BA20: =IF((ISBLANK(AZ20)),"",Legendary) -> 190
A21: PERCEPTION TOTAL: | E21: =sum(E22:E25) -> 360 | G21: =sum(G22:G25) -> 60 | I21: =sum(I22:I25) -> 60 | K21: =sum(K22:K25) -> 170 | M21: =sum(M22:M25) -> 170 | O21: =sum(O22:O25) -> 360 | Q21: =sum(Q22:Q25) -> 360 | S21: =sum(S22:S25) -> 360 | U21: =sum(U22:U25) -> 170 | W21: =sum(W22:W25) -> 170 | Y21: =sum(Y22:Y25) -> 360 | AA21: =sum(AA22:AA25) -> 60 | AC21: =sum(AC22:AC25) -> 60 | AE21: =sum(AE22:AE25) -> 60 | AG21: =sum(AG22:AG25) -> 60 | AI21: =sum(AI22:AI25) -> 60 | AK21: =sum(AK22:AK25) -> 60 | AM21: =sum(AM22:AM25) -> 60 | AO21: =sum(AO22:AO25) -> 170 | AQ21: =sum(AQ22:AQ25) -> 60 | AS21: =sum(AS22:AS25) -> 60 | AU21: =sum(AU22:AU25) -> 60 | AW21: =sum(AW22:AW25) -> 60 | AY21: =sum(AY22:AY25) -> 60 | BA21: =sum(BA22:BA25) -> 60
A22: PerceptionTrained | D22: 01 | E22: =IF((ISBLANK(D22)),"",Trained) -> 10 | F22: 01 | G22: =IF((ISBLANK(F22)),"",Trained) -> 10 | H22: 01 | I22: =IF((ISBLANK(H22)),"",Trained) -> 10 | J22: 00 | K22: =IF((ISBLANK(J22)),"",Trained) -> 10 | L22: 00 | M22: =IF((ISBLANK(L22)),"",Trained) -> 10 | N22: 00 | O22: =IF((ISBLANK(N22)),"",Trained) -> 10 | P22: 00 | Q22: =IF((ISBLANK(P22)),"",Trained) -> 10 | R22: 00 | S22: =IF((ISBLANK(R22)),"",Trained) -> 10 | T22: 00 | U22: =IF((ISBLANK(T22)),"",Trained) -> 10 | V22: 00 | W22: =IF((ISBLANK(V22)),"",Trained) -> 10 | X22: 00 | Y22: =IF((ISBLANK(X22)),"",Trained) -> 10 | Z22: 01 | AA22: =IF((ISBLANK(Z22)),"",Trained) -> 10 | AB22: 01 | AC22: =IF((ISBLANK(AB22)),"",Trained) -> 10 | AD22: 01 | AE22: =IF((ISBLANK(AD22)),"",Trained) -> 10 | AF22: 01 | AG22: =IF((ISBLANK(AF22)),"",Trained) -> 10 | AH22: 01 | AI22: =IF((ISBLANK(AH22)),"",Trained) -> 10 | AJ22: 01 | AK22: =IF((ISBLANK(AJ22)),"",Trained) -> 10 | AL22: 01 | AM22: =IF((ISBLANK(AL22)),"",Trained) -> 10 | AN22: 00 | AO22: =IF((ISBLANK(AN22)),"",Trained) -> 10 | AP22: 01 | AQ22: =IF((ISBLANK(AP22)),"",Trained) -> 10 | AR22: 01 | AS22: =IF((ISBLANK(AR22)),"",Trained) -> 10 | AT22: 01 | AU22: =IF((ISBLANK(AT22)),"",Trained) -> 10 | AV22: 01 | AW22: =IF((ISBLANK(AV22)),"",Trained) -> 10 | AX22: 01 | AY22: =IF((ISBLANK(AX22)),"",Trained) -> 10 | AZ22: 01 | BA22: =IF((ISBLANK(AZ22)),"",Trained) -> 10
A23: PerceptionExpert | D23: 03 | E23: =IF((ISBLANK(D23)),"",Expert) -> 50 | F23: 11 | G23: =IF((ISBLANK(F23)),"",Expert) -> 50 | H23: 05 | I23: =IF((ISBLANK(H23)),"",Expert) -> 50 | J23: 01 | K23: =IF((ISBLANK(J23)),"",Expert) -> 50 | L23: 01 | M23: =IF((ISBLANK(L23)),"",Expert) -> 50 | N23: 01 | O23: =IF((ISBLANK(N23)),"",Expert) -> 50 | P23: 01 | Q23: =IF((ISBLANK(P23)),"",Expert) -> 50 | R23: 01 | S23: =IF((ISBLANK(R23)),"",Expert) -> 50 | T23: 01 | U23: =IF((ISBLANK(T23)),"",Expert) -> 50 | V23: 01 | W23: =IF((ISBLANK(V23)),"",Expert) -> 50 | X23: 01 | Y23: =IF((ISBLANK(X23)),"",Expert) -> 50 | Z23: 13 | AA23: =IF((ISBLANK(Z23)),"",Expert) -> 50 | AB23: 09 | AC23: =IF((ISBLANK(AB23)),"",Expert) -> 50 | AD23: 09 | AE23: =IF((ISBLANK(AD23)),"",Expert) -> 50 | AF23: 03 | AG23: =IF((ISBLANK(AF23)),"",Expert) -> 50 | AH23: 09 | AI23: =IF((ISBLANK(AH23)),"",Expert) -> 50 | AJ23: 05 | AK23: =IF((ISBLANK(AJ23)),"",Expert) -> 50 | AL23: 05 | AM23: =IF((ISBLANK(AL23)),"",Expert) -> 50 | AN23: 01 | AO23: =IF((ISBLANK(AN23)),"",Expert) -> 50 | AP23: 11 | AQ23: =IF((ISBLANK(AP23)),"",Expert) -> 50 | AR23: 03 | AS23: =IF((ISBLANK(AR23)),"",Expert) -> 50 | AT23: 11 | AU23: =IF((ISBLANK(AT23)),"",Expert) -> 50 | AV23: 11 | AW23: =IF((ISBLANK(AV23)),"",Expert) -> 50 | AX23: 11 | AY23: =IF((ISBLANK(AX23)),"",Expert) -> 50 | AZ23: 11 | BA23: =IF((ISBLANK(AZ23)),"",Expert) -> 50
A24: PerceptionMaster | D24: 05 | E24: =IF((ISBLANK(D24)),"",Master) -> 110 | G24: =IF((ISBLANK(F24)),"",Master) | I24: =IF((ISBLANK(H24)),"",Master) | J24: 07 | K24: =IF((ISBLANK(J24)),"",Master) -> 110 | L24: 17 | M24: =IF((ISBLANK(L24)),"",Master) -> 110 | N24: 07 | O24: =IF((ISBLANK(N24)),"",Master) -> 110 | P24: 07 | Q24: =IF((ISBLANK(P24)),"",Master) -> 110 | R24: 07 | S24: =IF((ISBLANK(R24)),"",Master) -> 110 | T24: 09 | U24: =IF((ISBLANK(T24)),"",Master) -> 110 | V24: 11 | W24: =IF((ISBLANK(V24)),"",Master) -> 110 | X24: 07 | Y24: =IF((ISBLANK(X24)),"",Master) -> 110 | AA24: =IF((ISBLANK(Z24)),"",Master) | AC24: =IF((ISBLANK(AB24)),"",Master) | AE24: =IF((ISBLANK(AD24)),"",Master) | AG24: =IF((ISBLANK(AF24)),"",Master) | AI24: =IF((ISBLANK(AH24)),"",Master) | AK24: =IF((ISBLANK(AJ24)),"",Master) | AM24: =IF((ISBLANK(AL24)),"",Master) | AN24: 11 | AO24: =IF((ISBLANK(AN24)),"",Master) -> 110 | AQ24: =IF((ISBLANK(AP24)),"",Master) | AS24: =IF((ISBLANK(AR24)),"",Master) | AU24: =IF((ISBLANK(AT24)),"",Master) | AW24: =IF((ISBLANK(AV24)),"",Master) | AY24: =IF((ISBLANK(AX24)),"",Master) | BA24: =IF((ISBLANK(AZ24)),"",Master)
A25: PerceptionLegendary | D25: 07 | E25: =IF((ISBLANK(D25)),"",Legendary) -> 190 | G25: =IF((ISBLANK(F25)),"",Legendary) | I25: =IF((ISBLANK(H25)),"",Legendary) | K25: =IF((ISBLANK(J25)),"",Legendary) | M25: =IF((ISBLANK(L25)),"",Legendary) | N25: 15 | O25: =IF((ISBLANK(N25)),"",Legendary) -> 190 | P25: 13 | Q25: =IF((ISBLANK(P25)),"",Legendary) -> 190 | R25: 13 | S25: =IF((ISBLANK(R25)),"",Legendary) -> 190 | U25: =IF((ISBLANK(T25)),"",Legendary) | W25: =IF((ISBLANK(V25)),"",Legendary) | X25: 19 | Y25: =IF((ISBLANK(X25)),"",Legendary) -> 190 | AA25: =IF((ISBLANK(Z25)),"",Legendary) | AC25: =IF((ISBLANK(AB25)),"",Legendary) | AE25: =IF((ISBLANK(AD25)),"",Legendary) | AG25: =IF((ISBLANK(AF25)),"",Legendary) | AI25: =IF((ISBLANK(AH25)),"",Legendary) | AK25: =IF((ISBLANK(AJ25)),"",Legendary) | AM25: =IF((ISBLANK(AL25)),"",Legendary) | AO25: =IF((ISBLANK(AN25)),"",Legendary) | AQ25: =IF((ISBLANK(AP25)),"",Legendary) | AS25: =IF((ISBLANK(AR25)),"",Legendary) | AU25: =IF((ISBLANK(AT25)),"",Legendary) | AW25: =IF((ISBLANK(AV25)),"",Legendary) | AY25: =IF((ISBLANK(AX25)),"",Legendary) | BA25: =IF((ISBLANK(AZ25)),"",Legendary)
A26: SAVES TOTAL: | E26: =sum(E27:E38) -> 1080 | G26: =sum(G27:G38) -> 400 | I26: =sum(I27:I38) -> 180 | K26: =sum(K27:K38) -> 400 | M26: =sum(M27:M38) -> 590 | O26: =sum(O27:O38) -> 590 | Q26: =sum(Q27:Q38) -> 590 | S26: =sum(S27:S38) -> 590 | U26: =sum(U27:U38) -> 590 | W26: =sum(W27:W38) -> 590 | Y26: =sum(Y27:Y38) -> 400 | AA26: =sum(AA27:AA38) -> 400 | AC26: =sum(AC27:AC38) -> 400 | AE26: =sum(AE27:AE38) -> 590 | AG26: =sum(AG27:AG38) -> 400 | AI26: =sum(AI27:AI38) -> 400 | AK26: =sum(AK27:AK38) -> 400 | AM26: =sum(AM27:AM38) -> 290 | AO26: =sum(AO27:AO38) -> 480 | AQ26: =sum(AQ27:AQ38) -> 480 | AS26: =sum(AS27:AS38) -> 290 | AU26: =sum(AU27:AU38) -> 480 | AW26: =sum(AW27:AW38) -> 290 | AY26: =sum(AY27:AY38) -> 290 | BA26: =sum(BA27:BA38) -> 290
A27: FortitudeSaveTrained | D27: 01 | E27: =IF((ISBLANK(D27)),"",Trained) -> 10 | F27: 00 | G27: =IF((ISBLANK(F27)),"",Trained) -> 10 | H27: 00 | I27: =IF((ISBLANK(H27)),"",Trained) -> 10 | J27: 00 | K27: =IF((ISBLANK(J27)),"",Trained) -> 10 | L27: 00 | M27: =IF((ISBLANK(L27)),"",Trained) -> 10 | N27: 00 | O27: =IF((ISBLANK(N27)),"",Trained) -> 10 | P27: 01 | Q27: =IF((ISBLANK(P27)),"",Trained) -> 10 | R27: 01 | S27: =IF((ISBLANK(R27)),"",Trained) -> 10 | T27: 00 | U27: =IF((ISBLANK(T27)),"",Trained) -> 10 | V27: 01 | W27: =IF((ISBLANK(V27)),"",Trained) -> 10 | X27: 00 | Y27: =IF((ISBLANK(X27)),"",Trained) -> 10 | Z27: 00 | AA27: =IF((ISBLANK(Z27)),"",Trained) -> 10 | AB27: 00 | AC27: =IF((ISBLANK(AB27)),"",Trained) -> 10 | AD27: 00 | AE27: =IF((ISBLANK(AD27)),"",Trained) -> 10 | AF27: 00 | AG27: =IF((ISBLANK(AF27)),"",Trained) -> 10 | AH27: 00 | AI27: =IF((ISBLANK(AH27)),"",Trained) -> 10 | AJ27: 00 | AK27: =IF((ISBLANK(AJ27)),"",Trained) -> 10 | AL27: 01 | AM27: =IF((ISBLANK(AL27)),"",Trained) -> 10 | AN27: 01 | AO27: =IF((ISBLANK(AN27)),"",Trained) -> 10 | AP27: 01 | AQ27: =IF((ISBLANK(AP27)),"",Trained) -> 10 | AR27: 01 | AS27: =IF((ISBLANK(AR27)),"",Trained) -> 10 | AT27: 01 | AU27: =IF((ISBLANK(AT27)),"",Trained) -> 10 | AV27: 01 | AW27: =IF((ISBLANK(AV27)),"",Trained) -> 10 | AX27: 01 | AY27: =IF((ISBLANK(AX27)),"",Trained) -> 10 | AZ27: 01 | BA27: =IF((ISBLANK(AZ27)),"",Trained) -> 10
A28: FortitudeSaveExpert | D28: 03 | E28: =IF((ISBLANK(D28)),"",Expert) -> 50 | F28: 01 | G28: =IF((ISBLANK(F28)),"",Expert) -> 50 | H28: 01 | I28: =IF((ISBLANK(H28)),"",Expert) -> 50 | J28: 01 | K28: =IF((ISBLANK(J28)),"",Expert) -> 50 | L28: 01 | M28: =IF((ISBLANK(L28)),"",Expert) -> 50 | N28: 01 | O28: =IF((ISBLANK(N28)),"",Expert) -> 50 | P28: 09 | Q28: =IF((ISBLANK(P28)),"",Expert) -> 50 | R28: 09 | S28: =IF((ISBLANK(R28)),"",Expert) -> 50 | T28: 01 | U28: =IF((ISBLANK(T28)),"",Expert) -> 50 | V28: 03 | W28: =IF((ISBLANK(V28)),"",Expert) -> 50 | X28: 01 | Y28: =IF((ISBLANK(X28)),"",Expert) -> 50 | Z28: 01 | AA28: =IF((ISBLANK(Z28)),"",Expert) -> 50 | AB28: 01 | AC28: =IF((ISBLANK(AB28)),"",Expert) -> 50 | AD28: 01 | AE28: =IF((ISBLANK(AD28)),"",Expert) -> 50 | AF28: 01 | AG28: =IF((ISBLANK(AF28)),"",Expert) -> 50 | AH28: 01 | AI28: =IF((ISBLANK(AH28)),"",Expert) -> 50 | AJ28: 01 | AK28: =IF((ISBLANK(AJ28)),"",Expert) -> 50 | AL28: 03 | AM28: =IF((ISBLANK(AL28)),"",Expert) -> 50 | AN28: 09 | AO28: =IF((ISBLANK(AN28)),"",Expert) -> 50 | AP28: 09 | AQ28: =IF((ISBLANK(AP28)),"",Expert) -> 50 | AR28: 03 | AS28: =IF((ISBLANK(AR28)),"",Expert) -> 50 | AT28: 09 | AU28: =IF((ISBLANK(AT28)),"",Expert) -> 50 | AV28: 09 | AW28: =IF((ISBLANK(AV28)),"",Expert) -> 50 | AX28: 05 | AY28: =IF((ISBLANK(AX28)),"",Expert) -> 50 | AZ28: 05 | BA28: =IF((ISBLANK(AZ28)),"",Expert) -> 50
A29: FortitudeSaveMaster | D29: 05 | E29: =IF((ISBLANK(D29)),"",Master) -> 110 | F29: 09 | G29: =IF((ISBLANK(F29)),"",Master) -> 110 | H29: 07 | I29: C | J29: 09 | K29: =IF((ISBLANK(J29)),"",Master) -> 110 | L29: 07 | M29: =IF((ISBLANK(L29)),"",Master) -> 110 | N29: 11 | O29: =IF((ISBLANK(N29)),"",Master) -> 110 | Q29: =IF((ISBLANK(P29)),"",Master) | S29: =IF((ISBLANK(R29)),"",Master) | T29: 15 | U29: =IF((ISBLANK(T29)),"",Master) -> 110 | W29: =IF((ISBLANK(V29)),"",Master) | X29: 17 | Y29: =IF((ISBLANK(X29)),"",Master) -> 110 | Z29: 17 | AA29: =IF((ISBLANK(Z29)),"",Master) -> 110 | AB29: 11 | AC29: =IF((ISBLANK(AB29)),"",Master) -> 110 | AD29: 07 | AE29: =IF((ISBLANK(AD29)),"",Master) -> 110 | AF29: 11 | AG29: =IF((ISBLANK(AF29)),"",Master) -> 110 | AH29: 15 | AI29: =IF((ISBLANK(AH29)),"",Master) -> 110 | AJ29: 15 | AK29: =IF((ISBLANK(AJ29)),"",Master) -> 110 | AM29: =IF((ISBLANK(AL29)),"",Master) | AO29: =IF((ISBLANK(AN29)),"",Master) | AQ29: =IF((ISBLANK(AP29)),"",Master) | AS29: =IF((ISBLANK(AR29)),"",Master) | AU29: =IF((ISBLANK(AT29)),"",Master) | AW29: =IF((ISBLANK(AV29)),"",Master) | AY29: =IF((ISBLANK(AX29)),"",Master) | BA29: =IF((ISBLANK(AZ29)),"",Master)
A30: FortitudeSaveLegendary | D30: 07 | E30: =IF((ISBLANK(D30)),"",Legendary) -> 190 | G30: =IF((ISBLANK(F30)),"",Legendary) | H30: 15 | I30: C | K30: =IF((ISBLANK(J30)),"",Legendary) | L30: 13 | M30: =IF((ISBLANK(L30)),"",Legendary) -> 190 | O30: =IF((ISBLANK(N30)),"",Legendary) | Q30: =IF((ISBLANK(P30)),"",Legendary) | S30: =IF((ISBLANK(R30)),"",Legendary) | U30: =IF((ISBLANK(T30)),"",Legendary) | W30: =IF((ISBLANK(V30)),"",Legendary) | Y30: =IF((ISBLANK(X30)),"",Legendary) | AA30: =IF((ISBLANK(Z30)),"",Legendary) | AC30: =IF((ISBLANK(AB30)),"",Legendary) | AD30: 15 | AE30: =IF((ISBLANK(AD30)),"",Legendary) -> 190 | AG30: =IF((ISBLANK(AF30)),"",Legendary) | AI30: =IF((ISBLANK(AH30)),"",Legendary) | AK30: =IF((ISBLANK(AJ30)),"",Legendary) | AM30: =IF((ISBLANK(AL30)),"",Legendary) | AO30: =IF((ISBLANK(AN30)),"",Legendary) | AQ30: =IF((ISBLANK(AP30)),"",Legendary) | AS30: =IF((ISBLANK(AR30)),"",Legendary) | AU30: =IF((ISBLANK(AT30)),"",Legendary) | AW30: =IF((ISBLANK(AV30)),"",Legendary) | AY30: =IF((ISBLANK(AX30)),"",Legendary) | BA30: =IF((ISBLANK(AZ30)),"",Legendary)
A31: ReflexSaveTrained | D31: 01 | E31: =IF((ISBLANK(D31)),"",Trained) -> 10 | F31: 01 | G31: =IF((ISBLANK(F31)),"",Trained) -> 10 | H31: 00 | I31: =IF((ISBLANK(H31)),"",Trained) -> 10 | J31: 00 | K31: =IF((ISBLANK(J31)),"",Trained) -> 10 | L31: 01 | M31: =IF((ISBLANK(L31)),"",Trained) -> 10 | N31: 00 | O31: =IF((ISBLANK(N31)),"",Trained) -> 10 | P31: 00 | Q31: =IF((ISBLANK(P31)),"",Trained) -> 10 | R31: 00 | S31: =IF((ISBLANK(R31)),"",Trained) -> 10 | T31: 01 | U31: =IF((ISBLANK(T31)),"",Trained) -> 10 | V31: 00 | W31: =IF((ISBLANK(V31)),"",Trained) -> 10 | X31: 00 | Y31: =IF((ISBLANK(X31)),"",Trained) -> 10 | Z31: 01 | AA31: =IF((ISBLANK(Z31)),"",Trained) -> 10 | AB31: 00 | AC31: =IF((ISBLANK(AB31)),"",Trained) -> 10 | AD31: 00 | AE31: =IF((ISBLANK(AD31)),"",Trained) -> 10 | AF31: 01 | AG31: =IF((ISBLANK(AF31)),"",Trained) -> 10 | AH31: 01 | AI31: =IF((ISBLANK(AH31)),"",Trained) -> 10 | AJ31: 01 | AK31: =IF((ISBLANK(AJ31)),"",Trained) -> 10 | AL31: 01 | AM31: =IF((ISBLANK(AL31)),"",Trained) -> 10 | AN31: 01 | AO31: =IF((ISBLANK(AN31)),"",Trained) -> 10 | AP31: 01 | AQ31: =IF((ISBLANK(AP31)),"",Trained) -> 10 | AR31: 01 | AS31: =IF((ISBLANK(AR31)),"",Trained) -> 10 | AT31: 01 | AU31: =IF((ISBLANK(AT31)),"",Trained) -> 10 | AV31: 01 | AW31: =IF((ISBLANK(AV31)),"",Trained) -> 10 | AX31: 01 | AY31: =IF((ISBLANK(AX31)),"",Trained) -> 10 | AZ31: 01 | BA31: =IF((ISBLANK(AZ31)),"",Trained) -> 10
A32: ReflexSaveExpert | D32: 03 | E32: =IF((ISBLANK(D32)),"",Expert) -> 50 | F32: 09 | G32: =IF((ISBLANK(F32)),"",Expert) -> 50 | H32: 01 | I32: =IF((ISBLANK(H32)),"",Expert) -> 50 | J32: 01 | K32: =IF((ISBLANK(J32)),"",Expert) -> 50 | L32: 09 | M32: =IF((ISBLANK(L32)),"",Expert) -> 50 | N32: 01 | O32: =IF((ISBLANK(N32)),"",Expert) -> 50 | P32: 01 | Q32: =IF((ISBLANK(P32)),"",Expert) -> 50 | R32: 01 | S32: =IF((ISBLANK(R32)),"",Expert) -> 50 | T32: 03 | U32: =IF((ISBLANK(T32)),"",Expert) -> 50 | V32: 01 | W32: =IF((ISBLANK(V32)),"",Expert) -> 50 | X32: 01 | Y32: =IF((ISBLANK(X32)),"",Expert) -> 50 | Z32: 07 | AA32: =IF((ISBLANK(Z32)),"",Expert) -> 50 | AB32: 01 | AC32: =IF((ISBLANK(AB32)),"",Expert) -> 50 | AD32: 01 | AE32: =IF((ISBLANK(AD32)),"",Expert) -> 50 | AF32: 09 | AG32: =IF((ISBLANK(AF32)),"",Expert) -> 50 | AH32: 05 | AI32: =IF((ISBLANK(AH32)),"",Expert) -> 50 | AJ32: 11 | AK32: =IF((ISBLANK(AJ32)),"",Expert) -> 50 | AL32: 11 | AM32: =IF((ISBLANK(AL32)),"",Expert) -> 50 | AN32: 03 | AO32: =IF((ISBLANK(AN32)),"",Expert) -> 50 | AP32: 13 | AQ32: =IF((ISBLANK(AP32)),"",Expert) -> 50 | AR32: 05 | AS32: =IF((ISBLANK(AR32)),"",Expert) -> 50 | AT32: 05 | AU32: =IF((ISBLANK(AT32)),"",Expert) -> 50 | AV32: 05 | AW32: =IF((ISBLANK(AV32)),"",Expert) -> 50 | AX32: 09 | AY32: =IF((ISBLANK(AX32)),"",Expert) -> 50 | AZ32: 09 | BA32: =IF((ISBLANK(AZ32)),"",Expert) -> 50
A33: ReflexSaveMaster | D33: 05 | E33: =IF((ISBLANK(D33)),"",Master) -> 110 | G33: =IF((ISBLANK(F33)),"",Master) | H33: 07 | I33: C | J33: 15 | K33: =IF((ISBLANK(J33)),"",Master) -> 110 | M33: =IF((ISBLANK(L33)),"",Master) | N33: 07 | O33: =IF((ISBLANK(N33)),"",Master) -> 110 | P33: 07 | Q33: =IF((ISBLANK(P33)),"",Master) -> 110 | R33: 15 | S33: =IF((ISBLANK(R33)),"",Master) -> 110 | U33: =IF((ISBLANK(T33)),"",Master) | V33: 07 | W33: =IF((ISBLANK(V33)),"",Master) -> 110 | X33: 11 | Y33: =IF((ISBLANK(X33)),"",Master) -> 110 | AA33: =IF((ISBLANK(Z33)),"",Master) | AB33: 15 | AC33: =IF((ISBLANK(AB33)),"",Master) -> 110 | AD33: 11 | AE33: =IF((ISBLANK(AD33)),"",Master) -> 110 | AG33: =IF((ISBLANK(AF33)),"",Master) | AI33: =IF((ISBLANK(AH33)),"",Master) | AK33: =IF((ISBLANK(AJ33)),"",Master) | AM33: =IF((ISBLANK(AL33)),"",Master) | AO33: =IF((ISBLANK(AN33)),"",Master) | AQ33: =IF((ISBLANK(AP33)),"",Master) | AS33: =IF((ISBLANK(AR33)),"",Master) | AU33: =IF((ISBLANK(AT33)),"",Master) | AW33: =IF((ISBLANK(AV33)),"",Master) | AY33: =IF((ISBLANK(AX33)),"",Master) | BA33: =IF((ISBLANK(AZ33)),"",Master)
A34: ReflexSaveLegendary | D34: 07 | E34: =IF((ISBLANK(D34)),"",Legendary) -> 190 | G34: =IF((ISBLANK(F34)),"",Legendary) | H34: 15 | I34: C | K34: =IF((ISBLANK(J34)),"",Legendary) | M34: =IF((ISBLANK(L34)),"",Legendary) | N34: 15 | O34: =IF((ISBLANK(N34)),"",Legendary) -> 190 | P34: 13 | Q34: =IF((ISBLANK(P34)),"",Legendary) -> 190 | S34: =IF((ISBLANK(R34)),"",Legendary) | U34: =IF((ISBLANK(T34)),"",Legendary) | V34: 13 | W34: =IF((ISBLANK(V34)),"",Legendary) -> 190 | Y34: =IF((ISBLANK(X34)),"",Legendary) | AA34: =IF((ISBLANK(Z34)),"",Legendary) | AC34: =IF((ISBLANK(AB34)),"",Legendary) | AE34: =IF((ISBLANK(AD34)),"",Legendary) | AG34: =IF((ISBLANK(AF34)),"",Legendary) | AI34: =IF((ISBLANK(AH34)),"",Legendary) | AK34: =IF((ISBLANK(AJ34)),"",Legendary) | AM34: =IF((ISBLANK(AL34)),"",Legendary) | AO34: =IF((ISBLANK(AN34)),"",Legendary) | AQ34: =IF((ISBLANK(AP34)),"",Legendary) | AS34: =IF((ISBLANK(AR34)),"",Legendary) | AU34: =IF((ISBLANK(AT34)),"",Legendary) | AW34: =IF((ISBLANK(AV34)),"",Legendary) | AY34: =IF((ISBLANK(AX34)),"",Legendary) | BA34: =IF((ISBLANK(AZ34)),"",Legendary)
A35: WillSaveTrained | D35: 01 | E35: =IF((ISBLANK(D35)),"",Trained) -> 10 | F35: 00 | G35: =IF((ISBLANK(F35)),"",Trained) -> 10 | H35: 00 | I35: =IF((ISBLANK(H35)),"",Trained) -> 10 | J35: 01 | K35: =IF((ISBLANK(J35)),"",Trained) -> 10 | L35: 00 | M35: =IF((ISBLANK(L35)),"",Trained) -> 10 | N35: 01 | O35: =IF((ISBLANK(N35)),"",Trained) -> 10 | P35: 00 | Q35: =IF((ISBLANK(P35)),"",Trained) -> 10 | R35: 00 | S35: =IF((ISBLANK(R35)),"",Trained) -> 10 | T35: 00 | U35: =IF((ISBLANK(T35)),"",Trained) -> 10 | V35: 00 | W35: =IF((ISBLANK(V35)),"",Trained) -> 10 | X35: 01 | Y35: =IF((ISBLANK(X35)),"",Trained) -> 10 | Z35: 00 | AA35: =IF((ISBLANK(Z35)),"",Trained) -> 10 | AB35: 01 | AC35: =IF((ISBLANK(AB35)),"",Trained) -> 10 | AD35: 01 | AE35: =IF((ISBLANK(AD35)),"",Trained) -> 10 | AF35: 00 | AG35: =IF((ISBLANK(AF35)),"",Trained) -> 10 | AH35: 00 | AI35: =IF((ISBLANK(AH35)),"",Trained) -> 10 | AJ35: 00 | AK35: =IF((ISBLANK(AJ35)),"",Trained) -> 10 | AL35: 00 | AM35: =IF((ISBLANK(AL35)),"",Trained) -> 10 | AN35: 00 | AO35: =IF((ISBLANK(AN35)),"",Trained) -> 10 | AP35: 00 | AQ35: =IF((ISBLANK(AP35)),"",Trained) -> 10 | AR35: 00 | AS35: =IF((ISBLANK(AR35)),"",Trained) -> 10 | AT35: 00 | AU35: =IF((ISBLANK(AT35)),"",Trained) -> 10 | AV35: 00 | AW35: =IF((ISBLANK(AV35)),"",Trained) -> 10 | AX35: 00 | AY35: =IF((ISBLANK(AX35)),"",Trained) -> 10 | AZ35: 00 | BA35: =IF((ISBLANK(AZ35)),"",Trained) -> 10
A36: WillSaveExpert | D36: 03 | E36: =IF((ISBLANK(D36)),"",Expert) -> 50 | F36: 01 | G36: =IF((ISBLANK(F36)),"",Expert) -> 50 | H36: 01 | I36: =IF((ISBLANK(H36)),"",Expert) -> 50 | J36: 03 | K36: =IF((ISBLANK(J36)),"",Expert) -> 50 | L36: 01 | M36: =IF((ISBLANK(L36)),"",Expert) -> 50 | N36: 03 | O36: =IF((ISBLANK(N36)),"",Expert) -> 50 | P36: 01 | Q36: =IF((ISBLANK(P36)),"",Expert) -> 50 | R36: 01 | S36: =IF((ISBLANK(R36)),"",Expert) -> 50 | T36: 01 | U36: =IF((ISBLANK(T36)),"",Expert) -> 50 | V36: 01 | W36: =IF((ISBLANK(V36)),"",Expert) -> 50 | X36: 03 | Y36: =IF((ISBLANK(X36)),"",Expert) -> 50 | Z36: 01 | AA36: =IF((ISBLANK(Z36)),"",Expert) -> 50 | AB36: 07 | AC36: =IF((ISBLANK(AB36)),"",Expert) -> 50 | AD36: 03 | AE36: =IF((ISBLANK(AD36)),"",Expert) -> 50 | AF36: 01 | AG36: =IF((ISBLANK(AF36)),"",Expert) -> 50 | AH36: 01 | AI36: =IF((ISBLANK(AH36)),"",Expert) -> 50 | AJ36: 01 | AK36: =IF((ISBLANK(AJ36)),"",Expert) -> 50 | AL36: 01 | AM36: =IF((ISBLANK(AL36)),"",Expert) -> 50 | AN36: 01 | AO36: =IF((ISBLANK(AN36)),"",Expert) -> 50 | AP36: 01 | AQ36: =IF((ISBLANK(AP36)),"",Expert) -> 50 | AR36: 01 | AS36: =IF((ISBLANK(AR36)),"",Expert) -> 50 | AT36: 01 | AU36: =IF((ISBLANK(AT36)),"",Expert) -> 50 | AV36: 01 | AW36: =IF((ISBLANK(AV36)),"",Expert) -> 50 | AX36: 01 | AY36: =IF((ISBLANK(AX36)),"",Expert) -> 50 | AZ36: 01 | BA36: =IF((ISBLANK(AZ36)),"",Expert) -> 50
A37: WillSaveMaster | D37: 05 | E37: =IF((ISBLANK(D37)),"",Master) -> 110 | F37: 11 | G37: =IF((ISBLANK(F37)),"",Master) -> 110 | H37: 07 | I37: C | K37: =IF((ISBLANK(J37)),"",Master) | L37: 15 | M37: =IF((ISBLANK(L37)),"",Master) -> 110 | O37: =IF((ISBLANK(N37)),"",Master) | P37: 17 | Q37: =IF((ISBLANK(P37)),"",Master) -> 110 | R37: 11 | S37: =IF((ISBLANK(R37)),"",Master) -> 110 | T37: 07 | U37: =IF((ISBLANK(T37)),"",Master) -> 110 | V37: 17 | W37: =IF((ISBLANK(V37)),"",Master) -> 110 | Y37: =IF((ISBLANK(X37)),"",Master) | Z37: 11 | AA37: =IF((ISBLANK(Z37)),"",Master) -> 110 | AC37: =IF((ISBLANK(AB37)),"",Master) | AE37: =IF((ISBLANK(AD37)),"",Master) | AF37: 15 | AG37: =IF((ISBLANK(AF37)),"",Master) -> 110 | AH37: 09 | AI37: =IF((ISBLANK(AH37)),"",Master) -> 110 | AJ37: 09 | AK37: =IF((ISBLANK(AJ37)),"",Master) -> 110 | AL37: 09 | AM37: =IF((ISBLANK(AL37)),"",Master) -> 110 | AN37: 09 | AO37: =IF((ISBLANK(AN37)),"",Master) -> 110 | AP37: 07 | AQ37: =IF((ISBLANK(AP37)),"",Master) -> 110 | AR37: 11 | AS37: =IF((ISBLANK(AR37)),"",Master) -> 110 | AT37: 11 | AU37: =IF((ISBLANK(AT37)),"",Master) -> 110 | AV37: 17 | AW37: =IF((ISBLANK(AV37)),"",Master) -> 110 | AX37: 17 | AY37: =IF((ISBLANK(AX37)),"",Master) -> 110 | AZ37: 17 | BA37: =IF((ISBLANK(AZ37)),"",Master) -> 110
A38: WillSaveLegendary | D38: 07 | E38: =IF((ISBLANK(D38)),"",Legendary) -> 190 | G38: =IF((ISBLANK(F38)),"",Legendary) | H38: 15 | I38: C | K38: =IF((ISBLANK(J38)),"",Legendary) | M38: =IF((ISBLANK(L38)),"",Legendary) | O38: =IF((ISBLANK(N38)),"",Legendary) | Q38: =IF((ISBLANK(P38)),"",Legendary) | R38: 17 | S38: =IF((ISBLANK(R38)),"",Legendary) -> 190 | T38: 13 | U38: =IF((ISBLANK(T38)),"",Legendary) -> 190 | W38: =IF((ISBLANK(V38)),"",Legendary) | Y38: =IF((ISBLANK(X38)),"",Legendary) | AA38: =IF((ISBLANK(Z38)),"",Legendary) | AC38: =IF((ISBLANK(AB38)),"",Legendary) | AE38: =IF((ISBLANK(AD38)),"",Legendary) | AG38: =IF((ISBLANK(AF38)),"",Legendary) | AI38: =IF((ISBLANK(AH38)),"",Legendary) | AK38: =IF((ISBLANK(AJ38)),"",Legendary) | AM38: =IF((ISBLANK(AL38)),"",Legendary) | AN38: 17 | AO38: =IF((ISBLANK(AN38)),"",Legendary) -> 190 | AP38: 17 | AQ38: =IF((ISBLANK(AP38)),"",Legendary) -> 190 | AS38: =IF((ISBLANK(AR38)),"",Legendary) | AT38: 17 | AU38: =IF((ISBLANK(AT38)),"",Legendary) -> 190 | AW38: =IF((ISBLANK(AV38)),"",Legendary) | AY38: =IF((ISBLANK(AX38)),"",Legendary) | BA38: =IF((ISBLANK(AZ38)),"",Legendary)
A39: SKILLS TOTAL: | E39: =E59+E79+E100 -> 290 | G39: =G59+G79+G100 -> 20 | I39: =I59+I79+I100 -> 20 | K39: =K59+K79+K100 -> 20 | M39: =M59+M79+M100 -> 20 | O39: =O59+O79+O100 -> 30 | Q39: =Q59+Q79+Q100 -> 140 | S39: =S59+S79+S100 -> 120 | U39: =U59+U79+U100 -> 70 | W39: =W59+W79+W100 -> 40 | Y39: =Y59+Y79+Y100 -> 20 | AA39: =AA59+AA79+AA100 -> 40 | AC39: =AC59+AC79+AC100 -> 20 | AE39: =AE59+AE79+AE100 -> 20 | AG39: =AG59+AG79+AG100 -> 25 | AI39: =AI59+AI79+AI100 -> 15 | AK39: =AK59+AK79+AK100 -> 20 | AM39: =AM59+AM79+AM100 -> 20 | AO39: =AO59+AO79+AO100 -> 30 | AQ39: =AQ59+AQ79+AQ100 -> 25 | AS39: =AS59+AS79+AS100 -> 20 | AU39: =AU59+AU79+AU100 -> 20 | AW39: =AW59+AW79+AW100 -> 15 | AY39: =AY59+AY79+AY100 -> 20 | BA39: =BA59+BA79+BA100 -> 20
A40: InitialSkillIncreases | B40: L00 | D40: 1 | E40: =D40*SkillIncrease -> 5 | F40: 2 | G40: =F40*SkillIncrease -> 10 | H40: 4 | I40: =H40*SkillIncrease -> 20 | J40: 3 | K40: =J40*SkillIncrease -> 15 | L40: 3 | M40: =L40*SkillIncrease -> 15 | N40: 4 | O40: =N40*SkillIncrease -> 20 | P40: 7 | Q40: =P40*SkillIncrease -> 35 | R40: 4 | S40: =R40*SkillIncrease -> 20 | T40: 3 | U40: =T40*SkillIncrease -> 15 | V40: 4 | W40: =V40*SkillIncrease -> 20 | X40: 3 | Y40: =X40*SkillIncrease -> 15 | Z40: 3 | AA40: =Z40*SkillIncrease -> 15 | AB40: 3 | AC40: =AB40*SkillIncrease -> 15 | AD40: 3 | AE40: =AD40*SkillIncrease -> 15 | AF40: 3 | AG40: =AF40*SkillIncrease -> 15 | AH40: 2 | AI40: =AH40*SkillIncrease -> 10 | AJ40: 2 | AK40: =AJ40*SkillIncrease -> 10 | AL40: 2 | AM40: =AL40*SkillIncrease -> 10 | AN40: 4 | AO40: =AN40*SkillIncrease -> 20 | AP40: 3 | AQ40: =AP40*SkillIncrease -> 15 | AR40: 2 | AS40: =AR40*SkillIncrease -> 10 | AT40: 3 | AU40: =AT40*SkillIncrease -> 15 | AV40: 2 | AW40: =AV40*SkillIncrease -> 10 | AX40: 3 | AY40: =AX40*SkillIncrease -> 15 | AZ40: 2 | BA40: =AZ40*SkillIncrease -> 10
A41: SubclassSkillIncreases | B41: L00 | D41: 1 | E41: =D41*SkillIncrease -> 5 | F41: 1 | G41: =F41*SkillIncrease -> 5 | J41: 1 | K41: =J41*SkillIncrease -> 5 | P41: 1 | Q41: 0 | R41: 1 | S41: 0 | V41: 1 | W41: 0 | X41: 1 | Y41: =X41*SkillIncrease -> 5 | AE41: =AD41*SkillIncrease -> 0 | AF41: 2 | AG41: =AF41*SkillIncrease -> 10 | AJ41: 1 | AK41: =AJ41*SkillIncrease -> 5 | AL41: 1 | AM41: =AL41*SkillIncrease -> 5 | AP41: 1 | AQ41: =AP41*SkillIncrease -> 5 | AR41: 1 | AS41: =AR41*SkillIncrease -> 5 | AX41: 1 | AY41: =AX41*SkillIncrease -> 5 | AZ41: 2 | BA41: =AZ41*SkillIncrease -> 10
A42: SkillGrantAcrobatics | B42: L00 | D42: Acrobatics (Dex) | E42: =if((ISBLANK(D42)),"",SkillIncrease) -> 5 | G42: =if((ISBLANK(F42)),"",SkillIncrease) | I42: =if((ISBLANK(H42)),"",SkillIncrease) | K42: =if((ISBLANK(J42)),"",SkillIncrease) | M42: =if((ISBLANK(L42)),"",SkillIncrease) | O42: =if((ISBLANK(N42)),"",SkillIncrease) | Q42: =if((ISBLANK(P42)),"",SkillIncrease) | S42: =if((ISBLANK(R42)),"",SkillIncrease) | U42: =if((ISBLANK(T42)),"",SkillIncrease) | V42: Acrobatics (Dex) | W42: =if((ISBLANK(V42)),"",SkillIncrease) -> 5 | Y42: =if((ISBLANK(X42)),"",SkillIncrease) | AA42: =if((ISBLANK(Z42)),"",SkillIncrease) | AC42: =if((ISBLANK(AB42)),"",SkillIncrease) | AE42: =if((ISBLANK(AD42)),"",SkillIncrease) | AG42: =if((ISBLANK(AF42)),"",SkillIncrease) | AI42: =if((ISBLANK(AH42)),"",SkillIncrease) | AK42: =if((ISBLANK(AJ42)),"",SkillIncrease) | AM42: =if((ISBLANK(AL42)),"",SkillIncrease) | AO42: =if((ISBLANK(AN42)),"",SkillIncrease) | AQ42: =if((ISBLANK(AP42)),"",SkillIncrease) | AS42: =if((ISBLANK(AR42)),"",SkillIncrease) | AU42: =if((ISBLANK(AT42)),"",SkillIncrease) | AW42: =if((ISBLANK(AV42)),"",SkillIncrease) | AY42: =if((ISBLANK(AX42)),"",SkillIncrease) | BA42: =if((ISBLANK(AZ42)),"",SkillIncrease)
A43: SkillGrantArcana | B43: L00 | D43: Arcana (Int) | E43: =if((ISBLANK(D43)),"",SkillIncrease) -> 5 | G43: =if((ISBLANK(F43)),"",SkillIncrease) | I43: =if((ISBLANK(H43)),"",SkillIncrease) | K43: =if((ISBLANK(J43)),"",SkillIncrease) | M43: =if((ISBLANK(L43)),"",SkillIncrease) | O43: =if((ISBLANK(N43)),"",SkillIncrease) | Q43: =if((ISBLANK(P43)),"",SkillIncrease) | S43: =if((ISBLANK(R43)),"",SkillIncrease) | T43: Arcana (Int) | U43: =if((ISBLANK(T43)),"",SkillIncrease) -> 5 | W43: =if((ISBLANK(V43)),"",SkillIncrease) | Y43: =if((ISBLANK(X43)),"",SkillIncrease) | AA43: =if((ISBLANK(Z43)),"",SkillIncrease) | AC43: =if((ISBLANK(AB43)),"",SkillIncrease) | AE43: =if((ISBLANK(AD43)),"",SkillIncrease) | AG43: =if((ISBLANK(AF43)),"",SkillIncrease) | AH43: Arcana (Int) | AI43: =if((ISBLANK(AH43)),"",SkillIncrease) -> 5 | AK43: =if((ISBLANK(AJ43)),"",SkillIncrease) | AM43: =if((ISBLANK(AL43)),"",SkillIncrease) | AO43: =if((ISBLANK(AN43)),"",SkillIncrease) | AQ43: =if((ISBLANK(AP43)),"",SkillIncrease) | AS43: =if((ISBLANK(AR43)),"",SkillIncrease) | AU43: =if((ISBLANK(AT43)),"",SkillIncrease) | AV43: Arcana (Int) | AW43: =if((ISBLANK(AV43)),"",SkillIncrease) -> 5 | AY43: =if((ISBLANK(AX43)),"",SkillIncrease) | BA43: =if((ISBLANK(AZ43)),"",SkillIncrease)
A44: SkillGrantAthletics | B44: L00 | D44: Athletics (Str) | E44: =if((ISBLANK(D44)),"",SkillIncrease) -> 5 | G44: =if((ISBLANK(F44)),"",SkillIncrease) | I44: =if((ISBLANK(H44)),"",SkillIncrease) | K44: =if((ISBLANK(J44)),"",SkillIncrease) | L44: Athletics (Str) | M44: =if((ISBLANK(L44)),"",SkillIncrease) -> 5 | O44: =if((ISBLANK(N44)),"",SkillIncrease) | Q44: =if((ISBLANK(P44)),"",SkillIncrease) | S44: =if((ISBLANK(R44)),"",SkillIncrease) | U44: =if((ISBLANK(T44)),"",SkillIncrease) | W44: =if((ISBLANK(V44)),"",SkillIncrease) | Y44: =if((ISBLANK(X44)),"",SkillIncrease) | AA44: =if((ISBLANK(Z44)),"",SkillIncrease) | AC44: =if((ISBLANK(AB44)),"",SkillIncrease) | AE44: =if((ISBLANK(AD44)),"",SkillIncrease) | AG44: =if((ISBLANK(AF44)),"",SkillIncrease) | AI44: =if((ISBLANK(AH44)),"",SkillIncrease) | AK44: =if((ISBLANK(AJ44)),"",SkillIncrease) | AM44: =if((ISBLANK(AL44)),"",SkillIncrease) | AO44: =if((ISBLANK(AN44)),"",SkillIncrease) | AQ44: =if((ISBLANK(AP44)),"",SkillIncrease) | AS44: =if((ISBLANK(AR44)),"",SkillIncrease) | AU44: =if((ISBLANK(AT44)),"",SkillIncrease) | AW44: =if((ISBLANK(AV44)),"",SkillIncrease) | AY44: =if((ISBLANK(AX44)),"",SkillIncrease) | BA44: =if((ISBLANK(AZ44)),"",SkillIncrease)
A45: SkillGrantCrafting | B45: L00 | D45: Crafting (Int) | E45: =if((ISBLANK(D45)),"",SkillIncrease) -> 5 | G45: =if((ISBLANK(F45)),"",SkillIncrease) | I45: =if((ISBLANK(H45)),"",SkillIncrease) | K45: =if((ISBLANK(J45)),"",SkillIncrease) | M45: =if((ISBLANK(L45)),"",SkillIncrease) | O45: =if((ISBLANK(N45)),"",SkillIncrease) | Q45: =if((ISBLANK(P45)),"",SkillIncrease) | S45: =if((ISBLANK(R45)),"",SkillIncrease) | U45: =if((ISBLANK(T45)),"",SkillIncrease) | W45: =if((ISBLANK(V45)),"",SkillIncrease) | Y45: =if((ISBLANK(X45)),"",SkillIncrease) | Z45: Crafting (Int) | AA45: =if((ISBLANK(Z45)),"",SkillIncrease) -> 5 | AB45: Crafting (Int) | AC45: =if((ISBLANK(AB45)),"",SkillIncrease) -> 5 | AE45: =if((ISBLANK(AD45)),"",SkillIncrease) | AG45: =if((ISBLANK(AF45)),"",SkillIncrease) | AI45: =if((ISBLANK(AH45)),"",SkillIncrease) | AK45: =if((ISBLANK(AJ45)),"",SkillIncrease) | AM45: =if((ISBLANK(AL45)),"",SkillIncrease) | AO45: =if((ISBLANK(AN45)),"",SkillIncrease) | AQ45: =if((ISBLANK(AP45)),"",SkillIncrease) | AS45: =if((ISBLANK(AR45)),"",SkillIncrease) | AU45: =if((ISBLANK(AT45)),"",SkillIncrease) | AW45: =if((ISBLANK(AV45)),"",SkillIncrease) | AY45: =if((ISBLANK(AX45)),"",SkillIncrease) | BA45: =if((ISBLANK(AZ45)),"",SkillIncrease)
A46: SkillGrantDeception | B46: L00 | D46: Deception (Cha) | E46: =if((ISBLANK(D46)),"",SkillIncrease) -> 5 | G46: =if((ISBLANK(F46)),"",SkillIncrease) | I46: =if((ISBLANK(H46)),"",SkillIncrease) | K46: =if((ISBLANK(J46)),"",SkillIncrease) | M46: =if((ISBLANK(L46)),"",SkillIncrease) | O46: =if((ISBLANK(N46)),"",SkillIncrease) | Q46: =if((ISBLANK(P46)),"",SkillIncrease) | S46: =if((ISBLANK(R46)),"",SkillIncrease) | U46: =if((ISBLANK(T46)),"",SkillIncrease) | W46: =if((ISBLANK(V46)),"",SkillIncrease) | Y46: =if((ISBLANK(X46)),"",SkillIncrease) | AA46: =if((ISBLANK(Z46)),"",SkillIncrease) | AC46: =if((ISBLANK(AB46)),"",SkillIncrease) | AE46: =if((ISBLANK(AD46)),"",SkillIncrease) | AG46: =if((ISBLANK(AF46)),"",SkillIncrease) | AI46: =if((ISBLANK(AH46)),"",SkillIncrease) | AK46: =if((ISBLANK(AJ46)),"",SkillIncrease) | AM46: =if((ISBLANK(AL46)),"",SkillIncrease) | AO46: =if((ISBLANK(AN46)),"",SkillIncrease) | AQ46: =if((ISBLANK(AP46)),"",SkillIncrease) | AS46: =if((ISBLANK(AR46)),"",SkillIncrease) | AU46: =if((ISBLANK(AT46)),"",SkillIncrease) | AW46: =if((ISBLANK(AV46)),"",SkillIncrease) | AY46: =if((ISBLANK(AX46)),"",SkillIncrease) | BA46: =if((ISBLANK(AZ46)),"",SkillIncrease)
A47: SkillGrantDiplomacy | B47: L00 | D47: Diplomacy (Cha) | E47: =if((ISBLANK(D47)),"",SkillIncrease) -> 5 | G47: =if((ISBLANK(F47)),"",SkillIncrease) | I47: =if((ISBLANK(H47)),"",SkillIncrease) | K47: =if((ISBLANK(J47)),"",SkillIncrease) | M47: =if((ISBLANK(L47)),"",SkillIncrease) | O47: =if((ISBLANK(N47)),"",SkillIncrease) | Q47: =if((ISBLANK(P47)),"",SkillIncrease) | S47: =if((ISBLANK(R47)),"",SkillIncrease) | U47: =if((ISBLANK(T47)),"",SkillIncrease) | W47: =if((ISBLANK(V47)),"",SkillIncrease) | Y47: =if((ISBLANK(X47)),"",SkillIncrease) | AA47: =if((ISBLANK(Z47)),"",SkillIncrease) | AC47: =if((ISBLANK(AB47)),"",SkillIncrease) | AE47: =if((ISBLANK(AD47)),"",SkillIncrease) | AG47: =if((ISBLANK(AF47)),"",SkillIncrease) | AI47: =if((ISBLANK(AH47)),"",SkillIncrease) | AK47: =if((ISBLANK(AJ47)),"",SkillIncrease) | AM47: =if((ISBLANK(AL47)),"",SkillIncrease) | AO47: =if((ISBLANK(AN47)),"",SkillIncrease) | AQ47: =if((ISBLANK(AP47)),"",SkillIncrease) | AS47: =if((ISBLANK(AR47)),"",SkillIncrease) | AU47: =if((ISBLANK(AT47)),"",SkillIncrease) | AW47: =if((ISBLANK(AV47)),"",SkillIncrease) | AY47: =if((ISBLANK(AX47)),"",SkillIncrease) | BA47: =if((ISBLANK(AZ47)),"",SkillIncrease)
A48: SkillGrantIntimidation | B48: L00 | D48: Intimidation (Cha) | E48: =if((ISBLANK(D48)),"",SkillIncrease) -> 5 | G48: =if((ISBLANK(F48)),"",SkillIncrease) | I48: =if((ISBLANK(H48)),"",SkillIncrease) | K48: =if((ISBLANK(J48)),"",SkillIncrease) | M48: =if((ISBLANK(L48)),"",SkillIncrease) | O48: =if((ISBLANK(N48)),"",SkillIncrease) | Q48: =if((ISBLANK(P48)),"",SkillIncrease) | S48: =if((ISBLANK(R48)),"",SkillIncrease) | U48: =if((ISBLANK(T48)),"",SkillIncrease) | W48: =if((ISBLANK(V48)),"",SkillIncrease) | Y48: =if((ISBLANK(X48)),"",SkillIncrease) | AA48: =if((ISBLANK(Z48)),"",SkillIncrease) | AC48: =if((ISBLANK(AB48)),"",SkillIncrease) | AE48: =if((ISBLANK(AD48)),"",SkillIncrease) | AG48: =if((ISBLANK(AF48)),"",SkillIncrease) | AI48: =if((ISBLANK(AH48)),"",SkillIncrease) | AK48: =if((ISBLANK(AJ48)),"",SkillIncrease) | AM48: =if((ISBLANK(AL48)),"",SkillIncrease) | AO48: =if((ISBLANK(AN48)),"",SkillIncrease) | AQ48: =if((ISBLANK(AP48)),"",SkillIncrease) | AS48: =if((ISBLANK(AR48)),"",SkillIncrease) | AU48: =if((ISBLANK(AT48)),"",SkillIncrease) | AW48: =if((ISBLANK(AV48)),"",SkillIncrease) | AY48: =if((ISBLANK(AX48)),"",SkillIncrease) | BA48: =if((ISBLANK(AZ48)),"",SkillIncrease)
A49: SkillGrantLore | B49: L00 | D49: Lore (Int) | E49: =if((ISBLANK(D49)),"",SkillIncrease) -> 5 | G49: =if((ISBLANK(F49)),"",SkillIncrease) | I49: =if((ISBLANK(H49)),"",SkillIncrease) | K49: =if((ISBLANK(J49)),"",SkillIncrease) | M49: =if((ISBLANK(L49)),"",SkillIncrease) | O49: =if((ISBLANK(N49)),"",SkillIncrease) | Q49: =if((ISBLANK(P49)),"",SkillIncrease) | S49: =if((ISBLANK(R49)),"",SkillIncrease) | T49: Esoteric Lore | U49: =if((ISBLANK(T49)),"",SkillIncrease) -> 5 | W49: =if((ISBLANK(V49)),"",SkillIncrease) | Y49: =if((ISBLANK(X49)),"",SkillIncrease) | AA49: =if((ISBLANK(Z49)),"",SkillIncrease) | AC49: =if((ISBLANK(AB49)),"",SkillIncrease) | AE49: =if((ISBLANK(AD49)),"",SkillIncrease) | AG49: =if((ISBLANK(AF49)),"",SkillIncrease) | AI49: =if((ISBLANK(AH49)),"",SkillIncrease) | AK49: =if((ISBLANK(AJ49)),"",SkillIncrease) | AM49: =if((ISBLANK(AL49)),"",SkillIncrease) | AO49: =if((ISBLANK(AN49)),"",SkillIncrease) | AQ49: =if((ISBLANK(AP49)),"",SkillIncrease) | AS49: =if((ISBLANK(AR49)),"",SkillIncrease) | AU49: =if((ISBLANK(AT49)),"",SkillIncrease) | AW49: =if((ISBLANK(AV49)),"",SkillIncrease) | AY49: =if((ISBLANK(AX49)),"",SkillIncrease) | BA49: =if((ISBLANK(AZ49)),"",SkillIncrease)
A50: SkillGrantMedicine | B50: L00 | D50: Medicine (Wis) | E50: =if((ISBLANK(D50)),"",SkillIncrease) -> 5 | G50: =if((ISBLANK(F50)),"",SkillIncrease) | I50: =if((ISBLANK(H50)),"",SkillIncrease) | K50: =if((ISBLANK(J50)),"",SkillIncrease) | M50: =if((ISBLANK(L50)),"",SkillIncrease) | O50: =if((ISBLANK(N50)),"",SkillIncrease) | Q50: =if((ISBLANK(P50)),"",SkillIncrease) | S50: =if((ISBLANK(R50)),"",SkillIncrease) | U50: =if((ISBLANK(T50)),"",SkillIncrease) | W50: =if((ISBLANK(V50)),"",SkillIncrease) | Y50: =if((ISBLANK(X50)),"",SkillIncrease) | AA50: =if((ISBLANK(Z50)),"",SkillIncrease) | AC50: =if((ISBLANK(AB50)),"",SkillIncrease) | AE50: =if((ISBLANK(AD50)),"",SkillIncrease) | AG50: =if((ISBLANK(AF50)),"",SkillIncrease) | AI50: =if((ISBLANK(AH50)),"",SkillIncrease) | AK50: =if((ISBLANK(AJ50)),"",SkillIncrease) | AM50: =if((ISBLANK(AL50)),"",SkillIncrease) | AO50: =if((ISBLANK(AN50)),"",SkillIncrease) | AQ50: =if((ISBLANK(AP50)),"",SkillIncrease) | AS50: =if((ISBLANK(AR50)),"",SkillIncrease) | AU50: =if((ISBLANK(AT50)),"",SkillIncrease) | AW50: =if((ISBLANK(AV50)),"",SkillIncrease) | AY50: =if((ISBLANK(AX50)),"",SkillIncrease) | BA50: =if((ISBLANK(AZ50)),"",SkillIncrease)
A51: SkillGrantNature | B51: L00 | D51: Nature (Wis) | E51: =if((ISBLANK(D51)),"",SkillIncrease) -> 5 | G51: =if((ISBLANK(F51)),"",SkillIncrease) | I51: =if((ISBLANK(H51)),"",SkillIncrease) | K51: =if((ISBLANK(J51)),"",SkillIncrease) | M51: =if((ISBLANK(L51)),"",SkillIncrease) | N51: Nature (Wis) | O51: =if((ISBLANK(N51)),"",SkillIncrease) -> 5 | Q51: =if((ISBLANK(P51)),"",SkillIncrease) | S51: =if((ISBLANK(R51)),"",SkillIncrease) | T51: Nature (Wis) | U51: =if((ISBLANK(T51)),"",SkillIncrease) -> 5 | W51: =if((ISBLANK(V51)),"",SkillIncrease) | Y51: =if((ISBLANK(X51)),"",SkillIncrease) | AA51: =if((ISBLANK(Z51)),"",SkillIncrease) | AC51: =if((ISBLANK(AB51)),"",SkillIncrease) | AD51: Nature (Wis) | AE51: =if((ISBLANK(AD51)),"",SkillIncrease) -> 5 | AG51: =if((ISBLANK(AF51)),"",SkillIncrease) | AI51: =if((ISBLANK(AH51)),"",SkillIncrease) | AK51: =if((ISBLANK(AJ51)),"",SkillIncrease) | AM51: =if((ISBLANK(AL51)),"",SkillIncrease) | AO51: =if((ISBLANK(AN51)),"",SkillIncrease) | AQ51: =if((ISBLANK(AP51)),"",SkillIncrease) | AR51: Nature (Wis) | AS51: =if((ISBLANK(AR51)),"",SkillIncrease) -> 5 | AU51: =if((ISBLANK(AT51)),"",SkillIncrease) | AW51: =if((ISBLANK(AV51)),"",SkillIncrease) | AY51: =if((ISBLANK(AX51)),"",SkillIncrease) | BA51: =if((ISBLANK(AZ51)),"",SkillIncrease)
A52: SkillGrantOccultism | B52: L00 | D52: Occultism (Int) | E52: =if((ISBLANK(D52)),"",SkillIncrease) -> 5 | G52: =if((ISBLANK(F52)),"",SkillIncrease) | I52: =if((ISBLANK(H52)),"",SkillIncrease) | K52: =if((ISBLANK(J52)),"",SkillIncrease) | M52: =if((ISBLANK(L52)),"",SkillIncrease) | O52: =if((ISBLANK(N52)),"",SkillIncrease) | Q52: =if((ISBLANK(P52)),"",SkillIncrease) | S52: =if((ISBLANK(R52)),"",SkillIncrease) | T52: Occultism (Int) | U52: =if((ISBLANK(T52)),"",SkillIncrease) -> 5 | W52: =if((ISBLANK(V52)),"",SkillIncrease) | Y52: =if((ISBLANK(X52)),"",SkillIncrease) | AA52: =if((ISBLANK(Z52)),"",SkillIncrease) | AC52: =if((ISBLANK(AB52)),"",SkillIncrease) | AE52: =if((ISBLANK(AD52)),"",SkillIncrease) | AG52: =if((ISBLANK(AF52)),"",SkillIncrease) | AI52: =if((ISBLANK(AH52)),"",SkillIncrease) | AK52: =if((ISBLANK(AJ52)),"",SkillIncrease) | AM52: =if((ISBLANK(AL52)),"",SkillIncrease) | AN52: Occultism (Int) | AO52: =if((ISBLANK(AN52)),"",SkillIncrease) -> 5 | AQ52: =if((ISBLANK(AP52)),"",SkillIncrease) | AS52: =if((ISBLANK(AR52)),"",SkillIncrease) | AT52: Occultism (Int) | AU52: =if((ISBLANK(AT52)),"",SkillIncrease) -> 5 | AW52: =if((ISBLANK(AV52)),"",SkillIncrease) | AY52: =if((ISBLANK(AX52)),"",SkillIncrease) | BA52: =if((ISBLANK(AZ52)),"",SkillIncrease)
A53: SkillGrantPerformance | B53: L00 | D53: Performance (Cha) | E53: =if((ISBLANK(D53)),"",SkillIncrease) -> 5 | G53: =if((ISBLANK(F53)),"",SkillIncrease) | I53: =if((ISBLANK(H53)),"",SkillIncrease) | K53: =if((ISBLANK(J53)),"",SkillIncrease) | M53: =if((ISBLANK(L53)),"",SkillIncrease) | O53: =if((ISBLANK(N53)),"",SkillIncrease) | Q53: =if((ISBLANK(P53)),"",SkillIncrease) | S53: =if((ISBLANK(R53)),"",SkillIncrease) | U53: =if((ISBLANK(T53)),"",SkillIncrease) | W53: =if((ISBLANK(V53)),"",SkillIncrease) | Y53: =if((ISBLANK(X53)),"",SkillIncrease) | AA53: =if((ISBLANK(Z53)),"",SkillIncrease) | AC53: =if((ISBLANK(AB53)),"",SkillIncrease) | AE53: =if((ISBLANK(AD53)),"",SkillIncrease) | AG53: =if((ISBLANK(AF53)),"",SkillIncrease) | AI53: =if((ISBLANK(AH53)),"",SkillIncrease) | AK53: =if((ISBLANK(AJ53)),"",SkillIncrease) | AM53: =if((ISBLANK(AL53)),"",SkillIncrease) | AN53: Performance (Cha) | AO53: =if((ISBLANK(AN53)),"",SkillIncrease) -> 5 | AQ53: =if((ISBLANK(AP53)),"",SkillIncrease) | AS53: =if((ISBLANK(AR53)),"",SkillIncrease) | AU53: =if((ISBLANK(AT53)),"",SkillIncrease) | AW53: =if((ISBLANK(AV53)),"",SkillIncrease) | AY53: =if((ISBLANK(AX53)),"",SkillIncrease) | BA53: =if((ISBLANK(AZ53)),"",SkillIncrease)
A54: SkillGrantReligion | B54: L00 | D54: Religion (Wis) | E54: =if((ISBLANK(D54)),"",SkillIncrease) -> 5 | F54: Religion (Wis) | G54: =if((ISBLANK(F54)),"",SkillIncrease) -> 5 | I54: =if((ISBLANK(H54)),"",SkillIncrease) | K54: =if((ISBLANK(J54)),"",SkillIncrease) | M54: =if((ISBLANK(L54)),"",SkillIncrease) | O54: =if((ISBLANK(N54)),"",SkillIncrease) | Q54: =if((ISBLANK(P54)),"",SkillIncrease) | S54: =if((ISBLANK(R54)),"",SkillIncrease) | T54: Religion (Wis) | U54: =if((ISBLANK(T54)),"",SkillIncrease) -> 5 | W54: =if((ISBLANK(V54)),"",SkillIncrease) | Y54: =if((ISBLANK(X54)),"",SkillIncrease) | AA54: =if((ISBLANK(Z54)),"",SkillIncrease) | AC54: =if((ISBLANK(AB54)),"",SkillIncrease) | AE54: =if((ISBLANK(AD54)),"",SkillIncrease) | AG54: =if((ISBLANK(AF54)),"",SkillIncrease) | AI54: =if((ISBLANK(AH54)),"",SkillIncrease) | AJ54: Religion (Wis) | AK54: =if((ISBLANK(AJ54)),"",SkillIncrease) -> 5 | AL54: Religion (Wis) | AM54: =if((ISBLANK(AL54)),"",SkillIncrease) -> 5 | AO54: =if((ISBLANK(AN54)),"",SkillIncrease) | AP54: Religion (Wis) | AQ54: =if((ISBLANK(AP54)),"",SkillIncrease) -> 5 | AS54: =if((ISBLANK(AR54)),"",SkillIncrease) | AU54: =if((ISBLANK(AT54)),"",SkillIncrease) | AW54: =if((ISBLANK(AV54)),"",SkillIncrease) | AY54: =if((ISBLANK(AX54)),"",SkillIncrease) | BA54: =if((ISBLANK(AZ54)),"",SkillIncrease)
A55: SkillGrantSociety | B55: L00 | D55: Society (Int) | E55: =if((ISBLANK(D55)),"",SkillIncrease) -> 5 | G55: =if((ISBLANK(F55)),"",SkillIncrease) | I55: =if((ISBLANK(H55)),"",SkillIncrease) | K55: =if((ISBLANK(J55)),"",SkillIncrease) | M55: =if((ISBLANK(L55)),"",SkillIncrease) | O55: =if((ISBLANK(N55)),"",SkillIncrease) | Q55: =if((ISBLANK(P55)),"",SkillIncrease) | R55: Society (Int) | S55: =if((ISBLANK(R55)),"",SkillIncrease) -> 5 | U55: =if((ISBLANK(T55)),"",SkillIncrease) | W55: =if((ISBLANK(V55)),"",SkillIncrease) | Y55: =if((ISBLANK(X55)),"",SkillIncrease) | AA55: =if((ISBLANK(Z55)),"",SkillIncrease) | AC55: =if((ISBLANK(AB55)),"",SkillIncrease) | AE55: =if((ISBLANK(AD55)),"",SkillIncrease) | AG55: =if((ISBLANK(AF55)),"",SkillIncrease) | AI55: =if((ISBLANK(AH55)),"",SkillIncrease) | AK55: =if((ISBLANK(AJ55)),"",SkillIncrease) | AM55: =if((ISBLANK(AL55)),"",SkillIncrease) | AO55: =if((ISBLANK(AN55)),"",SkillIncrease) | AQ55: =if((ISBLANK(AP55)),"",SkillIncrease) | AS55: =if((ISBLANK(AR55)),"",SkillIncrease) | AU55: =if((ISBLANK(AT55)),"",SkillIncrease) | AW55: =if((ISBLANK(AV55)),"",SkillIncrease) | AY55: =if((ISBLANK(AX55)),"",SkillIncrease) | BA55: =if((ISBLANK(AZ55)),"",SkillIncrease)
A56: SkillGrantStealth | B56: L00 | D56: Stealth (Dex) | E56: =if((ISBLANK(D56)),"",SkillIncrease) -> 5 | G56: =if((ISBLANK(F56)),"",SkillIncrease) | I56: =if((ISBLANK(H56)),"",SkillIncrease) | K56: =if((ISBLANK(J56)),"",SkillIncrease) | M56: =if((ISBLANK(L56)),"",SkillIncrease) | O56: =if((ISBLANK(N56)),"",SkillIncrease) | P56: Stealth (Dex) | Q56: =if((ISBLANK(P56)),"",SkillIncrease) -> 5 | S56: =if((ISBLANK(R56)),"",SkillIncrease) | U56: =if((ISBLANK(T56)),"",SkillIncrease) | W56: =if((ISBLANK(V56)),"",SkillIncrease) | Y56: =if((ISBLANK(X56)),"",SkillIncrease) | AA56: =if((ISBLANK(Z56)),"",SkillIncrease) | AC56: =if((ISBLANK(AB56)),"",SkillIncrease) | AE56: =if((ISBLANK(AD56)),"",SkillIncrease) | AG56: =if((ISBLANK(AF56)),"",SkillIncrease) | AI56: =if((ISBLANK(AH56)),"",SkillIncrease) | AK56: =if((ISBLANK(AJ56)),"",SkillIncrease) | AM56: =if((ISBLANK(AL56)),"",SkillIncrease) | AO56: =if((ISBLANK(AN56)),"",SkillIncrease) | AQ56: =if((ISBLANK(AP56)),"",SkillIncrease) | AS56: =if((ISBLANK(AR56)),"",SkillIncrease) | AU56: =if((ISBLANK(AT56)),"",SkillIncrease) | AW56: =if((ISBLANK(AV56)),"",SkillIncrease) | AY56: =if((ISBLANK(AX56)),"",SkillIncrease) | BA56: =if((ISBLANK(AZ56)),"",SkillIncrease)
A57: SkillGrantSurvival | B57: L00 | D57: Survival (Wis) | E57: =if((ISBLANK(D57)),"",SkillIncrease) -> 5 | G57: =if((ISBLANK(F57)),"",SkillIncrease) | I57: =if((ISBLANK(H57)),"",SkillIncrease) | K57: =if((ISBLANK(J57)),"",SkillIncrease) | M57: =if((ISBLANK(L57)),"",SkillIncrease) | N57: Survival (Wis) | O57: =if((ISBLANK(N57)),"",SkillIncrease) -> 5 | Q57: =if((ISBLANK(P57)),"",SkillIncrease) | S57: =if((ISBLANK(R57)),"",SkillIncrease) | U57: =if((ISBLANK(T57)),"",SkillIncrease) | W57: =if((ISBLANK(V57)),"",SkillIncrease) | Y57: =if((ISBLANK(X57)),"",SkillIncrease) | AA57: =if((ISBLANK(Z57)),"",SkillIncrease) | AC57: =if((ISBLANK(AB57)),"",SkillIncrease) | AE57: =if((ISBLANK(AD57)),"",SkillIncrease) | AG57: =if((ISBLANK(AF57)),"",SkillIncrease) | AI57: =if((ISBLANK(AH57)),"",SkillIncrease) | AK57: =if((ISBLANK(AJ57)),"",SkillIncrease) | AM57: =if((ISBLANK(AL57)),"",SkillIncrease) | AO57: =if((ISBLANK(AN57)),"",SkillIncrease) | AQ57: =if((ISBLANK(AP57)),"",SkillIncrease) | AS57: =if((ISBLANK(AR57)),"",SkillIncrease) | AU57: =if((ISBLANK(AT57)),"",SkillIncrease) | AW57: =if((ISBLANK(AV57)),"",SkillIncrease) | AY57: =if((ISBLANK(AX57)),"",SkillIncrease) | BA57: =if((ISBLANK(AZ57)),"",SkillIncrease)
A58: SkillGrantThievery | B58: L00 | D58: Thievery (Dex) | E58: =if((ISBLANK(D58)),"",SkillIncrease) -> 5 | G58: =if((ISBLANK(F58)),"",SkillIncrease) | I58: =if((ISBLANK(H58)),"",SkillIncrease) | K58: =if((ISBLANK(J58)),"",SkillIncrease) | M58: =if((ISBLANK(L58)),"",SkillIncrease) | O58: =if((ISBLANK(N58)),"",SkillIncrease) | Q58: =if((ISBLANK(P58)),"",SkillIncrease) | S58: =if((ISBLANK(R58)),"",SkillIncrease) | U58: =if((ISBLANK(T58)),"",SkillIncrease) | W58: =if((ISBLANK(V58)),"",SkillIncrease) | Y58: =if((ISBLANK(X58)),"",SkillIncrease) | AA58: =if((ISBLANK(Z58)),"",SkillIncrease) | AC58: =if((ISBLANK(AB58)),"",SkillIncrease) | AE58: =if((ISBLANK(AD58)),"",SkillIncrease) | AG58: =if((ISBLANK(AF58)),"",SkillIncrease) | AI58: =if((ISBLANK(AH58)),"",SkillIncrease) | AK58: =if((ISBLANK(AJ58)),"",SkillIncrease) | AM58: =if((ISBLANK(AL58)),"",SkillIncrease) | AO58: =if((ISBLANK(AN58)),"",SkillIncrease) | AQ58: =if((ISBLANK(AP58)),"",SkillIncrease) | AS58: =if((ISBLANK(AR58)),"",SkillIncrease) | AU58: =if((ISBLANK(AT58)),"",SkillIncrease) | AW58: =if((ISBLANK(AV58)),"",SkillIncrease) | AY58: =if((ISBLANK(AX58)),"",SkillIncrease) | BA58: =if((ISBLANK(AZ58)),"",SkillIncrease)
A59: SkillsGrantedTotal | B59: L00 | D59: =(COUNTA(D42:D58))+D41+D40 -> 19 | E59: =SUM(E40:E58) -> 95 | F59: =(COUNTA(F42:F58))+F41+F40 -> 4 | G59: =SUM(G40:G58) -> 20 | H59: =(COUNTA(H42:H58))+H41+H40 -> 4 | I59: =SUM(I40:I58) -> 20 | J59: =(COUNTA(J42:J58))+J41+J40 -> 4 | K59: =SUM(K40:K58) -> 20 | L59: =(COUNTA(L42:L58))+L41+L40 -> 4 | M59: =SUM(M40:M58) -> 20 | N59: =(COUNTA(N42:N58))+N41+N40 -> 6 | O59: =SUM(O40:O58) -> 30 | P59: =(COUNTA(P42:P58))+P41+P40 -> 9 | Q59: =SUM(Q40:Q58) -> 40 | R59: =(COUNTA(R42:R58))+R41+R40 -> 6 | S59: =SUM(S40:S58) -> 25 | T59: =(COUNTA(T42:T58))+T41+T40 -> 8 | U59: =SUM(U40:U58) -> 40 | V59: =(COUNTA(V42:V58))+V41+V40 -> 6 | W59: =SUM(W40:W58) -> 25 | X59: =(COUNTA(X42:X58))+X41+X40 -> 4 | Y59: =SUM(Y40:Y58) -> 20 | Z59: =(COUNTA(Z42:Z58))+Z41+Z40 -> 4 | AA59: =SUM(AA40:AA58) -> 20 | AB59: =(COUNTA(AB42:AB58))+AB41+AB40 -> 4 | AC59: =SUM(AC40:AC58) -> 20 | AE59: =SUM(AE40:AE58) -> 20 | AF59: =(COUNTA(AF42:AF58))+AF41+AF40 -> 5 | AG59: =SUM(AG40:AG58) -> 25 | AH59: =(COUNTA(AH42:AH58))+AH41+AH40 -> 3 | AI59: =SUM(AI40:AI58) -> 15 | AJ59: =(COUNTA(AJ42:AJ58))+AJ41+AJ40 -> 4 | AK59: =SUM(AK40:AK58) -> 20 | AL59: =(COUNTA(AL42:AL58))+AL41+AL40 -> 4 | AM59: =SUM(AM40:AM58) -> 20 | AN59: =(COUNTA(AN42:AN58))+AN41+AN40 -> 6 | AO59: =SUM(AO40:AO58) -> 30 | AP59: =(COUNTA(AP42:AP58))+AP41+AP40 -> 5 | AQ59: =SUM(AQ40:AQ58) -> 25 | AR59: =(COUNTA(AR42:AR58))+AR41+AR40 -> 4 | AS59: =SUM(AS40:AS58) -> 20 | AT59: =(COUNTA(AT42:AT58))+AT41+AT40 -> 4 | AU59: =SUM(AU40:AU58) -> 20 | AV59: =(COUNTA(AV42:AV58))+AV41+AV40 -> 3 | AW59: =SUM(AW40:AW58) -> 15 | AX59: =(COUNTA(AX42:AX58))+AX41+AX40 -> 4 | AY59: =SUM(AY40:AY58) -> 20 | AZ59: =(COUNTA(AZ42:AZ58))+AZ41+AZ40 -> 4 | BA59: =SUM(BA40:BA58) -> 20
A60: SkillIncreaseExtra-L02 | B60: L02 | D60: 1 | E60: =if((ISBLANK(D60)),"",SkillIncrease) -> 5 | G60: =if((ISBLANK(F60)),"",SkillIncrease) | I60: =if((ISBLANK(H60)),"",SkillIncrease) | K60: =if((ISBLANK(J60)),"",SkillIncrease) | M60: =if((ISBLANK(L60)),"",SkillIncrease) | O60: =if((ISBLANK(N60)),"",SkillIncrease) | P60: 1 | Q60: =if((ISBLANK(P60)),"",SkillIncrease) -> 5 | R60: 1 | S60: =if((ISBLANK(R60)),"",SkillIncrease) -> 5 | U60: =if((ISBLANK(T60)),"",SkillIncrease) | W60: =if((ISBLANK(V60)),"",SkillIncrease) | Y60: =if((ISBLANK(X60)),"",SkillIncrease) | AA60: =if((ISBLANK(Z60)),"",SkillIncrease) | AC60: =if((ISBLANK(AB60)),"",SkillIncrease) | AE60: =if((ISBLANK(AD60)),"",SkillIncrease) | AG60: =if((ISBLANK(AF60)),"",SkillIncrease) | AI60: =if((ISBLANK(AH60)),"",SkillIncrease) | AK60: =if((ISBLANK(AJ60)),"",SkillIncrease) | AM60: =if((ISBLANK(AL60)),"",SkillIncrease) | AO60: =if((ISBLANK(AN60)),"",SkillIncrease) | AQ60: =if((ISBLANK(AP60)),"",SkillIncrease) | AS60: =if((ISBLANK(AR60)),"",SkillIncrease) | AU60: =if((ISBLANK(AT60)),"",SkillIncrease) | AW60: =if((ISBLANK(AV60)),"",SkillIncrease) | AY60: =if((ISBLANK(AX60)),"",SkillIncrease) | BA60: =if((ISBLANK(AZ60)),"",SkillIncrease)
A61: SkillIncreaseExtra-L03 | B61: L03 | D61: 1 | E61: =if((ISBLANK(D61)),"",SkillIncrease) -> 5 | G61: =if((ISBLANK(F61)),"",SkillIncrease) | I61: =if((ISBLANK(H61)),"",SkillIncrease) | K61: =if((ISBLANK(J61)),"",SkillIncrease) | M61: =if((ISBLANK(L61)),"",SkillIncrease) | O61: =if((ISBLANK(N61)),"",SkillIncrease) | Q61: =if((ISBLANK(P61)),"",SkillIncrease) | S61: =if((ISBLANK(R61)),"",SkillIncrease) | T61: 1 | U61: =if((ISBLANK(T61)),"",SkillIncrease) -> 5 | W61: =if((ISBLANK(V61)),"",SkillIncrease) | Y61: =if((ISBLANK(X61)),"",SkillIncrease) | Z61: 1 | AA61: =if((ISBLANK(Z61)),"",SkillIncrease) -> 5 | AC61: =if((ISBLANK(AB61)),"",SkillIncrease) | AE61: =if((ISBLANK(AD61)),"",SkillIncrease) | AG61: =if((ISBLANK(AF61)),"",SkillIncrease) | AI61: =if((ISBLANK(AH61)),"",SkillIncrease) | AK61: =if((ISBLANK(AJ61)),"",SkillIncrease) | AM61: =if((ISBLANK(AL61)),"",SkillIncrease) | AO61: =if((ISBLANK(AN61)),"",SkillIncrease) | AQ61: =if((ISBLANK(AP61)),"",SkillIncrease) | AS61: =if((ISBLANK(AR61)),"",SkillIncrease) | AU61: =if((ISBLANK(AT61)),"",SkillIncrease) | AW61: =if((ISBLANK(AV61)),"",SkillIncrease) | AY61: =if((ISBLANK(AX61)),"",SkillIncrease) | BA61: =if((ISBLANK(AZ61)),"",SkillIncrease)
A62: SkillIncreaseExtra-L04 | B62: L04 | D62: 1 | E62: =if((ISBLANK(D62)),"",SkillIncrease) -> 5 | G62: =if((ISBLANK(F62)),"",SkillIncrease) | I62: =if((ISBLANK(H62)),"",SkillIncrease) | K62: =if((ISBLANK(J62)),"",SkillIncrease) | M62: =if((ISBLANK(L62)),"",SkillIncrease) | O62: =if((ISBLANK(N62)),"",SkillIncrease) | P62: 1 | Q62: =if((ISBLANK(P62)),"",SkillIncrease) -> 5 | R62: 1 | S62: =if((ISBLANK(R62)),"",SkillIncrease) -> 5 | U62: =if((ISBLANK(T62)),"",SkillIncrease) | W62: =if((ISBLANK(V62)),"",SkillIncrease) | Y62: =if((ISBLANK(X62)),"",SkillIncrease) | AA62: =if((ISBLANK(Z62)),"",SkillIncrease) | AC62: =if((ISBLANK(AB62)),"",SkillIncrease) | AE62: =if((ISBLANK(AD62)),"",SkillIncrease) | AG62: =if((ISBLANK(AF62)),"",SkillIncrease) | AI62: =if((ISBLANK(AH62)),"",SkillIncrease) | AK62: =if((ISBLANK(AJ62)),"",SkillIncrease) | AM62: =if((ISBLANK(AL62)),"",SkillIncrease) | AO62: =if((ISBLANK(AN62)),"",SkillIncrease) | AQ62: =if((ISBLANK(AP62)),"",SkillIncrease) | AS62: =if((ISBLANK(AR62)),"",SkillIncrease) | AU62: =if((ISBLANK(AT62)),"",SkillIncrease) | AW62: =if((ISBLANK(AV62)),"",SkillIncrease) | AY62: =if((ISBLANK(AX62)),"",SkillIncrease) | BA62: =if((ISBLANK(AZ62)),"",SkillIncrease)
A63: SkillIncreaseExtra-L05 | B63: L05 | D63: 1 | E63: =if((ISBLANK(D63)),"",SkillIncrease) -> 5 | G63: =if((ISBLANK(F63)),"",SkillIncrease) | I63: =if((ISBLANK(H63)),"",SkillIncrease) | K63: =if((ISBLANK(J63)),"",SkillIncrease) | M63: =if((ISBLANK(L63)),"",SkillIncrease) | O63: =if((ISBLANK(N63)),"",SkillIncrease) | Q63: =if((ISBLANK(P63)),"",SkillIncrease) | S63: =if((ISBLANK(R63)),"",SkillIncrease) | U63: =if((ISBLANK(T63)),"",SkillIncrease) | W63: =if((ISBLANK(V63)),"",SkillIncrease) | Y63: =if((ISBLANK(X63)),"",SkillIncrease) | AA63: =if((ISBLANK(Z63)),"",SkillIncrease) | AC63: =if((ISBLANK(AB63)),"",SkillIncrease) | AE63: =if((ISBLANK(AD63)),"",SkillIncrease) | AG63: =if((ISBLANK(AF63)),"",SkillIncrease) | AI63: =if((ISBLANK(AH63)),"",SkillIncrease) | AK63: =if((ISBLANK(AJ63)),"",SkillIncrease) | AM63: =if((ISBLANK(AL63)),"",SkillIncrease) | AO63: =if((ISBLANK(AN63)),"",SkillIncrease) | AQ63: =if((ISBLANK(AP63)),"",SkillIncrease) | AS63: =if((ISBLANK(AR63)),"",SkillIncrease) | AU63: =if((ISBLANK(AT63)),"",SkillIncrease) | AW63: =if((ISBLANK(AV63)),"",SkillIncrease) | AY63: =if((ISBLANK(AX63)),"",SkillIncrease) | BA63: =if((ISBLANK(AZ63)),"",SkillIncrease)
A64: SkillIncreaseExtra-L06 | B64: L06 | D64: 1 | E64: =if((ISBLANK(D64)),"",SkillIncrease) -> 5 | G64: =if((ISBLANK(F64)),"",SkillIncrease) | I64: =if((ISBLANK(H64)),"",SkillIncrease) | K64: =if((ISBLANK(J64)),"",SkillIncrease) | M64: =if((ISBLANK(L64)),"",SkillIncrease) | O64: =if((ISBLANK(N64)),"",SkillIncrease) | P64: 1 | Q64: =if((ISBLANK(P64)),"",SkillIncrease) -> 5 | R64: 1 | S64: =if((ISBLANK(R64)),"",SkillIncrease) -> 5 | U64: =if((ISBLANK(T64)),"",SkillIncrease) | W64: =if((ISBLANK(V64)),"",SkillIncrease) | Y64: =if((ISBLANK(X64)),"",SkillIncrease) | AA64: =if((ISBLANK(Z64)),"",SkillIncrease) | AC64: =if((ISBLANK(AB64)),"",SkillIncrease) | AE64: =if((ISBLANK(AD64)),"",SkillIncrease) | AG64: =if((ISBLANK(AF64)),"",SkillIncrease) | AI64: =if((ISBLANK(AH64)),"",SkillIncrease) | AK64: =if((ISBLANK(AJ64)),"",SkillIncrease) | AM64: =if((ISBLANK(AL64)),"",SkillIncrease) | AO64: =if((ISBLANK(AN64)),"",SkillIncrease) | AQ64: =if((ISBLANK(AP64)),"",SkillIncrease) | AS64: =if((ISBLANK(AR64)),"",SkillIncrease) | AU64: =if((ISBLANK(AT64)),"",SkillIncrease) | AW64: =if((ISBLANK(AV64)),"",SkillIncrease) | AY64: =if((ISBLANK(AX64)),"",SkillIncrease) | BA64: =if((ISBLANK(AZ64)),"",SkillIncrease)
A65: SkillIncreaseExtra-L07 | B65: L07 | D65: 1 | E65: =if((ISBLANK(D65)),"",SkillIncrease) -> 5 | G65: =if((ISBLANK(F65)),"",SkillIncrease) | I65: =if((ISBLANK(H65)),"",SkillIncrease) | K65: =if((ISBLANK(J65)),"",SkillIncrease) | M65: =if((ISBLANK(L65)),"",SkillIncrease) | O65: =if((ISBLANK(N65)),"",SkillIncrease) | Q65: =if((ISBLANK(P65)),"",SkillIncrease) | S65: =if((ISBLANK(R65)),"",SkillIncrease) | T65: 1 | U65: =if((ISBLANK(T65)),"",SkillIncrease) -> 5 | W65: =if((ISBLANK(V65)),"",SkillIncrease) | Y65: =if((ISBLANK(X65)),"",SkillIncrease) | Z65: 1 | AA65: =if((ISBLANK(Z65)),"",SkillIncrease) -> 5 | AC65: =if((ISBLANK(AB65)),"",SkillIncrease) | AE65: =if((ISBLANK(AD65)),"",SkillIncrease) | AG65: =if((ISBLANK(AF65)),"",SkillIncrease) | AI65: =if((ISBLANK(AH65)),"",SkillIncrease) | AK65: =if((ISBLANK(AJ65)),"",SkillIncrease) | AM65: =if((ISBLANK(AL65)),"",SkillIncrease) | AO65: =if((ISBLANK(AN65)),"",SkillIncrease) | AQ65: =if((ISBLANK(AP65)),"",SkillIncrease) | AS65: =if((ISBLANK(AR65)),"",SkillIncrease) | AU65: =if((ISBLANK(AT65)),"",SkillIncrease) | AW65: =if((ISBLANK(AV65)),"",SkillIncrease) | AY65: =if((ISBLANK(AX65)),"",SkillIncrease) | BA65: =if((ISBLANK(AZ65)),"",SkillIncrease)
A66: SkillIncreaseExtra-L08 | B66: L08 | D66: 1 | E66: =if((ISBLANK(D66)),"",SkillIncrease) -> 5 | G66: =if((ISBLANK(F66)),"",SkillIncrease) | I66: =if((ISBLANK(H66)),"",SkillIncrease) | K66: =if((ISBLANK(J66)),"",SkillIncrease) | M66: =if((ISBLANK(L66)),"",SkillIncrease) | O66: =if((ISBLANK(N66)),"",SkillIncrease) | P66: 1 | Q66: =if((ISBLANK(P66)),"",SkillIncrease) -> 5 | R66: 1 | S66: =if((ISBLANK(R66)),"",SkillIncrease) -> 5 | U66: =if((ISBLANK(T66)),"",SkillIncrease) | W66: =if((ISBLANK(V66)),"",SkillIncrease) | Y66: =if((ISBLANK(X66)),"",SkillIncrease) | AA66: =if((ISBLANK(Z66)),"",SkillIncrease) | AC66: =if((ISBLANK(AB66)),"",SkillIncrease) | AE66: =if((ISBLANK(AD66)),"",SkillIncrease) | AG66: =if((ISBLANK(AF66)),"",SkillIncrease) | AI66: =if((ISBLANK(AH66)),"",SkillIncrease) | AK66: =if((ISBLANK(AJ66)),"",SkillIncrease) | AM66: =if((ISBLANK(AL66)),"",SkillIncrease) | AO66: =if((ISBLANK(AN66)),"",SkillIncrease) | AQ66: =if((ISBLANK(AP66)),"",SkillIncrease) | AS66: =if((ISBLANK(AR66)),"",SkillIncrease) | AU66: =if((ISBLANK(AT66)),"",SkillIncrease) | AW66: =if((ISBLANK(AV66)),"",SkillIncrease) | AY66: =if((ISBLANK(AX66)),"",SkillIncrease) | BA66: =if((ISBLANK(AZ66)),"",SkillIncrease)
A67: SkillIncreaseExtra-L09 | B67: L09 | D67: 1 | E67: =if((ISBLANK(D67)),"",SkillIncrease) -> 5 | G67: =if((ISBLANK(F67)),"",SkillIncrease) | I67: =if((ISBLANK(H67)),"",SkillIncrease) | K67: =if((ISBLANK(J67)),"",SkillIncrease) | M67: =if((ISBLANK(L67)),"",SkillIncrease) | O67: =if((ISBLANK(N67)),"",SkillIncrease) | Q67: =if((ISBLANK(P67)),"",SkillIncrease) | S67: =if((ISBLANK(R67)),"",SkillIncrease) | T67: 1 | U67: =if((ISBLANK(T67)),"",SkillIncrease) -> 5 | W67: =if((ISBLANK(V67)),"",SkillIncrease) | Y67: =if((ISBLANK(X67)),"",SkillIncrease) | AA67: =if((ISBLANK(Z67)),"",SkillIncrease) | AC67: =if((ISBLANK(AB67)),"",SkillIncrease) | AE67: =if((ISBLANK(AD67)),"",SkillIncrease) | AG67: =if((ISBLANK(AF67)),"",SkillIncrease) | AI67: =if((ISBLANK(AH67)),"",SkillIncrease) | AK67: =if((ISBLANK(AJ67)),"",SkillIncrease) | AM67: =if((ISBLANK(AL67)),"",SkillIncrease) | AO67: =if((ISBLANK(AN67)),"",SkillIncrease) | AQ67: =if((ISBLANK(AP67)),"",SkillIncrease) | AS67: =if((ISBLANK(AR67)),"",SkillIncrease) | AU67: =if((ISBLANK(AT67)),"",SkillIncrease) | AW67: =if((ISBLANK(AV67)),"",SkillIncrease) | AY67: =if((ISBLANK(AX67)),"",SkillIncrease) | BA67: =if((ISBLANK(AZ67)),"",SkillIncrease)
A68: SkillIncreaseExtra-L10 | B68: L10 | D68: 1 | E68: =if((ISBLANK(D68)),"",SkillIncrease) -> 5 | G68: =if((ISBLANK(F68)),"",SkillIncrease) | I68: =if((ISBLANK(H68)),"",SkillIncrease) | K68: =if((ISBLANK(J68)),"",SkillIncrease) | M68: =if((ISBLANK(L68)),"",SkillIncrease) | O68: =if((ISBLANK(N68)),"",SkillIncrease) | P68: 1 | Q68: =if((ISBLANK(P68)),"",SkillIncrease) -> 5 | R68: 1 | S68: =if((ISBLANK(R68)),"",SkillIncrease) -> 5 | U68: =if((ISBLANK(T68)),"",SkillIncrease) | W68: =if((ISBLANK(V68)),"",SkillIncrease) | Y68: =if((ISBLANK(X68)),"",SkillIncrease) | AA68: =if((ISBLANK(Z68)),"",SkillIncrease) | AC68: =if((ISBLANK(AB68)),"",SkillIncrease) | AE68: =if((ISBLANK(AD68)),"",SkillIncrease) | AG68: =if((ISBLANK(AF68)),"",SkillIncrease) | AI68: =if((ISBLANK(AH68)),"",SkillIncrease) | AK68: =if((ISBLANK(AJ68)),"",SkillIncrease) | AM68: =if((ISBLANK(AL68)),"",SkillIncrease) | AO68: =if((ISBLANK(AN68)),"",SkillIncrease) | AQ68: =if((ISBLANK(AP68)),"",SkillIncrease) | AS68: =if((ISBLANK(AR68)),"",SkillIncrease) | AU68: =if((ISBLANK(AT68)),"",SkillIncrease) | AW68: =if((ISBLANK(AV68)),"",SkillIncrease) | AY68: =if((ISBLANK(AX68)),"",SkillIncrease) | BA68: =if((ISBLANK(AZ68)),"",SkillIncrease)
A69: SkillIncreaseExtra-L11 | B69: L11 | D69: 1 | E69: =if((ISBLANK(D69)),"",SkillIncrease) -> 5 | G69: =if((ISBLANK(F69)),"",SkillIncrease) | I69: =if((ISBLANK(H69)),"",SkillIncrease) | K69: =if((ISBLANK(J69)),"",SkillIncrease) | M69: =if((ISBLANK(L69)),"",SkillIncrease) | O69: =if((ISBLANK(N69)),"",SkillIncrease) | Q69: =if((ISBLANK(P69)),"",SkillIncrease) | S69: =if((ISBLANK(R69)),"",SkillIncrease) | U69: =if((ISBLANK(T69)),"",SkillIncrease) | W69: =if((ISBLANK(V69)),"",SkillIncrease) | Y69: =if((ISBLANK(X69)),"",SkillIncrease) | AA69: =if((ISBLANK(Z69)),"",SkillIncrease) | AC69: =if((ISBLANK(AB69)),"",SkillIncrease) | AE69: =if((ISBLANK(AD69)),"",SkillIncrease) | AG69: =if((ISBLANK(AF69)),"",SkillIncrease) | AI69: =if((ISBLANK(AH69)),"",SkillIncrease) | AK69: =if((ISBLANK(AJ69)),"",SkillIncrease) | AM69: =if((ISBLANK(AL69)),"",SkillIncrease) | AO69: =if((ISBLANK(AN69)),"",SkillIncrease) | AQ69: =if((ISBLANK(AP69)),"",SkillIncrease) | AS69: =if((ISBLANK(AR69)),"",SkillIncrease) | AU69: =if((ISBLANK(AT69)),"",SkillIncrease) | AW69: =if((ISBLANK(AV69)),"",SkillIncrease) | AY69: =if((ISBLANK(AX69)),"",SkillIncrease) | BA69: =if((ISBLANK(AZ69)),"",SkillIncrease)
A70: SkillIncreaseExtra-L12 | B70: L12 | D70: 1 | E70: =if((ISBLANK(D70)),"",SkillIncrease) -> 5 | G70: =if((ISBLANK(F70)),"",SkillIncrease) | I70: =if((ISBLANK(H70)),"",SkillIncrease) | K70: =if((ISBLANK(J70)),"",SkillIncrease) | M70: =if((ISBLANK(L70)),"",SkillIncrease) | O70: =if((ISBLANK(N70)),"",SkillIncrease) | P70: 1 | Q70: =if((ISBLANK(P70)),"",SkillIncrease) -> 5 | R70: 1 | S70: =if((ISBLANK(R70)),"",SkillIncrease) -> 5 | U70: =if((ISBLANK(T70)),"",SkillIncrease) | W70: =if((ISBLANK(V70)),"",SkillIncrease) | Y70: =if((ISBLANK(X70)),"",SkillIncrease) | AA70: =if((ISBLANK(Z70)),"",SkillIncrease) | AC70: =if((ISBLANK(AB70)),"",SkillIncrease) | AE70: =if((ISBLANK(AD70)),"",SkillIncrease) | AG70: =if((ISBLANK(AF70)),"",SkillIncrease) | AI70: =if((ISBLANK(AH70)),"",SkillIncrease) | AK70: =if((ISBLANK(AJ70)),"",SkillIncrease) | AM70: =if((ISBLANK(AL70)),"",SkillIncrease) | AO70: =if((ISBLANK(AN70)),"",SkillIncrease) | AQ70: =if((ISBLANK(AP70)),"",SkillIncrease) | AS70: =if((ISBLANK(AR70)),"",SkillIncrease) | AU70: =if((ISBLANK(AT70)),"",SkillIncrease) | AW70: =if((ISBLANK(AV70)),"",SkillIncrease) | AY70: =if((ISBLANK(AX70)),"",SkillIncrease) | BA70: =if((ISBLANK(AZ70)),"",SkillIncrease)
A71: SkillIncreaseExtra-L13 | B71: L13 | D71: 1 | E71: =if((ISBLANK(D71)),"",SkillIncrease) -> 5 | G71: =if((ISBLANK(F71)),"",SkillIncrease) | I71: =if((ISBLANK(H71)),"",SkillIncrease) | K71: =if((ISBLANK(J71)),"",SkillIncrease) | M71: =if((ISBLANK(L71)),"",SkillIncrease) | O71: =if((ISBLANK(N71)),"",SkillIncrease) | Q71: =if((ISBLANK(P71)),"",SkillIncrease) | S71: =if((ISBLANK(R71)),"",SkillIncrease) | U71: =if((ISBLANK(T71)),"",SkillIncrease) | W71: =if((ISBLANK(V71)),"",SkillIncrease) | Y71: =if((ISBLANK(X71)),"",SkillIncrease) | AA71: =if((ISBLANK(Z71)),"",SkillIncrease) | AC71: =if((ISBLANK(AB71)),"",SkillIncrease) | AE71: =if((ISBLANK(AD71)),"",SkillIncrease) | AG71: =if((ISBLANK(AF71)),"",SkillIncrease) | AI71: =if((ISBLANK(AH71)),"",SkillIncrease) | AK71: =if((ISBLANK(AJ71)),"",SkillIncrease) | AM71: =if((ISBLANK(AL71)),"",SkillIncrease) | AO71: =if((ISBLANK(AN71)),"",SkillIncrease) | AQ71: =if((ISBLANK(AP71)),"",SkillIncrease) | AS71: =if((ISBLANK(AR71)),"",SkillIncrease) | AU71: =if((ISBLANK(AT71)),"",SkillIncrease) | AW71: =if((ISBLANK(AV71)),"",SkillIncrease) | AY71: =if((ISBLANK(AX71)),"",SkillIncrease) | BA71: =if((ISBLANK(AZ71)),"",SkillIncrease)
A72: SkillIncreaseExtra-L14 | B72: L14 | D72: 1 | E72: =if((ISBLANK(D72)),"",SkillIncrease) -> 5 | G72: =if((ISBLANK(F72)),"",SkillIncrease) | I72: =if((ISBLANK(H72)),"",SkillIncrease) | K72: =if((ISBLANK(J72)),"",SkillIncrease) | M72: =if((ISBLANK(L72)),"",SkillIncrease) | O72: =if((ISBLANK(N72)),"",SkillIncrease) | P72: 1 | Q72: =if((ISBLANK(P72)),"",SkillIncrease) -> 5 | R72: 1 | S72: =if((ISBLANK(R72)),"",SkillIncrease) -> 5 | U72: =if((ISBLANK(T72)),"",SkillIncrease) | W72: =if((ISBLANK(V72)),"",SkillIncrease) | Y72: =if((ISBLANK(X72)),"",SkillIncrease) | AA72: =if((ISBLANK(Z72)),"",SkillIncrease) | AC72: =if((ISBLANK(AB72)),"",SkillIncrease) | AE72: =if((ISBLANK(AD72)),"",SkillIncrease) | AG72: =if((ISBLANK(AF72)),"",SkillIncrease) | AI72: =if((ISBLANK(AH72)),"",SkillIncrease) | AK72: =if((ISBLANK(AJ72)),"",SkillIncrease) | AM72: =if((ISBLANK(AL72)),"",SkillIncrease) | AO72: =if((ISBLANK(AN72)),"",SkillIncrease) | AQ72: =if((ISBLANK(AP72)),"",SkillIncrease) | AS72: =if((ISBLANK(AR72)),"",SkillIncrease) | AU72: =if((ISBLANK(AT72)),"",SkillIncrease) | AW72: =if((ISBLANK(AV72)),"",SkillIncrease) | AY72: =if((ISBLANK(AX72)),"",SkillIncrease) | BA72: =if((ISBLANK(AZ72)),"",SkillIncrease)
A73: SkillIncreaseExtra-L15 | B73: L15 | D73: 1 | E73: =if((ISBLANK(D73)),"",SkillIncrease) -> 5 | G73: =if((ISBLANK(F73)),"",SkillIncrease) | I73: =if((ISBLANK(H73)),"",SkillIncrease) | K73: =if((ISBLANK(J73)),"",SkillIncrease) | M73: =if((ISBLANK(L73)),"",SkillIncrease) | O73: =if((ISBLANK(N73)),"",SkillIncrease) | Q73: =if((ISBLANK(P73)),"",SkillIncrease) | S73: =if((ISBLANK(R73)),"",SkillIncrease) | T73: 1 | U73: =if((ISBLANK(T73)),"",SkillIncrease) -> 5 | W73: =if((ISBLANK(V73)),"",SkillIncrease) | Y73: =if((ISBLANK(X73)),"",SkillIncrease) | Z73: 1 | AA73: =if((ISBLANK(Z73)),"",SkillIncrease) -> 5 | AC73: =if((ISBLANK(AB73)),"",SkillIncrease) | AE73: =if((ISBLANK(AD73)),"",SkillIncrease) | AG73: =if((ISBLANK(AF73)),"",SkillIncrease) | AI73: =if((ISBLANK(AH73)),"",SkillIncrease) | AK73: =if((ISBLANK(AJ73)),"",SkillIncrease) | AM73: =if((ISBLANK(AL73)),"",SkillIncrease) | AO73: =if((ISBLANK(AN73)),"",SkillIncrease) | AQ73: =if((ISBLANK(AP73)),"",SkillIncrease) | AS73: =if((ISBLANK(AR73)),"",SkillIncrease) | AU73: =if((ISBLANK(AT73)),"",SkillIncrease) | AW73: =if((ISBLANK(AV73)),"",SkillIncrease) | AY73: =if((ISBLANK(AX73)),"",SkillIncrease) | BA73: =if((ISBLANK(AZ73)),"",SkillIncrease)
A74: SkillIncreaseExtra-L16 | B74: L16 | D74: 1 | E74: =if((ISBLANK(D74)),"",SkillIncrease) -> 5 | G74: =if((ISBLANK(F74)),"",SkillIncrease) | I74: =if((ISBLANK(H74)),"",SkillIncrease) | K74: =if((ISBLANK(J74)),"",SkillIncrease) | M74: =if((ISBLANK(L74)),"",SkillIncrease) | O74: =if((ISBLANK(N74)),"",SkillIncrease) | P74: 1 | Q74: =if((ISBLANK(P74)),"",SkillIncrease) -> 5 | R74: 1 | S74: =if((ISBLANK(R74)),"",SkillIncrease) -> 5 | U74: =if((ISBLANK(T74)),"",SkillIncrease) | W74: =if((ISBLANK(V74)),"",SkillIncrease) | Y74: =if((ISBLANK(X74)),"",SkillIncrease) | AA74: =if((ISBLANK(Z74)),"",SkillIncrease) | AC74: =if((ISBLANK(AB74)),"",SkillIncrease) | AE74: =if((ISBLANK(AD74)),"",SkillIncrease) | AG74: =if((ISBLANK(AF74)),"",SkillIncrease) | AI74: =if((ISBLANK(AH74)),"",SkillIncrease) | AK74: =if((ISBLANK(AJ74)),"",SkillIncrease) | AM74: =if((ISBLANK(AL74)),"",SkillIncrease) | AO74: =if((ISBLANK(AN74)),"",SkillIncrease) | AQ74: =if((ISBLANK(AP74)),"",SkillIncrease) | AS74: =if((ISBLANK(AR74)),"",SkillIncrease) | AU74: =if((ISBLANK(AT74)),"",SkillIncrease) | AW74: =if((ISBLANK(AV74)),"",SkillIncrease) | AY74: =if((ISBLANK(AX74)),"",SkillIncrease) | BA74: =if((ISBLANK(AZ74)),"",SkillIncrease)
A75: SkillIncreaseExtra-L17 | B75: L17 | D75: 1 | E75: =if((ISBLANK(D75)),"",SkillIncrease) -> 5 | G75: =if((ISBLANK(F75)),"",SkillIncrease) | I75: =if((ISBLANK(H75)),"",SkillIncrease) | K75: =if((ISBLANK(J75)),"",SkillIncrease) | M75: =if((ISBLANK(L75)),"",SkillIncrease) | O75: =if((ISBLANK(N75)),"",SkillIncrease) | Q75: =if((ISBLANK(P75)),"",SkillIncrease) | S75: =if((ISBLANK(R75)),"",SkillIncrease) | T75: 1 | U75: =if((ISBLANK(T75)),"",SkillIncrease) -> 5 | W75: =if((ISBLANK(V75)),"",SkillIncrease) | Y75: =if((ISBLANK(X75)),"",SkillIncrease) | AA75: =if((ISBLANK(Z75)),"",SkillIncrease) | AC75: =if((ISBLANK(AB75)),"",SkillIncrease) | AE75: =if((ISBLANK(AD75)),"",SkillIncrease) | AG75: =if((ISBLANK(AF75)),"",SkillIncrease) | AI75: =if((ISBLANK(AH75)),"",SkillIncrease) | AK75: =if((ISBLANK(AJ75)),"",SkillIncrease) | AM75: =if((ISBLANK(AL75)),"",SkillIncrease) | AO75: =if((ISBLANK(AN75)),"",SkillIncrease) | AQ75: =if((ISBLANK(AP75)),"",SkillIncrease) | AS75: =if((ISBLANK(AR75)),"",SkillIncrease) | AU75: =if((ISBLANK(AT75)),"",SkillIncrease) | AW75: =if((ISBLANK(AV75)),"",SkillIncrease) | AY75: =if((ISBLANK(AX75)),"",SkillIncrease) | BA75: =if((ISBLANK(AZ75)),"",SkillIncrease)
A76: SkillIncreaseExtra-L18 | B76: L18 | D76: 1 | E76: =if((ISBLANK(D76)),"",SkillIncrease) -> 5 | G76: =if((ISBLANK(F76)),"",SkillIncrease) | I76: =if((ISBLANK(H76)),"",SkillIncrease) | K76: =if((ISBLANK(J76)),"",SkillIncrease) | M76: =if((ISBLANK(L76)),"",SkillIncrease) | O76: =if((ISBLANK(N76)),"",SkillIncrease) | P76: 1 | Q76: =if((ISBLANK(P76)),"",SkillIncrease) -> 5 | R76: 1 | S76: =if((ISBLANK(R76)),"",SkillIncrease) -> 5 | U76: =if((ISBLANK(T76)),"",SkillIncrease) | W76: =if((ISBLANK(V76)),"",SkillIncrease) | Y76: =if((ISBLANK(X76)),"",SkillIncrease) | AA76: =if((ISBLANK(Z76)),"",SkillIncrease) | AC76: =if((ISBLANK(AB76)),"",SkillIncrease) | AE76: =if((ISBLANK(AD76)),"",SkillIncrease) | AG76: =if((ISBLANK(AF76)),"",SkillIncrease) | AI76: =if((ISBLANK(AH76)),"",SkillIncrease) | AK76: =if((ISBLANK(AJ76)),"",SkillIncrease) | AM76: =if((ISBLANK(AL76)),"",SkillIncrease) | AO76: =if((ISBLANK(AN76)),"",SkillIncrease) | AQ76: =if((ISBLANK(AP76)),"",SkillIncrease) | AS76: =if((ISBLANK(AR76)),"",SkillIncrease) | AU76: =if((ISBLANK(AT76)),"",SkillIncrease) | AW76: =if((ISBLANK(AV76)),"",SkillIncrease) | AY76: =if((ISBLANK(AX76)),"",SkillIncrease) | BA76: =if((ISBLANK(AZ76)),"",SkillIncrease)
A77: SkillIncreaseExtra-L19 | B77: L19 | D77: 1 | E77: =if((ISBLANK(D77)),"",SkillIncrease) -> 5 | G77: =if((ISBLANK(F77)),"",SkillIncrease) | I77: =if((ISBLANK(H77)),"",SkillIncrease) | K77: =if((ISBLANK(J77)),"",SkillIncrease) | M77: =if((ISBLANK(L77)),"",SkillIncrease) | O77: =if((ISBLANK(N77)),"",SkillIncrease) | Q77: =if((ISBLANK(P77)),"",SkillIncrease) | S77: =if((ISBLANK(R77)),"",SkillIncrease) | U77: =if((ISBLANK(T77)),"",SkillIncrease) | W77: =if((ISBLANK(V77)),"",SkillIncrease) | Y77: =if((ISBLANK(X77)),"",SkillIncrease) | AA77: =if((ISBLANK(Z77)),"",SkillIncrease) | AC77: =if((ISBLANK(AB77)),"",SkillIncrease) | AE77: =if((ISBLANK(AD77)),"",SkillIncrease) | AG77: =if((ISBLANK(AF77)),"",SkillIncrease) | AI77: =if((ISBLANK(AH77)),"",SkillIncrease) | AK77: =if((ISBLANK(AJ77)),"",SkillIncrease) | AM77: =if((ISBLANK(AL77)),"",SkillIncrease) | AO77: =if((ISBLANK(AN77)),"",SkillIncrease) | AQ77: =if((ISBLANK(AP77)),"",SkillIncrease) | AS77: =if((ISBLANK(AR77)),"",SkillIncrease) | AU77: =if((ISBLANK(AT77)),"",SkillIncrease) | AW77: =if((ISBLANK(AV77)),"",SkillIncrease) | AY77: =if((ISBLANK(AX77)),"",SkillIncrease) | BA77: =if((ISBLANK(AZ77)),"",SkillIncrease)
A78: SkillIncreaseExtra-L20 | B78: L20 | D78: 1 | E78: =if((ISBLANK(D78)),"",SkillIncrease) -> 5 | G78: =if((ISBLANK(F78)),"",SkillIncrease) | I78: =if((ISBLANK(H78)),"",SkillIncrease) | K78: =if((ISBLANK(J78)),"",SkillIncrease) | M78: =if((ISBLANK(L78)),"",SkillIncrease) | O78: =if((ISBLANK(N78)),"",SkillIncrease) | P78: 1 | Q78: =if((ISBLANK(P78)),"",SkillIncrease) -> 5 | R78: 1 | S78: =if((ISBLANK(R78)),"",SkillIncrease) -> 5 | U78: =if((ISBLANK(T78)),"",SkillIncrease) | W78: =if((ISBLANK(V78)),"",SkillIncrease) | Y78: =if((ISBLANK(X78)),"",SkillIncrease) | AA78: =if((ISBLANK(Z78)),"",SkillIncrease) | AC78: =if((ISBLANK(AB78)),"",SkillIncrease) | AE78: =if((ISBLANK(AD78)),"",SkillIncrease) | AG78: =if((ISBLANK(AF78)),"",SkillIncrease) | AI78: =if((ISBLANK(AH78)),"",SkillIncrease) | AK78: =if((ISBLANK(AJ78)),"",SkillIncrease) | AM78: =if((ISBLANK(AL78)),"",SkillIncrease) | AO78: =if((ISBLANK(AN78)),"",SkillIncrease) | AQ78: =if((ISBLANK(AP78)),"",SkillIncrease) | AS78: =if((ISBLANK(AR78)),"",SkillIncrease) | AU78: =if((ISBLANK(AT78)),"",SkillIncrease) | AW78: =if((ISBLANK(AV78)),"",SkillIncrease) | AY78: =if((ISBLANK(AX78)),"",SkillIncrease) | BA78: =if((ISBLANK(AZ78)),"",SkillIncrease)
A79: SkillIncreaseExtraTotal | D79: =SUM(D60:D78) -> 19 | E79: =SUM(E60:E78) -> 95 | F79: =SUM(F60:F78) -> 0 | G79: =SUM(G60:G78) -> 0 | H79: =SUM(H60:H78) -> 0 | I79: =SUM(I60:I78) -> 0 | J79: =SUM(J60:J78) -> 0 | K79: =SUM(K60:K78) -> 0 | ... AC79: =SUM(AC60:AC78) -> 0 | AE79: =SUM(AE60:AE78) -> 0 | AF79: =SUM(AF60:AF78) -> 0 | AG79: =SUM(AG60:AG78) -> 0 | AH79: =SUM(AH60:AH78) -> 0 | AI79: =SUM(AI60:AI78) -> 0 | AJ79: =SUM(AJ60:AJ78) -> 0 | AK79: =SUM(AK60:AK78) -> 0 | AL79: =SUM(AL60:AL78) -> 0 | ... BA79: =SUM(BA60:BA78) -> 0
A80: SkillFeatExtra-L01 | B80: L01 | D80: 1 | E80: =if((ISBLANK(D80)),"",SkillFeat) -> 5 | G80: =if((ISBLANK(F80)),"",SkillFeat) | I80: =if((ISBLANK(H80)),"",SkillFeat) | K80: =if((ISBLANK(J80)),"",SkillFeat) | M80: =if((ISBLANK(L80)),"",SkillFeat) | O80: =if((ISBLANK(N80)),"",SkillFeat) | P80: 1 | Q80: =if((ISBLANK(P80)),"",SkillFeat) -> 5 | S80: =if((ISBLANK(R80)),"",SkillFeat) | T80: 1 | U80: =if((ISBLANK(T80)),"",SkillFeat) -> 5 | W80: =if((ISBLANK(V80)),"",SkillFeat) | Y80: =if((ISBLANK(X80)),"",SkillFeat) | Z80: 1 | AA80: =if((ISBLANK(Z80)),"",SkillFeat) -> 5 | AB80: 1 | AE80: =if((ISBLANK(AD80)),"",SkillFeat) | AG80: =if((ISBLANK(AF80)),"",SkillFeat) | AI80: =if((ISBLANK(AH80)),"",SkillFeat) | AK80: =if((ISBLANK(AJ80)),"",SkillFeat) | AM80: =if((ISBLANK(AL80)),"",SkillFeat) | AO80: =if((ISBLANK(AN80)),"",SkillFeat) | AQ80: =if((ISBLANK(AP80)),"",SkillFeat) | AS80: =if((ISBLANK(AR80)),"",SkillFeat) | AU80: =if((ISBLANK(AT80)),"",SkillFeat) | AW80: =if((ISBLANK(AV80)),"",SkillFeat) | AY80: =if((ISBLANK(AX80)),"",SkillFeat) | BA80: =if((ISBLANK(AZ80)),"",SkillFeat)
A81: SkillFeatExtra-L02 | B81: L02 | D81: 1 | E81: =if((ISBLANK(D81)),"",SkillFeat) -> 5 | G81: =if((ISBLANK(F81)),"",SkillFeat) | I81: =if((ISBLANK(H81)),"",SkillFeat) | K81: =if((ISBLANK(J81)),"",SkillFeat) | M81: =if((ISBLANK(L81)),"",SkillFeat) | O81: =if((ISBLANK(N81)),"",SkillFeat) | Q81: =if((ISBLANK(P81)),"",SkillFeat) | S81: =if((ISBLANK(R81)),"",SkillFeat) | U81: =if((ISBLANK(T81)),"",SkillFeat) | W81: =if((ISBLANK(V81)),"",SkillFeat) | Y81: =if((ISBLANK(X81)),"",SkillFeat) | AA81: =if((ISBLANK(Z81)),"",SkillFeat) | AC81: =if((ISBLANK(AB81)),"",SkillFeat) | AE81: =if((ISBLANK(AD81)),"",SkillFeat) | AG81: =if((ISBLANK(AF81)),"",SkillFeat) | AI81: =if((ISBLANK(AH81)),"",SkillFeat) | AK81: =if((ISBLANK(AJ81)),"",SkillFeat) | AM81: =if((ISBLANK(AL81)),"",SkillFeat) | AO81: =if((ISBLANK(AN81)),"",SkillFeat) | AQ81: =if((ISBLANK(AP81)),"",SkillFeat) | AS81: =if((ISBLANK(AR81)),"",SkillFeat) | AU81: =if((ISBLANK(AT81)),"",SkillFeat) | AW81: =if((ISBLANK(AV81)),"",SkillFeat) | AY81: =if((ISBLANK(AX81)),"",SkillFeat) | BA81: =if((ISBLANK(AZ81)),"",SkillFeat)
A82: SkillFeatExtra-L03 | B82: L03 | D82: 1 | E82: =if((ISBLANK(D82)),"",SkillFeat) -> 5 | G82: =if((ISBLANK(F82)),"",SkillFeat) | I82: =if((ISBLANK(H82)),"",SkillFeat) | K82: =if((ISBLANK(J82)),"",SkillFeat) | M82: =if((ISBLANK(L82)),"",SkillFeat) | O82: =if((ISBLANK(N82)),"",SkillFeat) | P82: 1 | Q82: =if((ISBLANK(P82)),"",SkillFeat) -> 5 | R82: 1 | S82: =if((ISBLANK(R82)),"",SkillFeat) -> 5 | U82: =if((ISBLANK(T82)),"",SkillFeat) | V82: 1 | W82: =if((ISBLANK(V82)),"",SkillFeat) -> 5 | Y82: =if((ISBLANK(X82)),"",SkillFeat) | AA82: =if((ISBLANK(Z82)),"",SkillFeat) | AC82: =if((ISBLANK(AB82)),"",SkillFeat) | AE82: =if((ISBLANK(AD82)),"",SkillFeat) | AG82: =if((ISBLANK(AF82)),"",SkillFeat) | AI82: =if((ISBLANK(AH82)),"",SkillFeat) | AK82: =if((ISBLANK(AJ82)),"",SkillFeat) | AM82: =if((ISBLANK(AL82)),"",SkillFeat) | AO82: =if((ISBLANK(AN82)),"",SkillFeat) | AQ82: =if((ISBLANK(AP82)),"",SkillFeat) | AS82: =if((ISBLANK(AR82)),"",SkillFeat) | AU82: =if((ISBLANK(AT82)),"",SkillFeat) | AW82: =if((ISBLANK(AV82)),"",SkillFeat) | AY82: =if((ISBLANK(AX82)),"",SkillFeat) | BA82: =if((ISBLANK(AZ82)),"",SkillFeat)
A83: SkillFeatExtra-L04 | B83: L04 | D83: 1 | E83: =if((ISBLANK(D83)),"",SkillFeat) -> 5 | G83: =if((ISBLANK(F83)),"",SkillFeat) | I83: =if((ISBLANK(H83)),"",SkillFeat) | K83: =if((ISBLANK(J83)),"",SkillFeat) | M83: =if((ISBLANK(L83)),"",SkillFeat) | O83: =if((ISBLANK(N83)),"",SkillFeat) | Q83: =if((ISBLANK(P83)),"",SkillFeat) | S83: =if((ISBLANK(R83)),"",SkillFeat) | U83: =if((ISBLANK(T83)),"",SkillFeat) | W83: =if((ISBLANK(V83)),"",SkillFeat) | Y83: =if((ISBLANK(X83)),"",SkillFeat) | AA83: =if((ISBLANK(Z83)),"",SkillFeat) | AC83: =if((ISBLANK(AB83)),"",SkillFeat) | AE83: =if((ISBLANK(AD83)),"",SkillFeat) | AG83: =if((ISBLANK(AF83)),"",SkillFeat) | AI83: =if((ISBLANK(AH83)),"",SkillFeat) | AK83: =if((ISBLANK(AJ83)),"",SkillFeat) | AM83: =if((ISBLANK(AL83)),"",SkillFeat) | AO83: =if((ISBLANK(AN83)),"",SkillFeat) | AQ83: =if((ISBLANK(AP83)),"",SkillFeat) | AS83: =if((ISBLANK(AR83)),"",SkillFeat) | AU83: =if((ISBLANK(AT83)),"",SkillFeat) | AW83: =if((ISBLANK(AV83)),"",SkillFeat) | AY83: =if((ISBLANK(AX83)),"",SkillFeat) | BA83: =if((ISBLANK(AZ83)),"",SkillFeat)
A84: SkillFeatExtra-L05 | B84: L05 | D84: 1 | E84: =if((ISBLANK(D84)),"",SkillFeat) -> 5 | G84: =if((ISBLANK(F84)),"",SkillFeat) | I84: =if((ISBLANK(H84)),"",SkillFeat) | K84: =if((ISBLANK(J84)),"",SkillFeat) | M84: =if((ISBLANK(L84)),"",SkillFeat) | O84: =if((ISBLANK(N84)),"",SkillFeat) | P84: 1 | Q84: =if((ISBLANK(P84)),"",SkillFeat) -> 5 | R84: 1 | S84: =if((ISBLANK(R84)),"",SkillFeat) -> 5 | U84: =if((ISBLANK(T84)),"",SkillFeat) | W84: =if((ISBLANK(V84)),"",SkillFeat) | Y84: =if((ISBLANK(X84)),"",SkillFeat) | AA84: =if((ISBLANK(Z84)),"",SkillFeat) | AC84: =if((ISBLANK(AB84)),"",SkillFeat) | AE84: =if((ISBLANK(AD84)),"",SkillFeat) | AG84: =if((ISBLANK(AF84)),"",SkillFeat) | AI84: =if((ISBLANK(AH84)),"",SkillFeat) | AK84: =if((ISBLANK(AJ84)),"",SkillFeat) | AM84: =if((ISBLANK(AL84)),"",SkillFeat) | AO84: =if((ISBLANK(AN84)),"",SkillFeat) | AQ84: =if((ISBLANK(AP84)),"",SkillFeat) | AS84: =if((ISBLANK(AR84)),"",SkillFeat) | AU84: =if((ISBLANK(AT84)),"",SkillFeat) | AW84: =if((ISBLANK(AV84)),"",SkillFeat) | AY84: =if((ISBLANK(AX84)),"",SkillFeat) | BA84: =if((ISBLANK(AZ84)),"",SkillFeat)
A85: SkillFeatExtra-L06 | B85: L06 | D85: 1 | E85: =if((ISBLANK(D85)),"",SkillFeat) -> 5 | G85: =if((ISBLANK(F85)),"",SkillFeat) | I85: =if((ISBLANK(H85)),"",SkillFeat) | K85: =if((ISBLANK(J85)),"",SkillFeat) | M85: =if((ISBLANK(L85)),"",SkillFeat) | O85: =if((ISBLANK(N85)),"",SkillFeat) | Q85: =if((ISBLANK(P85)),"",SkillFeat) | S85: =if((ISBLANK(R85)),"",SkillFeat) | U85: =if((ISBLANK(T85)),"",SkillFeat) | W85: =if((ISBLANK(V85)),"",SkillFeat) | Y85: =if((ISBLANK(X85)),"",SkillFeat) | AA85: =if((ISBLANK(Z85)),"",SkillFeat) | AC85: =if((ISBLANK(AB85)),"",SkillFeat) | AE85: =if((ISBLANK(AD85)),"",SkillFeat) | AG85: =if((ISBLANK(AF85)),"",SkillFeat) | AI85: =if((ISBLANK(AH85)),"",SkillFeat) | AK85: =if((ISBLANK(AJ85)),"",SkillFeat) | AM85: =if((ISBLANK(AL85)),"",SkillFeat) | AO85: =if((ISBLANK(AN85)),"",SkillFeat) | AQ85: =if((ISBLANK(AP85)),"",SkillFeat) | AS85: =if((ISBLANK(AR85)),"",SkillFeat) | AU85: =if((ISBLANK(AT85)),"",SkillFeat) | AW85: =if((ISBLANK(AV85)),"",SkillFeat) | AY85: =if((ISBLANK(AX85)),"",SkillFeat) | BA85: =if((ISBLANK(AZ85)),"",SkillFeat)
A86: SkillFeatExtra-L07 | B86: L07 | D86: 1 | E86: =if((ISBLANK(D86)),"",SkillFeat) -> 5 | G86: =if((ISBLANK(F86)),"",SkillFeat) | I86: =if((ISBLANK(H86)),"",SkillFeat) | K86: =if((ISBLANK(J86)),"",SkillFeat) | M86: =if((ISBLANK(L86)),"",SkillFeat) | O86: =if((ISBLANK(N86)),"",SkillFeat) | P86: 1 | Q86: =if((ISBLANK(P86)),"",SkillFeat) -> 5 | R86: 1 | S86: =if((ISBLANK(R86)),"",SkillFeat) -> 5 | U86: =if((ISBLANK(T86)),"",SkillFeat) | V86: 1 | W86: =if((ISBLANK(V86)),"",SkillFeat) -> 5 | Y86: =if((ISBLANK(X86)),"",SkillFeat) | AA86: =if((ISBLANK(Z86)),"",SkillFeat) | AC86: =if((ISBLANK(AB86)),"",SkillFeat) | AE86: =if((ISBLANK(AD86)),"",SkillFeat) | AG86: =if((ISBLANK(AF86)),"",SkillFeat) | AI86: =if((ISBLANK(AH86)),"",SkillFeat) | AK86: =if((ISBLANK(AJ86)),"",SkillFeat) | AM86: =if((ISBLANK(AL86)),"",SkillFeat) | AO86: =if((ISBLANK(AN86)),"",SkillFeat) | AQ86: =if((ISBLANK(AP86)),"",SkillFeat) | AS86: =if((ISBLANK(AR86)),"",SkillFeat) | AU86: =if((ISBLANK(AT86)),"",SkillFeat) | AW86: =if((ISBLANK(AV86)),"",SkillFeat) | AY86: =if((ISBLANK(AX86)),"",SkillFeat) | BA86: =if((ISBLANK(AZ86)),"",SkillFeat)
A87: SkillFeatExtra-L08 | B87: L08 | D87: 1 | E87: =if((ISBLANK(D87)),"",SkillFeat) -> 5 | G87: =if((ISBLANK(F87)),"",SkillFeat) | I87: =if((ISBLANK(H87)),"",SkillFeat) | K87: =if((ISBLANK(J87)),"",SkillFeat) | M87: =if((ISBLANK(L87)),"",SkillFeat) | O87: =if((ISBLANK(N87)),"",SkillFeat) | Q87: =if((ISBLANK(P87)),"",SkillFeat) | S87: =if((ISBLANK(R87)),"",SkillFeat) | U87: =if((ISBLANK(T87)),"",SkillFeat) | W87: =if((ISBLANK(V87)),"",SkillFeat) | Y87: =if((ISBLANK(X87)),"",SkillFeat) | AA87: =if((ISBLANK(Z87)),"",SkillFeat) | AC87: =if((ISBLANK(AB87)),"",SkillFeat) | AE87: =if((ISBLANK(AD87)),"",SkillFeat) | AG87: =if((ISBLANK(AF87)),"",SkillFeat) | AI87: =if((ISBLANK(AH87)),"",SkillFeat) | AK87: =if((ISBLANK(AJ87)),"",SkillFeat) | AM87: =if((ISBLANK(AL87)),"",SkillFeat) | AO87: =if((ISBLANK(AN87)),"",SkillFeat) | AQ87: =if((ISBLANK(AP87)),"",SkillFeat) | AS87: =if((ISBLANK(AR87)),"",SkillFeat) | AU87: =if((ISBLANK(AT87)),"",SkillFeat) | AW87: =if((ISBLANK(AV87)),"",SkillFeat) | AY87: =if((ISBLANK(AX87)),"",SkillFeat) | BA87: =if((ISBLANK(AZ87)),"",SkillFeat)
A88: SkillFeatExtra-L09 | B88: L09 | D88: 1 | E88: =if((ISBLANK(D88)),"",SkillFeat) -> 5 | G88: =if((ISBLANK(F88)),"",SkillFeat) | I88: =if((ISBLANK(H88)),"",SkillFeat) | K88: =if((ISBLANK(J88)),"",SkillFeat) | M88: =if((ISBLANK(L88)),"",SkillFeat) | O88: =if((ISBLANK(N88)),"",SkillFeat) | P88: 1 | Q88: =if((ISBLANK(P88)),"",SkillFeat) -> 5 | R88: 1 | S88: =if((ISBLANK(R88)),"",SkillFeat) -> 5 | U88: =if((ISBLANK(T88)),"",SkillFeat) | W88: =if((ISBLANK(V88)),"",SkillFeat) | Y88: =if((ISBLANK(X88)),"",SkillFeat) | AA88: =if((ISBLANK(Z88)),"",SkillFeat) | AC88: =if((ISBLANK(AB88)),"",SkillFeat) | AE88: =if((ISBLANK(AD88)),"",SkillFeat) | AG88: =if((ISBLANK(AF88)),"",SkillFeat) | AI88: =if((ISBLANK(AH88)),"",SkillFeat) | AK88: =if((ISBLANK(AJ88)),"",SkillFeat) | AM88: =if((ISBLANK(AL88)),"",SkillFeat) | AO88: =if((ISBLANK(AN88)),"",SkillFeat) | AQ88: =if((ISBLANK(AP88)),"",SkillFeat) | AS88: =if((ISBLANK(AR88)),"",SkillFeat) | AU88: =if((ISBLANK(AT88)),"",SkillFeat) | AW88: =if((ISBLANK(AV88)),"",SkillFeat) | AY88: =if((ISBLANK(AX88)),"",SkillFeat) | BA88: =if((ISBLANK(AZ88)),"",SkillFeat)
A89: SkillFeatExtra-L10 | B89: L10 | D89: 1 | E89: =if((ISBLANK(D89)),"",SkillFeat) -> 5 | G89: =if((ISBLANK(F89)),"",SkillFeat) | I89: =if((ISBLANK(H89)),"",SkillFeat) | K89: =if((ISBLANK(J89)),"",SkillFeat) | M89: =if((ISBLANK(L89)),"",SkillFeat) | O89: =if((ISBLANK(N89)),"",SkillFeat) | Q89: =if((ISBLANK(P89)),"",SkillFeat) | S89: =if((ISBLANK(R89)),"",SkillFeat) | U89: =if((ISBLANK(T89)),"",SkillFeat) | W89: =if((ISBLANK(V89)),"",SkillFeat) | Y89: =if((ISBLANK(X89)),"",SkillFeat) | AA89: =if((ISBLANK(Z89)),"",SkillFeat) | AC89: =if((ISBLANK(AB89)),"",SkillFeat) | AE89: =if((ISBLANK(AD89)),"",SkillFeat) | AG89: =if((ISBLANK(AF89)),"",SkillFeat) | AI89: =if((ISBLANK(AH89)),"",SkillFeat) | AK89: =if((ISBLANK(AJ89)),"",SkillFeat) | AM89: =if((ISBLANK(AL89)),"",SkillFeat) | AO89: =if((ISBLANK(AN89)),"",SkillFeat) | AQ89: =if((ISBLANK(AP89)),"",SkillFeat) | AS89: =if((ISBLANK(AR89)),"",SkillFeat) | AU89: =if((ISBLANK(AT89)),"",SkillFeat) | AW89: =if((ISBLANK(AV89)),"",SkillFeat) | AY89: =if((ISBLANK(AX89)),"",SkillFeat) | BA89: =if((ISBLANK(AZ89)),"",SkillFeat)
A90: SkillFeatExtra-L11 | B90: L11 | D90: 1 | E90: =if((ISBLANK(D90)),"",SkillFeat) -> 5 | G90: =if((ISBLANK(F90)),"",SkillFeat) | I90: =if((ISBLANK(H90)),"",SkillFeat) | K90: =if((ISBLANK(J90)),"",SkillFeat) | M90: =if((ISBLANK(L90)),"",SkillFeat) | O90: =if((ISBLANK(N90)),"",SkillFeat) | P90: 1 | Q90: =if((ISBLANK(P90)),"",SkillFeat) -> 5 | R90: 1 | S90: =if((ISBLANK(R90)),"",SkillFeat) -> 5 | U90: =if((ISBLANK(T90)),"",SkillFeat) | W90: =if((ISBLANK(V90)),"",SkillFeat) | Y90: =if((ISBLANK(X90)),"",SkillFeat) | AA90: =if((ISBLANK(Z90)),"",SkillFeat) | AC90: =if((ISBLANK(AB90)),"",SkillFeat) | AE90: =if((ISBLANK(AD90)),"",SkillFeat) | AG90: =if((ISBLANK(AF90)),"",SkillFeat) | AI90: =if((ISBLANK(AH90)),"",SkillFeat) | AK90: =if((ISBLANK(AJ90)),"",SkillFeat) | AM90: =if((ISBLANK(AL90)),"",SkillFeat) | AO90: =if((ISBLANK(AN90)),"",SkillFeat) | AQ90: =if((ISBLANK(AP90)),"",SkillFeat) | AS90: =if((ISBLANK(AR90)),"",SkillFeat) | AU90: =if((ISBLANK(AT90)),"",SkillFeat) | AW90: =if((ISBLANK(AV90)),"",SkillFeat) | AY90: =if((ISBLANK(AX90)),"",SkillFeat) | BA90: =if((ISBLANK(AZ90)),"",SkillFeat)
A91: SkillFeatExtra-L12 | B91: L12 | D91: 1 | E91: =if((ISBLANK(D91)),"",SkillFeat) -> 5 | G91: =if((ISBLANK(F91)),"",SkillFeat) | I91: =if((ISBLANK(H91)),"",SkillFeat) | K91: =if((ISBLANK(J91)),"",SkillFeat) | M91: =if((ISBLANK(L91)),"",SkillFeat) | O91: =if((ISBLANK(N91)),"",SkillFeat) | Q91: =if((ISBLANK(P91)),"",SkillFeat) | S91: =if((ISBLANK(R91)),"",SkillFeat) | U91: =if((ISBLANK(T91)),"",SkillFeat) | W91: =if((ISBLANK(V91)),"",SkillFeat) | Y91: =if((ISBLANK(X91)),"",SkillFeat) | AA91: =if((ISBLANK(Z91)),"",SkillFeat) | AC91: =if((ISBLANK(AB91)),"",SkillFeat) | AE91: =if((ISBLANK(AD91)),"",SkillFeat) | AG91: =if((ISBLANK(AF91)),"",SkillFeat) | AI91: =if((ISBLANK(AH91)),"",SkillFeat) | AK91: =if((ISBLANK(AJ91)),"",SkillFeat) | AM91: =if((ISBLANK(AL91)),"",SkillFeat) | AO91: =if((ISBLANK(AN91)),"",SkillFeat) | AQ91: =if((ISBLANK(AP91)),"",SkillFeat) | AS91: =if((ISBLANK(AR91)),"",SkillFeat) | AU91: =if((ISBLANK(AT91)),"",SkillFeat) | AW91: =if((ISBLANK(AV91)),"",SkillFeat) | AY91: =if((ISBLANK(AX91)),"",SkillFeat) | BA91: =if((ISBLANK(AZ91)),"",SkillFeat)
A92: SkillFeatExtra-L13 | B92: L13 | D92: 1 | E92: =if((ISBLANK(D92)),"",SkillFeat) -> 5 | G92: =if((ISBLANK(F92)),"",SkillFeat) | I92: =if((ISBLANK(H92)),"",SkillFeat) | K92: =if((ISBLANK(J92)),"",SkillFeat) | M92: =if((ISBLANK(L92)),"",SkillFeat) | O92: =if((ISBLANK(N92)),"",SkillFeat) | P92: 1 | Q92: =if((ISBLANK(P92)),"",SkillFeat) -> 5 | R92: 1 | S92: =if((ISBLANK(R92)),"",SkillFeat) -> 5 | U92: =if((ISBLANK(T92)),"",SkillFeat) | W92: =if((ISBLANK(V92)),"",SkillFeat) | Y92: =if((ISBLANK(X92)),"",SkillFeat) | AA92: =if((ISBLANK(Z92)),"",SkillFeat) | AC92: =if((ISBLANK(AB92)),"",SkillFeat) | AE92: =if((ISBLANK(AD92)),"",SkillFeat) | AG92: =if((ISBLANK(AF92)),"",SkillFeat) | AI92: =if((ISBLANK(AH92)),"",SkillFeat) | AK92: =if((ISBLANK(AJ92)),"",SkillFeat) | AM92: =if((ISBLANK(AL92)),"",SkillFeat) | AO92: =if((ISBLANK(AN92)),"",SkillFeat) | AQ92: =if((ISBLANK(AP92)),"",SkillFeat) | AS92: =if((ISBLANK(AR92)),"",SkillFeat) | AU92: =if((ISBLANK(AT92)),"",SkillFeat) | AW92: =if((ISBLANK(AV92)),"",SkillFeat) | AY92: =if((ISBLANK(AX92)),"",SkillFeat) | BA92: =if((ISBLANK(AZ92)),"",SkillFeat)
A93: SkillFeatExtra-L14 | B93: L14 | D93: 1 | E93: =if((ISBLANK(D93)),"",SkillFeat) -> 5 | G93: =if((ISBLANK(F93)),"",SkillFeat) | I93: =if((ISBLANK(H93)),"",SkillFeat) | K93: =if((ISBLANK(J93)),"",SkillFeat) | M93: =if((ISBLANK(L93)),"",SkillFeat) | O93: =if((ISBLANK(N93)),"",SkillFeat) | Q93: =if((ISBLANK(P93)),"",SkillFeat) | S93: =if((ISBLANK(R93)),"",SkillFeat) | U93: =if((ISBLANK(T93)),"",SkillFeat) | W93: =if((ISBLANK(V93)),"",SkillFeat) | Y93: =if((ISBLANK(X93)),"",SkillFeat) | AA93: =if((ISBLANK(Z93)),"",SkillFeat) | AC93: =if((ISBLANK(AB93)),"",SkillFeat) | AE93: =if((ISBLANK(AD93)),"",SkillFeat) | AG93: =if((ISBLANK(AF93)),"",SkillFeat) | AI93: =if((ISBLANK(AH93)),"",SkillFeat) | AK93: =if((ISBLANK(AJ93)),"",SkillFeat) | AM93: =if((ISBLANK(AL93)),"",SkillFeat) | AO93: =if((ISBLANK(AN93)),"",SkillFeat) | AQ93: =if((ISBLANK(AP93)),"",SkillFeat) | AS93: =if((ISBLANK(AR93)),"",SkillFeat) | AU93: =if((ISBLANK(AT93)),"",SkillFeat) | AW93: =if((ISBLANK(AV93)),"",SkillFeat) | AY93: =if((ISBLANK(AX93)),"",SkillFeat) | BA93: =if((ISBLANK(AZ93)),"",SkillFeat)
A94: SkillFeatExtra-L15 | B94: L15 | D94: 1 | E94: =if((ISBLANK(D94)),"",SkillFeat) -> 5 | G94: =if((ISBLANK(F94)),"",SkillFeat) | I94: =if((ISBLANK(H94)),"",SkillFeat) | K94: =if((ISBLANK(J94)),"",SkillFeat) | M94: =if((ISBLANK(L94)),"",SkillFeat) | O94: =if((ISBLANK(N94)),"",SkillFeat) | P94: 1 | Q94: =if((ISBLANK(P94)),"",SkillFeat) -> 5 | R94: 1 | S94: =if((ISBLANK(R94)),"",SkillFeat) -> 5 | U94: =if((ISBLANK(T94)),"",SkillFeat) | V94: 1 | W94: =if((ISBLANK(V94)),"",SkillFeat) -> 5 | Y94: =if((ISBLANK(X94)),"",SkillFeat) | AA94: =if((ISBLANK(Z94)),"",SkillFeat) | AC94: =if((ISBLANK(AB94)),"",SkillFeat) | AE94: =if((ISBLANK(AD94)),"",SkillFeat) | AG94: =if((ISBLANK(AF94)),"",SkillFeat) | AI94: =if((ISBLANK(AH94)),"",SkillFeat) | AK94: =if((ISBLANK(AJ94)),"",SkillFeat) | AM94: =if((ISBLANK(AL94)),"",SkillFeat) | AO94: =if((ISBLANK(AN94)),"",SkillFeat) | AQ94: =if((ISBLANK(AP94)),"",SkillFeat) | AS94: =if((ISBLANK(AR94)),"",SkillFeat) | AU94: =if((ISBLANK(AT94)),"",SkillFeat) | AW94: =if((ISBLANK(AV94)),"",SkillFeat) | AY94: =if((ISBLANK(AX94)),"",SkillFeat) | BA94: =if((ISBLANK(AZ94)),"",SkillFeat)
A95: SkillFeatExtra-L16 | B95: L16 | D95: 1 | E95: =if((ISBLANK(D95)),"",SkillFeat) -> 5 | G95: =if((ISBLANK(F95)),"",SkillFeat) | I95: =if((ISBLANK(H95)),"",SkillFeat) | K95: =if((ISBLANK(J95)),"",SkillFeat) | M95: =if((ISBLANK(L95)),"",SkillFeat) | O95: =if((ISBLANK(N95)),"",SkillFeat) | Q95: =if((ISBLANK(P95)),"",SkillFeat) | S95: =if((ISBLANK(R95)),"",SkillFeat) | U95: =if((ISBLANK(T95)),"",SkillFeat) | W95: =if((ISBLANK(V95)),"",SkillFeat) | Y95: =if((ISBLANK(X95)),"",SkillFeat) | AA95: =if((ISBLANK(Z95)),"",SkillFeat) | AC95: =if((ISBLANK(AB95)),"",SkillFeat) | AE95: =if((ISBLANK(AD95)),"",SkillFeat) | AG95: =if((ISBLANK(AF95)),"",SkillFeat) | AI95: =if((ISBLANK(AH95)),"",SkillFeat) | AK95: =if((ISBLANK(AJ95)),"",SkillFeat) | AM95: =if((ISBLANK(AL95)),"",SkillFeat) | AO95: =if((ISBLANK(AN95)),"",SkillFeat) | AQ95: =if((ISBLANK(AP95)),"",SkillFeat) | AS95: =if((ISBLANK(AR95)),"",SkillFeat) | AU95: =if((ISBLANK(AT95)),"",SkillFeat) | AW95: =if((ISBLANK(AV95)),"",SkillFeat) | AY95: =if((ISBLANK(AX95)),"",SkillFeat) | BA95: =if((ISBLANK(AZ95)),"",SkillFeat)
A96: SkillFeatExtra-L17 | B96: L17 | D96: 1 | E96: =if((ISBLANK(D96)),"",SkillFeat) -> 5 | G96: =if((ISBLANK(F96)),"",SkillFeat) | I96: =if((ISBLANK(H96)),"",SkillFeat) | K96: =if((ISBLANK(J96)),"",SkillFeat) | M96: =if((ISBLANK(L96)),"",SkillFeat) | O96: =if((ISBLANK(N96)),"",SkillFeat) | P96: 1 | Q96: =if((ISBLANK(P96)),"",SkillFeat) -> 5 | R96: 1 | S96: =if((ISBLANK(R96)),"",SkillFeat) -> 5 | U96: =if((ISBLANK(T96)),"",SkillFeat) | W96: =if((ISBLANK(V96)),"",SkillFeat) | Y96: =if((ISBLANK(X96)),"",SkillFeat) | AA96: =if((ISBLANK(Z96)),"",SkillFeat) | AC96: =if((ISBLANK(AB96)),"",SkillFeat) | AE96: =if((ISBLANK(AD96)),"",SkillFeat) | AG96: =if((ISBLANK(AF96)),"",SkillFeat) | AI96: =if((ISBLANK(AH96)),"",SkillFeat) | AK96: =if((ISBLANK(AJ96)),"",SkillFeat) | AM96: =if((ISBLANK(AL96)),"",SkillFeat) | AO96: =if((ISBLANK(AN96)),"",SkillFeat) | AQ96: =if((ISBLANK(AP96)),"",SkillFeat) | AS96: =if((ISBLANK(AR96)),"",SkillFeat) | AU96: =if((ISBLANK(AT96)),"",SkillFeat) | AW96: =if((ISBLANK(AV96)),"",SkillFeat) | AY96: =if((ISBLANK(AX96)),"",SkillFeat) | BA96: =if((ISBLANK(AZ96)),"",SkillFeat)
A97: SkillFeatExtra-L18 | B97: L18 | D97: 1 | E97: =if((ISBLANK(D97)),"",SkillFeat) -> 5 | G97: =if((ISBLANK(F97)),"",SkillFeat) | I97: =if((ISBLANK(H97)),"",SkillFeat) | K97: =if((ISBLANK(J97)),"",SkillFeat) | M97: =if((ISBLANK(L97)),"",SkillFeat) | O97: =if((ISBLANK(N97)),"",SkillFeat) | Q97: =if((ISBLANK(P97)),"",SkillFeat) | S97: =if((ISBLANK(R97)),"",SkillFeat) | U97: =if((ISBLANK(T97)),"",SkillFeat) | W97: =if((ISBLANK(V97)),"",SkillFeat) | Y97: =if((ISBLANK(X97)),"",SkillFeat) | AA97: =if((ISBLANK(Z97)),"",SkillFeat) | AC97: =if((ISBLANK(AB97)),"",SkillFeat) | AE97: =if((ISBLANK(AD97)),"",SkillFeat) | AG97: =if((ISBLANK(AF97)),"",SkillFeat) | AI97: =if((ISBLANK(AH97)),"",SkillFeat) | AK97: =if((ISBLANK(AJ97)),"",SkillFeat) | AM97: =if((ISBLANK(AL97)),"",SkillFeat) | AO97: =if((ISBLANK(AN97)),"",SkillFeat) | AQ97: =if((ISBLANK(AP97)),"",SkillFeat) | AS97: =if((ISBLANK(AR97)),"",SkillFeat) | AU97: =if((ISBLANK(AT97)),"",SkillFeat) | AW97: =if((ISBLANK(AV97)),"",SkillFeat) | AY97: =if((ISBLANK(AX97)),"",SkillFeat) | BA97: =if((ISBLANK(AZ97)),"",SkillFeat)
A98: SkillFeatExtra-L19 | B98: L19 | D98: 1 | E98: =if((ISBLANK(D98)),"",SkillFeat) -> 5 | G98: =if((ISBLANK(F98)),"",SkillFeat) | I98: =if((ISBLANK(H98)),"",SkillFeat) | K98: =if((ISBLANK(J98)),"",SkillFeat) | M98: =if((ISBLANK(L98)),"",SkillFeat) | O98: =if((ISBLANK(N98)),"",SkillFeat) | P98: 1 | Q98: =if((ISBLANK(P98)),"",SkillFeat) -> 5 | R98: 1 | S98: =if((ISBLANK(R98)),"",SkillFeat) -> 5 | U98: =if((ISBLANK(T98)),"",SkillFeat) | W98: =if((ISBLANK(V98)),"",SkillFeat) | Y98: =if((ISBLANK(X98)),"",SkillFeat) | AA98: =if((ISBLANK(Z98)),"",SkillFeat) | AC98: =if((ISBLANK(AB98)),"",SkillFeat) | AE98: =if((ISBLANK(AD98)),"",SkillFeat) | AG98: =if((ISBLANK(AF98)),"",SkillFeat) | AI98: =if((ISBLANK(AH98)),"",SkillFeat) | AK98: =if((ISBLANK(AJ98)),"",SkillFeat) | AM98: =if((ISBLANK(AL98)),"",SkillFeat) | AO98: =if((ISBLANK(AN98)),"",SkillFeat) | AQ98: =if((ISBLANK(AP98)),"",SkillFeat) | AS98: =if((ISBLANK(AR98)),"",SkillFeat) | AU98: =if((ISBLANK(AT98)),"",SkillFeat) | AW98: =if((ISBLANK(AV98)),"",SkillFeat) | AY98: =if((ISBLANK(AX98)),"",SkillFeat) | BA98: =if((ISBLANK(AZ98)),"",SkillFeat)
A99: SkillFeatExtra-L20 | B99: L20 | D99: 1 | E99: =if((ISBLANK(D99)),"",SkillFeat) -> 5 | G99: =if((ISBLANK(F99)),"",SkillFeat) | I99: =if((ISBLANK(H99)),"",SkillFeat) | K99: =if((ISBLANK(J99)),"",SkillFeat) | M99: =if((ISBLANK(L99)),"",SkillFeat) | O99: =if((ISBLANK(N99)),"",SkillFeat) | Q99: =if((ISBLANK(P99)),"",SkillFeat) | S99: =if((ISBLANK(R99)),"",SkillFeat) | U99: =if((ISBLANK(T99)),"",SkillFeat) | W99: =if((ISBLANK(V99)),"",SkillFeat) | Y99: =if((ISBLANK(X99)),"",SkillFeat) | AA99: =if((ISBLANK(Z99)),"",SkillFeat) | AC99: =if((ISBLANK(AB99)),"",SkillFeat) | AE99: =if((ISBLANK(AD99)),"",SkillFeat) | AG99: =if((ISBLANK(AF99)),"",SkillFeat) | AI99: =if((ISBLANK(AH99)),"",SkillFeat) | AK99: =if((ISBLANK(AJ99)),"",SkillFeat) | AM99: =if((ISBLANK(AL99)),"",SkillFeat) | AO99: =if((ISBLANK(AN99)),"",SkillFeat) | AQ99: =if((ISBLANK(AP99)),"",SkillFeat) | AS99: =if((ISBLANK(AR99)),"",SkillFeat) | AU99: =if((ISBLANK(AT99)),"",SkillFeat) | AW99: =if((ISBLANK(AV99)),"",SkillFeat) | AY99: =if((ISBLANK(AX99)),"",SkillFeat) | BA99: =if((ISBLANK(AZ99)),"",SkillFeat)
A100: SkillFeatExtraTotal | D100: =SUM(D80:D99) -> 20 | E100: =SUM(E80:E99) -> 100 | F100: =SUM(F80:F99) -> 0 | G100: =SUM(G80:G99) -> 0 | H100: =SUM(H80:H99) -> 0 | I100: =SUM(I80:I99) -> 0 | J100: =SUM(J80:J99) -> 0 | K100: =SUM(K80:K99) -> 0 | ... AC100: =SUM(AC80:AC99) -> 0 | AE100: =SUM(AE80:AE99) -> 0 | AF100: =SUM(AF80:AF99) -> 0 | AG100: =SUM(AG80:AG99) -> 0 | AH100: =SUM(AH80:AH99) -> 0 | AI100: =SUM(AI80:AI99) -> 0 | AJ100: =SUM(AJ80:AJ99) -> 0 | AK100: =SUM(AK80:AK99) -> 0 | AL100: =SUM(AL80:AL99) -> 0 | ... BA100: =SUM(BA80:BA99) -> 0
...

Sheet CLASSTOTALS
A2: CLASS | D2: GROUP | E2: Proficiencies | F2: Initial Proficiency | G2: L00 | H2: 01 | I2: 02 | J2: 03 | K2: 04 | L2: 05 | M2: 06 | N2: 07 | O2: 08 | P2: 09 | Q2: 10 | R2: 11 | S2: 12 | T2: 13 | U2: 14 | V2: 15 | W2: 16 | X2: 17 | Y2: 18 | Z2: 19 | AA2: 20 | AB2: Final | AC2: Row Totals
A3: =VLOOKUP($C3, CLASSNUMBERFINDER, 2, false) -> 1 | C3: Champion
A4: {={"FormulaRow01";(INDEX(CLASSLIST,A3,1))}} -> FormulaRow01 | B4: FILTERFORMULAOUT | C4: {={"CLASSTYPE";(INDEX(ALLCLASSDATA,MATCH("ClassType",CLASSFEATUREHEADERS,0),MATCH($A5,CLASSNAMEHEADERS,0)))}} -> CLASSTYPE | D4: {={"TOTAL";("Total: " & H5+J5+L5+N5+P5+R5+T5+V5+X5+Z5)}} -> TOTAL | E4: {={"BALANCE";(IF((H5+J5+L5+N5+P5+R5+T5+V5+X5+Z5)=2100,"(balanced)",(IF((H5+J5+L5+N5+P5+R5+T5+V5+X5+Z5)>2100,"OVERBUDGET: ","UNDERBUDGET: ")) & (H5+J5+L5+N5+P5+R5+T5+V5+X5+Z5-2100)))}} -> BALANCE | H4: {={"SUM LVL0/1/2";((SUMIF(F6:I85,"<>#REF!")+(SUMIF(J6:AA13,"<>#REF!"))))}} -> SUM LVL0/1/2 | J4: {={"SUM LVL3/4";(SUMIF(J14:K85,"<>#REF!"))}} -> SUM LVL3/4 | L4: {={"SUM LVL5/6";(SUMIF(L14:M85,"<>#REF!"))}} -> SUM LVL5/6 | N4: {={"SUM LVL7/8";(SUMIF(N14:O85,"<>#REF!"))}} -> SUM LVL7/8 | P4: {={"SUM LVL9/10";(SUMIF(P14:Q85,"<>#REF!"))}} -> SUM LVL9/10 | R4: {={"SUM LVL11/12";(SUMIF(R14:S85,"<>#REF!"))}} -> SUM LVL11/12 | T4: {={"SUM LVL13/14";(SUMIF(T14:U85,"<>#REF!"))}} -> SUM LVL13/14 | V4: {={"SUM LVL15/16";(SUMIF(V14:W85,"<>#REF!"))}} -> SUM LVL15/16 | X4: {={"SUM LVL17/18";(SUMIF(X14:Y85,"<>#REF!"))}} -> SUM LVL17/18 | Z4: {={"SUM LVL19/20";(SUMIF(Z14:AA85,"<>#REF!"))}} -> SUM LVL19/20 | AC4: {={"SUM ROWTOTALS";(SUMIF(AC7:AC93,"<>#REF!"))}} -> SUM ROWTOTALS
A5: Champion | C5: Soldier | D5: Total: 2100 | E5: (balanced) | H5: 420 | J5: 30 | L5: 50 | N5: 170 | P5: 300 | R5: 270 | T5: 220 | V5: 150 | X5: 300 | Z5: 190 | AC5: 2100
A6: {={"FormulaRow02";(INDEX(CLASSLIST,A3,1))}} -> FormulaRow02 | B6: FILTERFORMULAOUT | C6: {={"CLASSTYPE";((INDEX(ALLCLASSDATA,MATCH("ClassType",CLASSFEATUREHEADERS,0),MATCH($A7,CLASSNAMEHEADERS,0))))}} -> CLASSTYPE | D6: {={"FEATURES";"Features"}} -> FEATURES | E6: {={"INITIALFEATURES";"Initial Features"}} -> INITIALFEATURES | F6: {={"KEY";"Key"}} -> KEY | G6: {={"HP";"HP"}} -> HP | H6: {={"CLASSFEATL01";"ClassFeatL01"}} -> CLASSFEATL01 | I6: {={"SHIELDBLOCKL01";"ShieldBlockL01"}} -> SHIELDBLOCKL01 | J6: {={"INITIALSKILLS";"InitialSkills"}} -> INITIALSKILLS | K6: {={"SUBCLASSSKILLS";"SubclassSkills"}} -> SUBCLASSSKILLS | L6: {={"GRANTEDSKILLS";"GrantedSkills"}} -> GRANTEDSKILLS | P6: {={"FOCUSSPELLS";"FocusSpells:"}} -> FOCUSSPELLS | Q6: {={"FOCUSSPELL1-L00";((INDEX(ALLCLASSDATA,MATCH("FocusSpell1-L00",CLASSFEATUREHEADERS,0),MATCH(($A7),CLASSNAMEHEADERS,0))))}} -> FOCUSSPELL1-L00 | R6: {={"FOCUSSPELL2-L00";((INDEX(ALLCLASSDATA,MATCH("FocusSpell2-L00",CLASSFEATUREHEADERS,0),MATCH(($A7),CLASSNAMEHEADERS,0))))}} -> FOCUSSPELL2-L00 | S6: {={"FOCUSSPELL3-L00";((INDEX(ALLCLASSDATA,MATCH("FocusSpell3-L00",CLASSFEATUREHEADERS,0),MATCH(($A7),CLASSNAMEHEADERS,0))))}} -> FOCUSSPELL3-L00 | T6: {={"FOCUSSPELL4-L00";((INDEX(ALLCLASSDATA,MATCH("FocusSpell4-L00",CLASSFEATUREHEADERS,0),MATCH(($A7),CLASSNAMEHEADERS,0))))}} -> FOCUSSPELL4-L00 | U6: {={"FOCUSSPELL5-L00";((INDEX(ALLCLASSDATA,MATCH("FocusSpell5-L00",CLASSFEATUREHEADERS,0),MATCH(($A7),CLASSNAMEHEADERS,0))))}} -> FOCUSSPELL5-L00
A7: Champion | C7: Soldier | D7: Features | E7: Initial Features | F7: Key | G7: HP | H7: ClassFeatL01 | I7: ShieldBlockL01 | J7: InitialSkills | K7: SubclassSkills | L7: GrantedSkills | P7: FocusSpells: | Q7: Lay on Hands or Touch of Corruption
A8: {={"FormulaRow03";(INDEX(CLASSLIST,A3,1))}} -> FormulaRow03 | B8: FILTERFORMULAOUT | C8: {={"CLASSTYPE";((INDEX(ALLCLASSDATA,MATCH("ClassType",CLASSFEATUREHEADERS,0),MATCH($A9,CLASSNAMEHEADERS,0))))}} -> CLASSTYPE | D8: {={"FEATUREPTS";"FeaturesPts"}} -> FEATUREPTS | E8: {={"INITIALFEATURES";"Initial Features"}} -> INITIALFEATURES | F8: {={"KEYABILITY";((INDEX(ALLCLASSDATA,MATCH("KEYABILITY",CLASSFEATUREHEADERS,0),MATCH($A9,CLASSNAMEHEADERS,0))))}} -> KEYABILITY | G8: {={"HP";((INDEX(ALLCLASSDATA,MATCH("HP",CLASSFEATUREHEADERS,0),MATCH(($A9 & "Points"),CLASSNAMEHEADERS,0))))}} -> HP | H8: {={"CLASSFEATL01";((INDEX(ALLCLASSDATA,MATCH("ClassFeatL01",CLASSFEATUREHEADERS,0),MATCH(($A9 & "Points"),CLASSNAMEHEADERS,0))))}} -> CLASSFEATL01 | I8: {={"SHIELDBLOCKL01";((INDEX(ALLCLASSDATA,MATCH("ShieldBlockL01",CLASSFEATUREHEADERS,0),MATCH(($A9 & "Points"),CLASSNAMEHEADERS,0))))}} -> SHIELDBLOCKL01 | J8: {={"INITIALSKILLINCREASES";((INDEX(ALLCLASSDATA,MATCH("InitialSkillIncreases",CLASSFEATUREHEADERS,0),MATCH(($A9 & "Points"),CLASSNAMEHEADERS,0))))}} -> INITIALSKILLINCREASES | K8: {={"SUBCLASSSKILLINCREASES";((INDEX(ALLCLASSDATA,MATCH("SubclassSkillIncreases",CLASSFEATUREHEADERS,0),MATCH(($A9 & "Points"),CLASSNAMEHEADERS,0))))}} -> SUBCLASSSKILLINCREASES | L8: {={"GRANTEDSKILLS";(((INDEX(ALLCLASSDATA,MATCH("SkillsGrantedTotal",CLASSFEATUREHEADERS,0),MATCH(($A9 & "Points"),CLASSNAMEHEADERS,0)))-(INDEX(ALLCLASSDATA,MATCH("InitialSkillIncreases",CLASSFEATUREHEADERS,0),MATCH(($A9 & "Points"),CLASSNAMEHEADERS,0)))-(INDEX(ALLCLASSDATA,MATCH("SubclassSkillIncreases",CLASSFEATUREHEADERS,0),MATCH(($A9 & "Points"),CLASSNAMEHEADERS,0)))))}} -> GRANTEDSKILLS | Q8: {={"FOCUSSPELL1-L00";((INDEX(ALLCLASSDATA,MATCH("FocusSpell1-L00",CLASSFEATUREHEADERS,0),MATCH(($A9 & "Points"),CLASSNAMEHEADERS,0))))}} -> FOCUSSPELL1-L00 | R8: {={"FOCUSSPELL2-L00";((INDEX(ALLCLASSDATA,MATCH("FocusSpell2-L00",CLASSFEATUREHEADERS,0),MATCH(($A9 & "Points"),CLASSNAMEHEADERS,0))))}} -> FOCUSSPELL2-L00 | S8: {={"FOCUSSPELL3-L00";((INDEX(ALLCLASSDATA,MATCH("FocusSpell3-L00",CLASSFEATUREHEADERS,0),MATCH(($A9 & "Points"),CLASSNAMEHEADERS,0))))}} -> FOCUSSPELL3-L00 | T8: {={"FOCUSSPELL4-L00";((INDEX(ALLCLASSDATA,MATCH("FocusSpell4-L00",CLASSFEATUREHEADERS,0),MATCH(($A9 & "Points"),CLASSNAMEHEADERS,0))))}} -> FOCUSSPELL4-L00 | U8: {={"FOCUSSPELL5-L00";((INDEX(ALLCLASSDATA,MATCH("FocusSpell5-L00",CLASSFEATUREHEADERS,0),MATCH(($A9 & "Points"),CLASSNAMEHEADERS,0))))}} -> FOCUSSPELL5-L00 | AC8: {={"FEATUREPTS TOTAL";(sum(G9:AA9))}} -> FEATUREPTS TOTAL
A9: Champion | C9: Soldier | D9: FeaturesPts | E9: Initial Features | F9: STR/DEX | G9: 100 | H9: 10 | I9: 10 | J9: 10 | K9: 5 | L9: 5 | Q9: 10 | AC9: 150
A10: {={"FormulaRow04";(INDEX(CLASSLIST,A3,1))}} -> FormulaRow04 | B10: FILTERFORMULAOUT | C10: {={"CLASSTYPE";((INDEX(ALLCLASSDATA,MATCH("ClassType",CLASSFEATUREHEADERS,0),MATCH($A11,CLASSNAMEHEADERS,0))))}} -> CLASSTYPE | D10: {={"INITIALFEATURES";"InitialFeatures"}} -> INITIALFEATURES | E10: {={"CLASS/SUBCLASSFEATURES";"Class/Subclass Features"}} -> CLASS/SUBCLASSFEATURES | H10: {={"CLASSINITIALABILITY1-L00";((INDEX(ALLCLASSDATA,MATCH("ClassInitialAbility1-L00",CLASSFEATUREHEADERS,0),MATCH(($A11),CLASSNAMEHEADERS,0))))}} -> CLASSINITIALABILITY1-L00 | I10: {={"CLASSINITIALABILITY2-L00";((INDEX(ALLCLASSDATA,MATCH("ClassInitialAbility2-L00",CLASSFEATUREHEADERS,0),MATCH(($A11),CLASSNAMEHEADERS,0))))}} -> CLASSINITIALABILITY2-L00 | J10: {={"CLASSINITIALABILITY3-L00";((INDEX(ALLCLASSDATA,MATCH("ClassInitialAbility3-L00",CLASSFEATUREHEADERS,0),MATCH(($A11),CLASSNAMEHEADERS,0))))}} -> CLASSINITIALABILITY3-L00 | K10: {={"CLASSINITIALABILITY4-L00";((INDEX(ALLCLASSDATA,MATCH("ClassInitialAbility4-L00",CLASSFEATUREHEADERS,0),MATCH(($A11),CLASSNAMEHEADERS,0))))}} -> CLASSINITIALABILITY4-L00 | L10: {={"CLASSINITIALABILITY5-L00";((INDEX(ALLCLASSDATA,MATCH("ClassInitialAbility5-L00",CLASSFEATUREHEADERS,0),MATCH(($A11),CLASSNAMEHEADERS,0))))}} -> CLASSINITIALABILITY5-L00 | M10: {={"CLASSINITIALABILITY6-L00";((INDEX(ALLCLASSDATA,MATCH("ClassInitialAbility6-L00",CLASSFEATUREHEADERS,0),MATCH(($A11),CLASSNAMEHEADERS,0))))}} -> CLASSINITIALABILITY6-L00 | N10: {={"CLASSINITIALABILITY7-L00";((INDEX(ALLCLASSDATA,MATCH("ClassInitialAbility7-L00",CLASSFEATUREHEADERS,0),MATCH(($A11),CLASSNAMEHEADERS,0))))}} -> CLASSINITIALABILITY7-L00 | O10: {={"CLASSINITIALABILITY8-L00";((INDEX(ALLCLASSDATA,MATCH("ClassInitialAbility8-L00",CLASSFEATUREHEADERS,0),MATCH(($A11),CLASSNAMEHEADERS,0))))}} -> CLASSINITIALABILITY8-L00 | P10: {={"CLASSINITIALABILITY9-L00";((INDEX(ALLCLASSDATA,MATCH("ClassInitialAbility9-L00",CLASSFEATUREHEADERS,0),MATCH(($A11),CLASSNAMEHEADERS,0))))}} -> CLASSINITIALABILITY9-L00 | Q10: {={"CLASSINITIALABILITY10-L00";((INDEX(ALLCLASSDATA,MATCH("ClassInitialAbility10-L00",CLASSFEATUREHEADERS,0),MATCH(($A11),CLASSNAMEHEADERS,0))))}} -> CLASSINITIALABILITY10-L00 | R10: {={"SUBCLASSINITIAL1-L00";((INDEX(ALLCLASSDATA,MATCH("SubclassInitial1-L00",CLASSFEATUREHEADERS,0),MATCH(($A11),CLASSNAMEHEADERS,0))))}} -> SUBCLASSINITIAL1-L00 | S10: {={"SUBCLASSINITIAL2-L00";((INDEX(ALLCLASSDATA,MATCH("SubclassInitial2-L00",CLASSFEATUREHEADERS,0),MATCH(($A11),CLASSNAMEHEADERS,0))))}} -> SUBCLASSINITIAL2-L00 | T10: {={"SUBCLASSINITIAL3-L00";((INDEX(ALLCLASSDATA,MATCH("SubclassInitial3-L00",CLASSFEATUREHEADERS,0),MATCH(($A11),CLASSNAMEHEADERS,0))))}} -> SUBCLASSINITIAL3-L00 | U10: {={"SUBCLASSINITIAL4-L00";((INDEX(ALLCLASSDATA,MATCH("SubclassInitial4-L00",CLASSFEATUREHEADERS,0),MATCH(($A11),CLASSNAMEHEADERS,0))))}} -> SUBCLASSINITIAL4-L00 | V10: {={"SUBCLASSINITIAL5-L00";((INDEX(ALLCLASSDATA,MATCH("SubclassInitial5-L00",CLASSFEATUREHEADERS,0),MATCH(($A11),CLASSNAMEHEADERS,0))))}} -> SUBCLASSINITIAL5-L00 | W10: {={"SUBCLASSINITIAL6-L00";((INDEX(ALLCLASSDATA,MATCH("SubclassInitial6-L00",CLASSFEATUREHEADERS,0),MATCH(($A11),CLASSNAMEHEADERS,0))))}} -> SUBCLASSINITIAL6-L00 | X10: {={"SUBCLASSINITIAL7-L00";((INDEX(ALLCLASSDATA,MATCH("SubclassInitial7-L00",CLASSFEATUREHEADERS,0),MATCH(($A11),CLASSNAMEHEADERS,0))))}} -> SUBCLASSINITIAL7-L00 | Y10: {={"SUBCLASSINITIAL8-L00";((INDEX(ALLCLASSDATA,MATCH("SubclassInitial8-L00",CLASSFEATUREHEADERS,0),MATCH(($A11),CLASSNAMEHEADERS,0))))}} -> SUBCLASSINITIAL8-L00 | Z10: {={"SUBCLASSINITIAL9-L00";((INDEX(ALLCLASSDATA,MATCH("SubclassInitial9-L00",CLASSFEATUREHEADERS,0),MATCH(($A11),CLASSNAMEHEADERS,0))))}} -> SUBCLASSINITIAL9-L00 | AA10: {={"SUBCLASSINITIAL10-L00";((INDEX(ALLCLASSDATA,MATCH("SubclassInitial10-L00",CLASSFEATUREHEADERS,0),MATCH(($A11),CLASSNAMEHEADERS,0))))}} -> SUBCLASSINITIAL10-L00
A11: Champion | C11: Soldier | D11: InitialFeatures | E11: Class/Subclass Features | H11: Champion's Code | I11: Deific Weapon | J11: Deity and Cause | K11: Devotion Spells | L11: Shield Block | R11: Champion's Reaction
A12: {={"FormulaRow05";(INDEX(CLASSLIST,A3,1))}} -> FormulaRow05 | B12: FILTERFORMULAOUT | C12: {={"CLASSTYPE";((INDEX(ALLCLASSDATA,MATCH("ClassType",CLASSFEATUREHEADERS,0),MATCH($A13,CLASSNAMEHEADERS,0))))}} -> CLASSTYPE | D12: {={"INITIALFEATURESPTS";"InitialFeaturesPts"}} -> INITIALFEATURESPTS | E12: {={"CLASS/SUBCLASSFEATURES";"Class/Subclass Features"}} -> CLASS/SUBCLASSFEATURES | H12: {={"CLASSINITIALABILITY1-L00PTS";((INDEX(ALLCLASSDATA,MATCH("ClassInitialAbility1-L00",CLASSFEATUREHEADERS,0),MATCH(($A13 & "Points"),CLASSNAMEHEADERS,0))))}} -> CLASSINITIALABILITY1-L00PTS | I12: {={"CLASSINITIALABILITY2-L00PTS";((INDEX(ALLCLASSDATA,MATCH("ClassInitialAbility2-L00",CLASSFEATUREHEADERS,0),MATCH(($A13 & "Points"),CLASSNAMEHEADERS,0))))}} -> CLASSINITIALABILITY2-L00PTS | J12: {={"CLASSINITIALABILITY3-L00PTS";((INDEX(ALLCLASSDATA,MATCH("ClassInitialAbility3-L00",CLASSFEATUREHEADERS,0),MATCH(($A13 & "Points"),CLASSNAMEHEADERS,0))))}} -> CLASSINITIALABILITY3-L00PTS | K12: {={"CLASSINITIALABILITY4-L00PTS";((INDEX(ALLCLASSDATA,MATCH("ClassInitialAbility4-L00",CLASSFEATUREHEADERS,0),MATCH(($A13 & "Points"),CLASSNAMEHEADERS,0))))}} -> CLASSINITIALABILITY4-L00PTS | L12: {={"CLASSINITIALABILITY5-L00PTS";((INDEX(ALLCLASSDATA,MATCH("ClassInitialAbility5-L00",CLASSFEATUREHEADERS,0),MATCH(($A13 & "Points"),CLASSNAMEHEADERS,0))))}} -> CLASSINITIALABILITY5-L00PTS | M12: {={"CLASSINITIALABILITY6-L00PTS";((INDEX(ALLCLASSDATA,MATCH("ClassInitialAbility6-L00",CLASSFEATUREHEADERS,0),MATCH(($A13 & "Points"),CLASSNAMEHEADERS,0))))}} -> CLASSINITIALABILITY6-L00PTS | N12: {={"CLASSINITIALABILITY7-L00PTS";((INDEX(ALLCLASSDATA,MATCH("ClassInitialAbility7-L00",CLASSFEATUREHEADERS,0),MATCH(($A13 & "Points"),CLASSNAMEHEADERS,0))))}} -> CLASSINITIALABILITY7-L00PTS | O12: {={"CLASSINITIALABILITY8-L00PTS";((INDEX(ALLCLASSDATA,MATCH("ClassInitialAbility8-L00",CLASSFEATUREHEADERS,0),MATCH(($A13 & "Points"),CLASSNAMEHEADERS,0))))}} -> CLASSINITIALABILITY8-L00PTS | P12: {={"CLASSINITIALABILITY9-L00PTS";((INDEX(ALLCLASSDATA,MATCH("ClassInitialAbility9-L00",CLASSFEATUREHEADERS,0),MATCH(($A13 & "Points"),CLASSNAMEHEADERS,0))))}} -> CLASSINITIALABILITY9-L00PTS | Q12: {={"CLASSINITIALABILITY10-L00PTS";((INDEX(ALLCLASSDATA,MATCH("ClassInitialAbility10-L00",CLASSFEATUREHEADERS,0),MATCH(($A13 & "Points"),CLASSNAMEHEADERS,0))))}} -> CLASSINITIALABILITY10-L00PTS | R12: {={"SUBCLASSINITIAL1-L00PTS";((INDEX(ALLCLASSDATA,MATCH("SubclassInitial1-L00",CLASSFEATUREHEADERS,0),MATCH(($A13 & "Points"),CLASSNAMEHEADERS,0))))}} -> SUBCLASSINITIAL1-L00PTS | S12: {={"SUBCLASSINITIAL2-L00PTS";((INDEX(ALLCLASSDATA,MATCH("SubclassInitial2-L00",CLASSFEATUREHEADERS,0),MATCH(($A13 & "Points"),CLASSNAMEHEADERS,0))))}} -> SUBCLASSINITIAL2-L00PTS | T12: {={"SUBCLASSINITIAL3-L00PTS";((INDEX(ALLCLASSDATA,MATCH("SubclassInitial3-L00",CLASSFEATUREHEADERS,0),MATCH(($A13 & "Points"),CLASSNAMEHEADERS,0))))}} -> SUBCLASSINITIAL3-L00PTS | U12: {={"SUBCLASSINITIAL4-L00PTS";((INDEX(ALLCLASSDATA,MATCH("SubclassInitial4-L00",CLASSFEATUREHEADERS,0),MATCH(($A13 & "Points"),CLASSNAMEHEADERS,0))))}} -> SUBCLASSINITIAL4-L00PTS | V12: {={"SUBCLASSINITIAL5-L00PTS";((INDEX(ALLCLASSDATA,MATCH("SubclassInitial5-L00",CLASSFEATUREHEADERS,0),MATCH(($A13 & "Points"),CLASSNAMEHEADERS,0))))}} -> SUBCLASSINITIAL5-L00PTS | W12: {={"SUBCLASSINITIAL6-L00PTS";((INDEX(ALLCLASSDATA,MATCH("SubclassInitial6-L00",CLASSFEATUREHEADERS,0),MATCH(($A13 & "Points"),CLASSNAMEHEADERS,0))))}} -> SUBCLASSINITIAL6-L00PTS | X12: {={"SUBCLASSINITIAL7-L00PTS";((INDEX(ALLCLASSDATA,MATCH("SubclassInitial7-L00",CLASSFEATUREHEADERS,0),MATCH(($A13 & "Points"),CLASSNAMEHEADERS,0))))}} -> SUBCLASSINITIAL7-L00PTS | Y12: {={"SUBCLASSINITIAL8-L00PTS";((INDEX(ALLCLASSDATA,MATCH("SubclassInitial8-L00",CLASSFEATUREHEADERS,0),MATCH(($A13 & "Points"),CLASSNAMEHEADERS,0))))}} -> SUBCLASSINITIAL8-L00PTS | Z12: {={"SUBCLASSINITIAL9-L00PTS";((INDEX(ALLCLASSDATA,MATCH("SubclassInitial9-L00",CLASSFEATUREHEADERS,0),MATCH(($A13 & "Points"),CLASSNAMEHEADERS,0))))}} -> SUBCLASSINITIAL9-L00PTS | AA12: {={"SUBCLASSINITIAL10-L00PTS";((INDEX(ALLCLASSDATA,MATCH("SubclassInitial10-L00",CLASSFEATUREHEADERS,0),MATCH(($A13 & "Points"),CLASSNAMEHEADERS,0))))}} -> SUBCLASSINITIAL10-L00PTS | AC12: {={"INITIALFEATUREPTS TOTAL";(sum(G13:AA13))}} -> INITIALFEATUREPTS TOTAL
A13: Champion | C13: Soldier | D13: InitialFeaturesPts | E13: Class/Subclass Features | R13: 50 | AC13: 50
A14: {={"FormulaRow06";(INDEX(CLASSLIST,A3,1))}} -> FormulaRow06 | B14: FILTERFORMULAOUT | C14: {={"CLASSTYPE";((INDEX(ALLCLASSDATA,MATCH("ClassType",CLASSFEATUREHEADERS,0),MATCH($A15,CLASSNAMEHEADERS,0))))}} -> CLASSTYPE | D14: {={"SKILLS";"Skills"}} -> SKILLS | E14: {={"EXTRASKILLINCREASES";"Extra Skill Increases"}} -> EXTRASKILLINCREASES | I14: {={"SKILLINCREASEEXTRA-L02";((INDEX(ALLCLASSDATA,MATCH("SkillIncreaseExtra-L02",CLASSFEATUREHEADERS,0),MATCH(($A15 & "Points"),CLASSNAMEHEADERS,0))))}} -> SKILLINCREASEEXTRA-L02 | J14: {={"SKILLINCREASEEXTRA-L03";((INDEX(ALLCLASSDATA,MATCH("SkillIncreaseExtra-L03",CLASSFEATUREHEADERS,0),MATCH(($A15 & "Points"),CLASSNAMEHEADERS,0))))}} -> SKILLINCREASEEXTRA-L03 | K14: {={"SKILLINCREASEEXTRA-L04";((INDEX(ALLCLASSDATA,MATCH("SkillIncreaseExtra-L04",CLASSFEATUREHEADERS,0),MATCH(($A15 & "Points"),CLASSNAMEHEADERS,0))))}} -> SKILLINCREASEEXTRA-L04 | L14: {={"SKILLINCREASEEXTRA-L05";((INDEX(ALLCLASSDATA,MATCH("SkillIncreaseExtra-L05",CLASSFEATUREHEADERS,0),MATCH(($A15 & "Points"),CLASSNAMEHEADERS,0))))}} -> SKILLINCREASEEXTRA-L05 | M14: {={"SKILLINCREASEEXTRA-L06";((INDEX(ALLCLASSDATA,MATCH("SkillIncreaseExtra-L06",CLASSFEATUREHEADERS,0),MATCH(($A15 & "Points"),CLASSNAMEHEADERS,0))))}} -> SKILLINCREASEEXTRA-L06 | N14: {={"SKILLINCREASEEXTRA-L07";((INDEX(ALLCLASSDATA,MATCH("SkillIncreaseExtra-L07",CLASSFEATUREHEADERS,0),MATCH(($A15 & "Points"),CLASSNAMEHEADERS,0))))}} -> SKILLINCREASEEXTRA-L07 | O14: {={"SKILLINCREASEEXTRA-L08";((INDEX(ALLCLASSDATA,MATCH("SkillIncreaseExtra-L08",CLASSFEATUREHEADERS,0),MATCH(($A15 & "Points"),CLASSNAMEHEADERS,0))))}} -> SKILLINCREASEEXTRA-L08 | P14: {={"SKILLINCREASEEXTRA-L09";((INDEX(ALLCLASSDATA,MATCH("SkillIncreaseExtra-L09",CLASSFEATUREHEADERS,0),MATCH(($A15 & "Points"),CLASSNAMEHEADERS,0))))}} -> SKILLINCREASEEXTRA-L09 | Q14: {={"SKILLINCREASEEXTRA-L10";((INDEX(ALLCLASSDATA,MATCH("SkillIncreaseExtra-L10",CLASSFEATUREHEADERS,0),MATCH(($A15 & "Points"),CLASSNAMEHEADERS,0))))}} -> SKILLINCREASEEXTRA-L10 | R14: {={"SKILLINCREASEEXTRA-L11";((INDEX(ALLCLASSDATA,MATCH("SkillIncreaseExtra-L11",CLASSFEATUREHEADERS,0),MATCH(($A15 & "Points"),CLASSNAMEHEADERS,0))))}} -> SKILLINCREASEEXTRA-L11 | S14: {={"SKILLINCREASEEXTRA-L12";((INDEX(ALLCLASSDATA,MATCH("SkillIncreaseExtra-L12",CLASSFEATUREHEADERS,0),MATCH(($A15 & "Points"),CLASSNAMEHEADERS,0))))}} -> SKILLINCREASEEXTRA-L12 | T14: {={"SKILLINCREASEEXTRA-L13";((INDEX(ALLCLASSDATA,MATCH("SkillIncreaseExtra-L13",CLASSFEATUREHEADERS,0),MATCH(($A15 & "Points"),CLASSNAMEHEADERS,0))))}} -> SKILLINCREASEEXTRA-L13 | U14: {={"SKILLINCREASEEXTRA-L14";((INDEX(ALLCLASSDATA,MATCH("SkillIncreaseExtra-L14",CLASSFEATUREHEADERS,0),MATCH(($A15 & "Points"),CLASSNAMEHEADERS,0))))}} -> SKILLINCREASEEXTRA-L14 | V14: {={"SKILLINCREASEEXTRA-L15";((INDEX(ALLCLASSDATA,MATCH("SkillIncreaseExtra-L15",CLASSFEATUREHEADERS,0),MATCH(($A15 & "Points"),CLASSNAMEHEADERS,0))))}} -> SKILLINCREASEEXTRA-L15 | W14: {={"SKILLINCREASEEXTRA-L16";((INDEX(ALLCLASSDATA,MATCH("SkillIncreaseExtra-L16",CLASSFEATUREHEADERS,0),MATCH(($A15 & "Points"),CLASSNAMEHEADERS,0))))}} -> SKILLINCREASEEXTRA-L16 | X14: {={"SKILLINCREASEEXTRA-L17";((INDEX(ALLCLASSDATA,MATCH("SkillIncreaseExtra-L17",CLASSFEATUREHEADERS,0),MATCH(($A15 & "Points"),CLASSNAMEHEADERS,0))))}} -> SKILLINCREASEEXTRA-L17 | Y14: {={"SKILLINCREASEEXTRA-L18";((INDEX(ALLCLASSDATA,MATCH("SkillIncreaseExtra-L18",CLASSFEATUREHEADERS,0),MATCH(($A15 & "Points"),CLASSNAMEHEADERS,0))))}} -> SKILLINCREASEEXTRA-L18 | Z14: {={"SKILLINCREASEEXTRA-L19";((INDEX(ALLCLASSDATA,MATCH("SkillIncreaseExtra-L19",CLASSFEATUREHEADERS,0),MATCH(($A15 & "Points"),CLASSNAMEHEADERS,0))))}} -> SKILLINCREASEEXTRA-L19 | AA14: {={"SKILLINCREASEEXTRA-L20";((INDEX(ALLCLASSDATA,MATCH("SkillIncreaseExtra-L20",CLASSFEATUREHEADERS,0),MATCH(($A15 & "Points"),CLASSNAMEHEADERS,0))))}} -> SKILLINCREASEEXTRA-L20 | AC14: {={"SKILLINCREASE TOTAL";(sum(G15:AA15))}} -> SKILLINCREASE TOTAL
A15: Champion | C15: Soldier | D15: Skills | E15: Extra Skill Increases | AC15: 0
A16: {={"FormulaRow07";(INDEX(CLASSLIST,A3,1))}} -> FormulaRow07 | B16: FILTERFORMULAOUT | C16: {={"CLASSTYPE";((INDEX(ALLCLASSDATA,MATCH("ClassType",CLASSFEATUREHEADERS,0),MATCH($A17,CLASSNAMEHEADERS,0))))}} -> CLASSTYPE | D16: {={"SKILLS";"Skills"}} -> SKILLS | E16: {={"EXTRASKILLFEATS";"Extra Skill Feats"}} -> EXTRASKILLFEATS | H16: {={"SKILLFEATEXTRA-L01";((INDEX(ALLCLASSDATA,MATCH("SkillFeatExtra-L01",CLASSFEATUREHEADERS,0),MATCH(($A17 & "Points"),CLASSNAMEHEADERS,0))))}} -> SKILLFEATEXTRA-L01 | I16: {={"SKILLFEATEXTRA-L02";((INDEX(ALLCLASSDATA,MATCH("SkillFeatExtra-L02",CLASSFEATUREHEADERS,0),MATCH(($A17 & "Points"),CLASSNAMEHEADERS,0))))}} -> SKILLFEATEXTRA-L02 | J16: {={"SKILLFEATEXTRA-L03";((INDEX(ALLCLASSDATA,MATCH("SkillFeatExtra-L03",CLASSFEATUREHEADERS,0),MATCH(($A17 & "Points"),CLASSNAMEHEADERS,0))))}} -> SKILLFEATEXTRA-L03 | K16: {={"SKILLFEATEXTRA-L04";((INDEX(ALLCLASSDATA,MATCH("SkillFeatExtra-L04",CLASSFEATUREHEADERS,0),MATCH(($A17 & "Points"),CLASSNAMEHEADERS,0))))}} -> SKILLFEATEXTRA-L04 | L16: {={"SKILLFEATEXTRA-L05";((INDEX(ALLCLASSDATA,MATCH("SkillFeatExtra-L05",CLASSFEATUREHEADERS,0),MATCH(($A17 & "Points"),CLASSNAMEHEADERS,0))))}} -> SKILLFEATEXTRA-L05 | M16: {={"SKILLFEATEXTRA-L06";((INDEX(ALLCLASSDATA,MATCH("SkillFeatExtra-L06",CLASSFEATUREHEADERS,0),MATCH(($A17 & "Points"),CLASSNAMEHEADERS,0))))}} -> SKILLFEATEXTRA-L06 | N16: {={"SKILLFEATEXTRA-L07";((INDEX(ALLCLASSDATA,MATCH("SkillFeatExtra-L07",CLASSFEATUREHEADERS,0),MATCH(($A17 & "Points"),CLASSNAMEHEADERS,0))))}} -> SKILLFEATEXTRA-L07 | O16: {={"SKILLFEATEXTRA-L08";((INDEX(ALLCLASSDATA,MATCH("SkillFeatExtra-L08",CLASSFEATUREHEADERS,0),MATCH(($A17 & "Points"),CLASSNAMEHEADERS,0))))}} -> SKILLFEATEXTRA-L08 | P16: {={"SKILLFEATEXTRA-L09";((INDEX(ALLCLASSDATA,MATCH("SkillFeatExtra-L09",CLASSFEATUREHEADERS,0),MATCH(($A17 & "Points"),CLASSNAMEHEADERS,0))))}} -> SKILLFEATEXTRA-L09 | Q16: {={"SKILLFEATEXTRA-L10";((INDEX(ALLCLASSDATA,MATCH("SkillFeatExtra-L10",CLASSFEATUREHEADERS,0),MATCH(($A17 & "Points"),CLASSNAMEHEADERS,0))))}} -> SKILLFEATEXTRA-L10 | R16: {={"SKILLFEATEXTRA-L11";((INDEX(ALLCLASSDATA,MATCH("SkillFeatExtra-L11",CLASSFEATUREHEADERS,0),MATCH(($A17 & "Points"),CLASSNAMEHEADERS,0))))}} -> SKILLFEATEXTRA-L11 | S16: {={"SKILLFEATEXTRA-L12";((INDEX(ALLCLASSDATA,MATCH("SkillFeatExtra-L12",CLASSFEATUREHEADERS,0),MATCH(($A17 & "Points"),CLASSNAMEHEADERS,0))))}} -> SKILLFEATEXTRA-L12 | T16: {={"SKILLFEATEXTRA-L13";((INDEX(ALLCLASSDATA,MATCH("SkillFeatExtra-L13",CLASSFEATUREHEADERS,0),MATCH(($A17 & "Points"),CLASSNAMEHEADERS,0))))}} -> SKILLFEATEXTRA-L13 | U16: {={"SKILLFEATEXTRA-L14";((INDEX(ALLCLASSDATA,MATCH("SkillFeatExtra-L14",CLASSFEATUREHEADERS,0),MATCH(($A17 & "Points"),CLASSNAMEHEADERS,0))))}} -> SKILLFEATEXTRA-L14 | V16: {={"SKILLFEATEXTRA-L15";((INDEX(ALLCLASSDATA,MATCH("SkillFeatExtra-L15",CLASSFEATUREHEADERS,0),MATCH(($A17 & "Points"),CLASSNAMEHEADERS,0))))}} -> SKILLFEATEXTRA-L15 | W16: {={"SKILLFEATEXTRA-L16";((INDEX(ALLCLASSDATA,MATCH("SkillFeatExtra-L16",CLASSFEATUREHEADERS,0),MATCH(($A17 & "Points"),CLASSNAMEHEADERS,0))))}} -> SKILLFEATEXTRA-L16 | X16: {={"SKILLFEATEXTRA-L17";((INDEX(ALLCLASSDATA,MATCH("SkillFeatExtra-L17",CLASSFEATUREHEADERS,0),MATCH(($A17 & "Points"),CLASSNAMEHEADERS,0))))}} -> SKILLFEATEXTRA-L17 | Y16: {={"SKILLFEATEXTRA-L18";((INDEX(ALLCLASSDATA,MATCH("SkillFeatExtra-L18",CLASSFEATUREHEADERS,0),MATCH(($A17 & "Points"),CLASSNAMEHEADERS,0))))}} -> SKILLFEATEXTRA-L18 | Z16: {={"SKILLFEATEXTRA-L19";((INDEX(ALLCLASSDATA,MATCH("SkillFeatExtra-L19",CLASSFEATUREHEADERS,0),MATCH(($A17 & "Points"),CLASSNAMEHEADERS,0))))}} -> SKILLFEATEXTRA-L19 | AA16: {={"SKILLFEATEXTRA-L20";((INDEX(ALLCLASSDATA,MATCH("SkillFeatExtra-L20",CLASSFEATUREHEADERS,0),MATCH(($A17 & "Points"),CLASSNAMEHEADERS,0))))}} -> SKILLFEATEXTRA-L20 | AC16: {={"SKILLFEAT TOTAL";(sum(G17:AA17))}} -> SKILLFEAT TOTAL
A17: Champion | C17: Soldier | D17: Skills | E17: Extra Skill Feats | AC17: 0
A18: {={"FormulaRow08";(INDEX(CLASSLIST,A3,1))}} -> FormulaRow08 | B18: FILTERFORMULAOUT | C18: {={"CLASSTYPE";((INDEX(ALLCLASSDATA,MATCH("ClassType",CLASSFEATUREHEADERS,0),MATCH($A19,CLASSNAMEHEADERS,0))))}} -> CLASSTYPE | D18: {={"CLASSABILITY";"ClassAbility"}} -> CLASSABILITY | E18: {={"CLASSABILITY1";"ClassAbility1"}} -> CLASSABILITY1 | J18: {={"CLASSABILITY1-L03";((INDEX(ALLCLASSDATA,MATCH("ClassAbility1-L03",CLASSFEATUREHEADERS,0),MATCH(($A19),CLASSNAMEHEADERS,0))))}} -> CLASSABILITY1-L03 | L18: {={"CLASSABILITY1-L05";((INDEX(ALLCLASSDATA,MATCH("ClassAbility1-L05",CLASSFEATUREHEADERS,0),MATCH(($A19),CLASSNAMEHEADERS,0))))}} -> CLASSABILITY1-L05 | N18: {={"CLASSABILITY1-L07";((INDEX(ALLCLASSDATA,MATCH("ClassAbility1-L07",CLASSFEATUREHEADERS,0),MATCH(($A19),CLASSNAMEHEADERS,0))))}} -> CLASSABILITY1-L07 | P18: {={"CLASSABILITY1-L09";((INDEX(ALLCLASSDATA,MATCH("ClassAbility1-L09",CLASSFEATUREHEADERS,0),MATCH(($A19),CLASSNAMEHEADERS,0))))}} -> CLASSABILITY1-L09 | R18: {={"CLASSABILITY1-L11";((INDEX(ALLCLASSDATA,MATCH("ClassAbility1-L11",CLASSFEATUREHEADERS,0),MATCH(($A19),CLASSNAMEHEADERS,0))))}} -> CLASSABILITY1-L11 | T18: {={"CLASSABILITY1-L13";((INDEX(ALLCLASSDATA,MATCH("ClassAbility1-L13",CLASSFEATUREHEADERS,0),MATCH(($A19),CLASSNAMEHEADERS,0))))}} -> CLASSABILITY1-L13 | V18: {={"CLASSABILITY1-L15";((INDEX(ALLCLASSDATA,MATCH("ClassAbility1-L15",CLASSFEATUREHEADERS,0),MATCH(($A19),CLASSNAMEHEADERS,0))))}} -> CLASSABILITY1-L15 | X18: {={"CLASSABILITY1-L17";((INDEX(ALLCLASSDATA,MATCH("ClassAbility1-L17",CLASSFEATUREHEADERS,0),MATCH(($A19),CLASSNAMEHEADERS,0))))}} -> CLASSABILITY1-L17 | Z18: {={"CLASSABILITY1-L19";((INDEX(ALLCLASSDATA,MATCH("ClassAbility1-L19",CLASSFEATUREHEADERS,0),MATCH(($A19),CLASSNAMEHEADERS,0))))}} -> CLASSABILITY1-L19
A19: Champion | C19: Soldier | D19: ClassAbility | E19: ClassAbility1 | J19: Divine Ally | L19: Weapon Expertise | N19: Weapon Specialization | P19: Champion Expertise | R19: Alertness | T19: Weapon Mastery | V19: Greater Weapon Specialization | X19: Champion Mastery | Z19: Hero's Defiance
A20: {={"FormulaRow09";(INDEX(CLASSLIST,A3,1))}} -> FormulaRow09 | B20: FILTERFORMULAOUT | C20: {={"CLASSTYPE";((INDEX(ALLCLASSDATA,MATCH("ClassType",CLASSFEATUREHEADERS,0),MATCH($A21,CLASSNAMEHEADERS,0))))}} -> CLASSTYPE | D20: {={"CLASSABILITYPTS";"ClassAbilityPts"}} -> CLASSABILITYPTS | E20: {={"CLASSABILITY1";"ClassAbility1"}} -> CLASSABILITY1 | J20: {={"CLASSABILITY1-L03PTS";((INDEX(ALLCLASSDATA,MATCH("ClassAbility1-L03",CLASSFEATUREHEADERS,0),MATCH(($A21 & "Points"),CLASSNAMEHEADERS,0))))}} -> CLASSABILITY1-L03PTS | L20: {={"CLASSABILITY1-L05PTS";((INDEX(ALLCLASSDATA,MATCH("ClassAbility1-L05",CLASSFEATUREHEADERS,0),MATCH(($A21 & "Points"),CLASSNAMEHEADERS,0))))}} -> CLASSABILITY1-L05PTS | N20: {={"CLASSABILITY1-L07PTS";((INDEX(ALLCLASSDATA,MATCH("ClassAbility1-L07",CLASSFEATUREHEADERS,0),MATCH(($A21 & "Points"),CLASSNAMEHEADERS,0))))}} -> CLASSABILITY1-L07PTS | P20: {={"CLASSABILITY1-L09PTS";((INDEX(ALLCLASSDATA,MATCH("ClassAbility1-L09",CLASSFEATUREHEADERS,0),MATCH(($A21 & "Points"),CLASSNAMEHEADERS,0))))}} -> CLASSABILITY1-L09PTS | R20: {={"CLASSABILITY1-L11PTS";((INDEX(ALLCLASSDATA,MATCH("ClassAbility1-L11",CLASSFEATUREHEADERS,0),MATCH(($A21 & "Points"),CLASSNAMEHEADERS,0))))}} -> CLASSABILITY1-L11PTS | T20: {={"CLASSABILITY1-L13PTS";((INDEX(ALLCLASSDATA,MATCH("ClassAbility1-L13",CLASSFEATUREHEADERS,0),MATCH(($A21 & "Points"),CLASSNAMEHEADERS,0))))}} -> CLASSABILITY1-L13PTS | V20: {={"CLASSABILITY1-L15PTS";((INDEX(ALLCLASSDATA,MATCH("ClassAbility1-L15",CLASSFEATUREHEADERS,0),MATCH(($A21 & "Points"),CLASSNAMEHEADERS,0))))}} -> CLASSABILITY1-L15PTS | X20: {={"CLASSABILITY1-L17PTS";((INDEX(ALLCLASSDATA,MATCH("ClassAbility1-L17",CLASSFEATUREHEADERS,0),MATCH(($A21 & "Points"),CLASSNAMEHEADERS,0))))}} -> CLASSABILITY1-L17PTS | Z20: {={"CLASSABILITY1-L19PTS";((INDEX(ALLCLASSDATA,MATCH("ClassAbility1-L19",CLASSFEATUREHEADERS,0),MATCH(($A21 & "Points"),CLASSNAMEHEADERS,0))))}} -> CLASSABILITY1-L19PTS | AC20: {={"CLASSABILITY1 TOTAL";(sum(G21:AA21))}} -> CLASSABILITY1 TOTAL
A21: Champion | C21: Soldier | D21: ClassAbilityPts | E21: ClassAbility1 | J21: 30 | Z21: 190 | AC21: 220
A22: {={"FormulaRow10";(INDEX(CLASSLIST,A3,1))}} -> FormulaRow10 | B22: FILTERFORMULAOUT | C22: {={"CLASSTYPE";((INDEX(ALLCLASSDATA,MATCH("ClassType",CLASSFEATUREHEADERS,0),MATCH($A23,CLASSNAMEHEADERS,0))))}} -> CLASSTYPE | D22: {={"CLASSABILITY";"ClassAbility"}} -> CLASSABILITY | E22: {={"CLASSABILITY2";"ClassAbility2"}} -> CLASSABILITY2 | J22: {={"CLASSABILITY2-L03";((INDEX(ALLCLASSDATA,MATCH("ClassAbility2-L03",CLASSFEATUREHEADERS,0),MATCH(($A23),CLASSNAMEHEADERS,0))))}} -> CLASSABILITY2-L03 | L22: {={"CLASSABILITY2-L05";((INDEX(ALLCLASSDATA,MATCH("ClassAbility2-L05",CLASSFEATUREHEADERS,0),MATCH(($A23),CLASSNAMEHEADERS,0))))}} -> CLASSABILITY2-L05 | N22: {={"CLASSABILITY2-L07";((INDEX(ALLCLASSDATA,MATCH("ClassAbility2-L07",CLASSFEATUREHEADERS,0),MATCH(($A23),CLASSNAMEHEADERS,0))))}} -> CLASSABILITY2-L07 | P22: {={"CLASSABILITY2-L09";((INDEX(ALLCLASSDATA,MATCH("ClassAbility2-L09",CLASSFEATUREHEADERS,0),MATCH(($A23),CLASSNAMEHEADERS,0))))}} -> CLASSABILITY2-L09 | R22: {={"CLASSABILITY2-L11";((INDEX(ALLCLASSDATA,MATCH("ClassAbility2-L11",CLASSFEATUREHEADERS,0),MATCH(($A23),CLASSNAMEHEADERS,0))))}} -> CLASSABILITY2-L11 | T22: {={"CLASSABILITY2-L13";((INDEX(ALLCLASSDATA,MATCH("ClassAbility2-L13",CLASSFEATUREHEADERS,0),MATCH(($A23),CLASSNAMEHEADERS,0))))}} -> CLASSABILITY2-L13 | V22: {={"CLASSABILITY2-L15";((INDEX(ALLCLASSDATA,MATCH("ClassAbility2-L15",CLASSFEATUREHEADERS,0),MATCH(($A23),CLASSNAMEHEADERS,0))))}} -> CLASSABILITY2-L15 | X22: {={"CLASSABILITY2-L17";((INDEX(ALLCLASSDATA,MATCH("ClassAbility2-L17",CLASSFEATUREHEADERS,0),MATCH(($A23),CLASSNAMEHEADERS,0))))}} -> CLASSABILITY2-L17 | Z22: {={"CLASSABILITY2-L19";((INDEX(ALLCLASSDATA,MATCH("ClassAbility2-L19",CLASSFEATUREHEADERS,0),MATCH(($A23),CLASSNAMEHEADERS,0))))}} -> CLASSABILITY2-L19
A23: Champion | C23: Soldier | D23: ClassAbility | E23: ClassAbility2 | N23: Armor Expertise | P23: Lightning Reflexes | R23: Divine Will | T23: Armor Mastery | X23: Legendary Armor
A24: {={"FormulaRow11";(INDEX(CLASSLIST,A3,1))}} -> FormulaRow11 | B24: FILTERFORMULAOUT | C24: {={"CLASSTYPE";((INDEX(ALLCLASSDATA,MATCH("ClassType",CLASSFEATUREHEADERS,0),MATCH($A25,CLASSNAMEHEADERS,0))))}} -> CLASSTYPE | D24: {={"CLASSABILITYPTS";"ClassAbilityPts"}} -> CLASSABILITYPTS | E24: {={"CLASSABILITY2";"ClassAbility2"}} -> CLASSABILITY2 | J24: {={"CLASSABILITY2-L03PTS";((INDEX(ALLCLASSDATA,MATCH("ClassAbility2-L03",CLASSFEATUREHEADERS,0),MATCH(($A25 & "Points"),CLASSNAMEHEADERS,0))))}} -> CLASSABILITY2-L03PTS | L24: {={"CLASSABILITY2-L05PTS";((INDEX(ALLCLASSDATA,MATCH("ClassAbility2-L05",CLASSFEATUREHEADERS,0),MATCH(($A25 & "Points"),CLASSNAMEHEADERS,0))))}} -> CLASSABILITY2-L05PTS | N24: {={"CLASSABILITY2-L07PTS";((INDEX(ALLCLASSDATA,MATCH("ClassAbility2-L07",CLASSFEATUREHEADERS,0),MATCH(($A25 & "Points"),CLASSNAMEHEADERS,0))))}} -> CLASSABILITY2-L07PTS | P24: {={"CLASSABILITY2-L09PTS";((INDEX(ALLCLASSDATA,MATCH("ClassAbility2-L09",CLASSFEATUREHEADERS,0),MATCH(($A25 & "Points"),CLASSNAMEHEADERS,0))))}} -> CLASSABILITY2-L09PTS | R24: {={"CLASSABILITY2-L11PTS";((INDEX(ALLCLASSDATA,MATCH("ClassAbility2-L11",CLASSFEATUREHEADERS,0),MATCH(($A25 & "Points"),CLASSNAMEHEADERS,0))))}} -> CLASSABILITY2-L11PTS | T24: {={"CLASSABILITY2-L13PTS";((INDEX(ALLCLASSDATA,MATCH("ClassAbility2-L13",CLASSFEATUREHEADERS,0),MATCH(($A25 & "Points"),CLASSNAMEHEADERS,0))))}} -> CLASSABILITY2-L13PTS | V24: {={"CLASSABILITY2-L15PTS";((INDEX(ALLCLASSDATA,MATCH("ClassAbility2-L15",CLASSFEATUREHEADERS,0),MATCH(($A25 & "Points"),CLASSNAMEHEADERS,0))))}} -> CLASSABILITY2-L15PTS | X24: {={"CLASSABILITY2-L17PTS";((INDEX(ALLCLASSDATA,MATCH("ClassAbility2-L17",CLASSFEATUREHEADERS,0),MATCH(($A25 & "Points"),CLASSNAMEHEADERS,0))))}} -> CLASSABILITY2-L17PTS | Z24: {={"CLASSABILITY2-L19PTS";((INDEX(ALLCLASSDATA,MATCH("ClassAbility2-L19",CLASSFEATUREHEADERS,0),MATCH(($A25 & "Points"),CLASSNAMEHEADERS,0))))}} -> CLASSABILITY2-L19PTS | AC24: {={"CLASSABILITY2 TOTAL";(sum(G25:AA25))}} -> CLASSABILITY2 TOTAL
A25: Champion | C25: Soldier | D25: ClassAbilityPts | E25: ClassAbility2 | AC25: 0
A26: {={"FormulaRow12";(INDEX(CLASSLIST,A3,1))}} -> FormulaRow12 | B26: FILTERFORMULAOUT | C26: {={"CLASSTYPE";((INDEX(ALLCLASSDATA,MATCH("ClassType",CLASSFEATUREHEADERS,0),MATCH($A27,CLASSNAMEHEADERS,0))))}} -> CLASSTYPE | D26: {={"CLASSABILITY";"ClassAbility"}} -> CLASSABILITY | E26: {={"CLASSABILITY3";"ClassAbility3"}} -> CLASSABILITY3 | J26: {={"CLASSABILITY3-L03";((INDEX(ALLCLASSDATA,MATCH("ClassAbility3-L03",CLASSFEATUREHEADERS,0),MATCH(($A27),CLASSNAMEHEADERS,0))))}} -> CLASSABILITY3-L03 | L26: {={"CLASSABILITY3-L05";((INDEX(ALLCLASSDATA,MATCH("ClassAbility3-L05",CLASSFEATUREHEADERS,0),MATCH(($A27),CLASSNAMEHEADERS,0))))}} -> CLASSABILITY3-L05 | N26: {={"CLASSABILITY3-L07";((INDEX(ALLCLASSDATA,MATCH("ClassAbility3-L07",CLASSFEATUREHEADERS,0),MATCH(($A27),CLASSNAMEHEADERS,0))))}} -> CLASSABILITY3-L07 | P26: {={"CLASSABILITY3-L09";((INDEX(ALLCLASSDATA,MATCH("ClassAbility3-L09",CLASSFEATUREHEADERS,0),MATCH(($A27),CLASSNAMEHEADERS,0))))}} -> CLASSABILITY3-L09 | R26: {={"CLASSABILITY3-L11";((INDEX(ALLCLASSDATA,MATCH("ClassAbility3-L11",CLASSFEATUREHEADERS,0),MATCH(($A27),CLASSNAMEHEADERS,0))))}} -> CLASSABILITY3-L11 | T26: {={"CLASSABILITY3-L13";((INDEX(ALLCLASSDATA,MATCH("ClassAbility3-L13",CLASSFEATUREHEADERS,0),MATCH(($A27),CLASSNAMEHEADERS,0))))}} -> CLASSABILITY3-L13 | V26: {={"CLASSABILITY3-L15";((INDEX(ALLCLASSDATA,MATCH("ClassAbility3-L15",CLASSFEATUREHEADERS,0),MATCH(($A27),CLASSNAMEHEADERS,0))))}} -> CLASSABILITY3-L15 | X26: {={"CLASSABILITY3-L17";((INDEX(ALLCLASSDATA,MATCH("ClassAbility3-L17",CLASSFEATUREHEADERS,0),MATCH(($A27),CLASSNAMEHEADERS,0))))}} -> CLASSABILITY3-L17 | Z26: {={"CLASSABILITY3-L19";((INDEX(ALLCLASSDATA,MATCH("ClassAbility3-L19",CLASSFEATUREHEADERS,0),MATCH(($A27),CLASSNAMEHEADERS,0))))}} -> CLASSABILITY3-L19
A27: Champion | C27: Soldier | D27: ClassAbility | E27: ClassAbility3 | P27: Juggernaut
A28: {={"FormulaRow13";(INDEX(CLASSLIST,A3,1))}} -> FormulaRow13 | B28: FILTERFORMULAOUT | C28: {={"CLASSTYPE";((INDEX(ALLCLASSDATA,MATCH("ClassType",CLASSFEATUREHEADERS,0),MATCH($A29,CLASSNAMEHEADERS,0))))}} -> CLASSTYPE | D28: {={"CLASSABILITYPTS";"ClassAbilityPts"}} -> CLASSABILITYPTS | E28: {={"CLASSABILITY3";"ClassAbility3"}} -> CLASSABILITY3 | J28: {={"CLASSABILITY3-L03PTS";((INDEX(ALLCLASSDATA,MATCH("ClassAbility3-L03",CLASSFEATUREHEADERS,0),MATCH(($A29 & "Points"),CLASSNAMEHEADERS,0))))}} -> CLASSABILITY3-L03PTS | L28: {={"CLASSABILITY3-L05PTS";((INDEX(ALLCLASSDATA,MATCH("ClassAbility3-L05",CLASSFEATUREHEADERS,0),MATCH(($A29 & "Points"),CLASSNAMEHEADERS,0))))}} -> CLASSABILITY3-L05PTS | N28: {={"CLASSABILITY3-L07PTS";((INDEX(ALLCLASSDATA,MATCH("ClassAbility3-L07",CLASSFEATUREHEADERS,0),MATCH(($A29 & "Points"),CLASSNAMEHEADERS,0))))}} -> CLASSABILITY3-L07PTS | P28: {={"CLASSABILITY3-L09PTS";((INDEX(ALLCLASSDATA,MATCH("ClassAbility3-L09",CLASSFEATUREHEADERS,0),MATCH(($A29 & "Points"),CLASSNAMEHEADERS,0))))}} -> CLASSABILITY3-L09PTS | R28: {={"CLASSABILITY3-L11PTS";((INDEX(ALLCLASSDATA,MATCH("ClassAbility3-L11",CLASSFEATUREHEADERS,0),MATCH(($A29 & "Points"),CLASSNAMEHEADERS,0))))}} -> CLASSABILITY3-L11PTS | T28: {={"CLASSABILITY3-L13PTS";((INDEX(ALLCLASSDATA,MATCH("ClassAbility3-L13",CLASSFEATUREHEADERS,0),MATCH(($A29 & "Points"),CLASSNAMEHEADERS,0))))}} -> CLASSABILITY3-L13PTS | V28: {={"CLASSABILITY3-L15PTS";((INDEX(ALLCLASSDATA,MATCH("ClassAbility3-L15",CLASSFEATUREHEADERS,0),MATCH(($A29 & "Points"),CLASSNAMEHEADERS,0))))}} -> CLASSABILITY3-L15PTS | X28: {={"CLASSABILITY3-L17PTS";((INDEX(ALLCLASSDATA,MATCH("ClassAbility3-L17",CLASSFEATUREHEADERS,0),MATCH(($A29 & "Points"),CLASSNAMEHEADERS,0))))}} -> CLASSABILITY3-L17PTS | Z28: {={"CLASSABILITY3-L19PTS";((INDEX(ALLCLASSDATA,MATCH("ClassAbility3-L19",CLASSFEATUREHEADERS,0),MATCH(($A29 & "Points"),CLASSNAMEHEADERS,0))))}} -> CLASSABILITY3-L19PTS | AC28: {={"CLASSABILITY3 TOTAL";(sum(G29:AA29))}} -> CLASSABILITY3 TOTAL
A29: Champion | C29: Soldier | D29: ClassAbilityPts | E29: ClassAbility3 | AC29: 0
A30: {={"FormulaRow14";(INDEX(CLASSLIST,A3,1))}} -> FormulaRow14 | B30: FILTERFORMULAOUT | C30: {={"CLASSTYPE";((INDEX(ALLCLASSDATA,MATCH("ClassType",CLASSFEATUREHEADERS,0),MATCH($A31,CLASSNAMEHEADERS,0))))}} -> CLASSTYPE | D30: {={"CLASSABILITY";"ClassAbility"}} -> CLASSABILITY | E30: {={"CLASSABILITY4";"ClassAbility4"}} -> CLASSABILITY4 | J30: {={"CLASSABILITY4-L03";((INDEX(ALLCLASSDATA,MATCH("ClassAbility4-L03",CLASSFEATUREHEADERS,0),MATCH(($A31),CLASSNAMEHEADERS,0))))}} -> CLASSABILITY4-L03 | L30: {={"CLASSABILITY4-L05";((INDEX(ALLCLASSDATA,MATCH("ClassAbility4-L05",CLASSFEATUREHEADERS,0),MATCH(($A31),CLASSNAMEHEADERS,0))))}} -> CLASSABILITY4-L05 | N30: {={"CLASSABILITY4-L07";((INDEX(ALLCLASSDATA,MATCH("ClassAbility4-L07",CLASSFEATUREHEADERS,0),MATCH(($A31),CLASSNAMEHEADERS,0))))}} -> CLASSABILITY4-L07 | P30: {={"CLASSABILITY4-L09";((INDEX(ALLCLASSDATA,MATCH("ClassAbility4-L09",CLASSFEATUREHEADERS,0),MATCH(($A31),CLASSNAMEHEADERS,0))))}} -> CLASSABILITY4-L09 | R30: {={"CLASSABILITY4-L11";((INDEX(ALLCLASSDATA,MATCH("ClassAbility4-L11",CLASSFEATUREHEADERS,0),MATCH(($A31),CLASSNAMEHEADERS,0))))}} -> CLASSABILITY4-L11 | T30: {={"CLASSABILITY4-L13";((INDEX(ALLCLASSDATA,MATCH("ClassAbility4-L13",CLASSFEATUREHEADERS,0),MATCH(($A31),CLASSNAMEHEADERS,0))))}} -> CLASSABILITY4-L13 | V30: {={"CLASSABILITY4-L15";((INDEX(ALLCLASSDATA,MATCH("ClassAbility4-L15",CLASSFEATUREHEADERS,0),MATCH(($A31),CLASSNAMEHEADERS,0))))}} -> CLASSABILITY4-L15 | X30: {={"CLASSABILITY4-L17";((INDEX(ALLCLASSDATA,MATCH("ClassAbility4-L17",CLASSFEATUREHEADERS,0),MATCH(($A31),CLASSNAMEHEADERS,0))))}} -> CLASSABILITY4-L17 | Z30: {={"CLASSABILITY4-L19";((INDEX(ALLCLASSDATA,MATCH("ClassAbility4-L19",CLASSFEATUREHEADERS,0),MATCH(($A31),CLASSNAMEHEADERS,0))))}} -> CLASSABILITY4-L19
A31: Champion | C31: Soldier | D31: ClassAbility | E31: ClassAbility4
A32: {={"FormulaRow15";(INDEX(CLASSLIST,A3,1))}} -> FormulaRow15 | B32: FILTERFORMULAOUT | C32: {={"CLASSTYPE";((INDEX(ALLCLASSDATA,MATCH("ClassType",CLASSFEATUREHEADERS,0),MATCH($A33,CLASSNAMEHEADERS,0))))}} -> CLASSTYPE | D32: {={"CLASSABILITYPTS";"ClassAbilityPts"}} -> CLASSABILITYPTS | E32: {={"CLASSABILITY4";"ClassAbility4"}} -> CLASSABILITY4 | J32: {={"CLASSABILITY4-L03PTS";((INDEX(ALLCLASSDATA,MATCH("ClassAbility4-L03",CLASSFEATUREHEADERS,0),MATCH(($A33 & "Points"),CLASSNAMEHEADERS,0))))}} -> CLASSABILITY4-L03PTS | L32: {={"CLASSABILITY4-L05PTS";((INDEX(ALLCLASSDATA,MATCH("ClassAbility4-L05",CLASSFEATUREHEADERS,0),MATCH(($A33 & "Points"),CLASSNAMEHEADERS,0))))}} -> CLASSABILITY4-L05PTS | N32: {={"CLASSABILITY4-L07PTS";((INDEX(ALLCLASSDATA,MATCH("ClassAbility4-L07",CLASSFEATUREHEADERS,0),MATCH(($A33 & "Points"),CLASSNAMEHEADERS,0))))}} -> CLASSABILITY4-L07PTS | P32: {={"CLASSABILITY4-L09PTS";((INDEX(ALLCLASSDATA,MATCH("ClassAbility4-L09",CLASSFEATUREHEADERS,0),MATCH(($A33 & "Points"),CLASSNAMEHEADERS,0))))}} -> CLASSABILITY4-L09PTS | R32: {={"CLASSABILITY4-L11PTS";((INDEX(ALLCLASSDATA,MATCH("ClassAbility4-L11",CLASSFEATUREHEADERS,0),MATCH(($A33 & "Points"),CLASSNAMEHEADERS,0))))}} -> CLASSABILITY4-L11PTS | T32: {={"CLASSABILITY4-L13PTS";((INDEX(ALLCLASSDATA,MATCH("ClassAbility4-L13",CLASSFEATUREHEADERS,0),MATCH(($A33 & "Points"),CLASSNAMEHEADERS,0))))}} -> CLASSABILITY4-L13PTS | V32: {={"CLASSABILITY4-L15PTS";((INDEX(ALLCLASSDATA,MATCH("ClassAbility4-L15",CLASSFEATUREHEADERS,0),MATCH(($A33 & "Points"),CLASSNAMEHEADERS,0))))}} -> CLASSABILITY4-L15PTS | X32: {={"CLASSABILITY4-L17PTS";((INDEX(ALLCLASSDATA,MATCH("ClassAbility4-L17",CLASSFEATUREHEADERS,0),MATCH(($A33 & "Points"),CLASSNAMEHEADERS,0))))}} -> CLASSABILITY4-L17PTS | Z32: {={"CLASSABILITY4-L19PTS";((INDEX(ALLCLASSDATA,MATCH("ClassAbility4-L19",CLASSFEATUREHEADERS,0),MATCH(($A33 & "Points"),CLASSNAMEHEADERS,0))))}} -> CLASSABILITY4-L19PTS | AC32: {={"CLASSABILITY4 TOTAL";(sum(G33:AA33))}} -> CLASSABILITY4 TOTAL
A33: Champion | C33: Soldier | D33: ClassAbilityPts | E33: ClassAbility4 | AC33: 0
A34: {={"FormulaRow16";(INDEX(CLASSLIST,A3,1))}} -> FormulaRow16 | B34: FILTERFORMULAOUT | C34: {={"CLASSTYPE";((INDEX(ALLCLASSDATA,MATCH("ClassType",CLASSFEATUREHEADERS,0),MATCH($A35,CLASSNAMEHEADERS,0))))}} -> CLASSTYPE | D34: {={"CLASSABILITY";"ClassAbility"}} -> CLASSABILITY | E34: {={"SUBCLASSABILITY1";"SubclassAbility1"}} -> SUBCLASSABILITY1 | J34: {={"SUBCLASSABILITY1-L03";((INDEX(ALLCLASSDATA,MATCH("SubclassAbility1-L03",CLASSFEATUREHEADERS,0),MATCH(($A35),CLASSNAMEHEADERS,0))))}} -> SUBCLASSABILITY1-L03 | L34: {={"SUBCLASSABILITY1-L05";((INDEX(ALLCLASSDATA,MATCH("SubclassAbility1-L05",CLASSFEATUREHEADERS,0),MATCH(($A35),CLASSNAMEHEADERS,0))))}} -> SUBCLASSABILITY1-L05 | N34: {={"SUBCLASSABILITY1-L07";((INDEX(ALLCLASSDATA,MATCH("SubclassAbility1-L07",CLASSFEATUREHEADERS,0),MATCH(($A35),CLASSNAMEHEADERS,0))))}} -> SUBCLASSABILITY1-L07 | P34: {={"SUBCLASSABILITY1-L09";((INDEX(ALLCLASSDATA,MATCH("SubclassAbility1-L09",CLASSFEATUREHEADERS,0),MATCH(($A35),CLASSNAMEHEADERS,0))))}} -> SUBCLASSABILITY1-L09 | R34: {={"SUBCLASSABILITY1-L11";((INDEX(ALLCLASSDATA,MATCH("SubclassAbility1-L11",CLASSFEATUREHEADERS,0),MATCH(($A35),CLASSNAMEHEADERS,0))))}} -> SUBCLASSABILITY1-L11 | T34: {={"SUBCLASSABILITY1-L13";((INDEX(ALLCLASSDATA,MATCH("SubclassAbility1-L13",CLASSFEATUREHEADERS,0),MATCH(($A35),CLASSNAMEHEADERS,0))))}} -> SUBCLASSABILITY1-L13 | V34: {={"SUBCLASSABILITY1-L15";((INDEX(ALLCLASSDATA,MATCH("SubclassAbility1-L15",CLASSFEATUREHEADERS,0),MATCH(($A35),CLASSNAMEHEADERS,0))))}} -> SUBCLASSABILITY1-L15 | X34: {={"SUBCLASSABILITY1-L17";((INDEX(ALLCLASSDATA,MATCH("SubclassAbility1-L17",CLASSFEATUREHEADERS,0),MATCH(($A35),CLASSNAMEHEADERS,0))))}} -> SUBCLASSABILITY1-L17 | Z34: {={"SUBCLASSABILITY1-L19";((INDEX(ALLCLASSDATA,MATCH("SubclassAbility1-L19",CLASSFEATUREHEADERS,0),MATCH(($A35),CLASSNAMEHEADERS,0))))}} -> SUBCLASSABILITY1-L19
A35: Champion | C35: Soldier | D35: ClassAbility | E35: SubclassAbility1 | P35: Divine Smite | R35: Exalt
A36: {={"FormulaRow17";(INDEX(CLASSLIST,A3,1))}} -> FormulaRow17 | B36: FILTERFORMULAOUT | C36: {={"CLASSTYPE";((INDEX(ALLCLASSDATA,MATCH("ClassType",CLASSFEATUREHEADERS,0),MATCH($A37,CLASSNAMEHEADERS,0))))}} -> CLASSTYPE | D36: {={"CLASSABILITYPTS";"ClassAbilityPts"}} -> CLASSABILITYPTS | E36: {={"SUBCLASSABILITY1";"SubclassAbility1"}} -> SUBCLASSABILITY1 | J36: {={"SUBCLASSABILITY1-L03PTS";((INDEX(ALLCLASSDATA,MATCH("SubclassAbility1-L03",CLASSFEATUREHEADERS,0),MATCH(($A37 & "Points"),CLASSNAMEHEADERS,0))))}} -> SUBCLASSABILITY1-L03PTS | L36: {={"SUBCLASSABILITY1-L05PTS";((INDEX(ALLCLASSDATA,MATCH("SubclassAbility1-L05",CLASSFEATUREHEADERS,0),MATCH(($A37 & "Points"),CLASSNAMEHEADERS,0))))}} -> SUBCLASSABILITY1-L05PTS | N36: {={"SUBCLASSABILITY1-L07PTS";((INDEX(ALLCLASSDATA,MATCH("SubclassAbility1-L07",CLASSFEATUREHEADERS,0),MATCH(($A37 & "Points"),CLASSNAMEHEADERS,0))))}} -> SUBCLASSABILITY1-L07PTS | P36: {={"SUBCLASSABILITY1-L09PTS";((INDEX(ALLCLASSDATA,MATCH("SubclassAbility1-L09",CLASSFEATUREHEADERS,0),MATCH(($A37 & "Points"),CLASSNAMEHEADERS,0))))}} -> SUBCLASSABILITY1-L09PTS | R36: {={"SUBCLASSABILITY1-L11PTS";((INDEX(ALLCLASSDATA,MATCH("SubclassAbility1-L11",CLASSFEATUREHEADERS,0),MATCH(($A37 & "Points"),CLASSNAMEHEADERS,0))))}} -> SUBCLASSABILITY1-L11PTS | T36: {={"SUBCLASSABILITY1-L13PTS";((INDEX(ALLCLASSDATA,MATCH("SubclassAbility1-L13",CLASSFEATUREHEADERS,0),MATCH(($A37 & "Points"),CLASSNAMEHEADERS,0))))}} -> SUBCLASSABILITY1-L13PTS | V36: {={"SUBCLASSABILITY1-L15PTS";((INDEX(ALLCLASSDATA,MATCH("SubclassAbility1-L15",CLASSFEATUREHEADERS,0),MATCH(($A37 & "Points"),CLASSNAMEHEADERS,0))))}} -> SUBCLASSABILITY1-L15PTS | X36: {={"SUBCLASSABILITY1-L17PTS";((INDEX(ALLCLASSDATA,MATCH("SubclassAbility1-L17",CLASSFEATUREHEADERS,0),MATCH(($A37 & "Points"),CLASSNAMEHEADERS,0))))}} -> SUBCLASSABILITY1-L17PTS | Z36: {={"SUBCLASSABILITY1-L19PTS";((INDEX(ALLCLASSDATA,MATCH("SubclassAbility1-L19",CLASSFEATUREHEADERS,0),MATCH(($A37 & "Points"),CLASSNAMEHEADERS,0))))}} -> SUBCLASSABILITY1-L19PTS | AC36: {={"SUBCLASSABILITY1 TOTAL";(sum(G37:AA37))}} -> SUBCLASSABILITY1 TOTAL
A37: Champion | C37: Soldier | D37: ClassAbilityPts | E37: SubclassAbility1 | P37: 90 | R37: 110 | AC37: 200
A38: {={"FormulaRow18";(INDEX(CLASSLIST,A3,1))}} -> FormulaRow18 | B38: FILTERFORMULAOUT | C38: {={"CLASSTYPE";((INDEX(ALLCLASSDATA,MATCH("ClassType",CLASSFEATUREHEADERS,0),MATCH($A39,CLASSNAMEHEADERS,0))))}} -> CLASSTYPE | D38: {={"CLASSABILITY";"ClassAbility"}} -> CLASSABILITY | E38: {={"SUBCLASSABILITY2";"SubclassAbility2"}} -> SUBCLASSABILITY2 | J38: {={"SUBCLASSABILITY2-L03";((INDEX(ALLCLASSDATA,MATCH("SubclassAbility2-L03",CLASSFEATUREHEADERS,0),MATCH(($A39),CLASSNAMEHEADERS,0))))}} -> SUBCLASSABILITY2-L03 | L38: {={"SUBCLASSABILITY2-L05";((INDEX(ALLCLASSDATA,MATCH("SubclassAbility2-L05",CLASSFEATUREHEADERS,0),MATCH(($A39),CLASSNAMEHEADERS,0))))}} -> SUBCLASSABILITY2-L05 | N38: {={"SUBCLASSABILITY2-L07";((INDEX(ALLCLASSDATA,MATCH("SubclassAbility2-L07",CLASSFEATUREHEADERS,0),MATCH(($A39),CLASSNAMEHEADERS,0))))}} -> SUBCLASSABILITY2-L07 | P38: {={"SUBCLASSABILITY2-L09";((INDEX(ALLCLASSDATA,MATCH("SubclassAbility2-L09",CLASSFEATUREHEADERS,0),MATCH(($A39),CLASSNAMEHEADERS,0))))}} -> SUBCLASSABILITY2-L09 | R38: {={"SUBCLASSABILITY2-L11";((INDEX(ALLCLASSDATA,MATCH("SubclassAbility2-L11",CLASSFEATUREHEADERS,0),MATCH(($A39),CLASSNAMEHEADERS,0))))}} -> SUBCLASSABILITY2-L11 | T38: {={"SUBCLASSABILITY2-L13";((INDEX(ALLCLASSDATA,MATCH("SubclassAbility2-L13",CLASSFEATUREHEADERS,0),MATCH(($A39),CLASSNAMEHEADERS,0))))}} -> SUBCLASSABILITY2-L13 | V38: {={"SUBCLASSABILITY2-L15";((INDEX(ALLCLASSDATA,MATCH("SubclassAbility2-L15",CLASSFEATUREHEADERS,0),MATCH(($A39),CLASSNAMEHEADERS,0))))}} -> SUBCLASSABILITY2-L15 | X38: {={"SUBCLASSABILITY2-L17";((INDEX(ALLCLASSDATA,MATCH("SubclassAbility2-L17",CLASSFEATUREHEADERS,0),MATCH(($A39),CLASSNAMEHEADERS,0))))}} -> SUBCLASSABILITY2-L17 | Z38: {={"SUBCLASSABILITY2-L19";((INDEX(ALLCLASSDATA,MATCH("SubclassAbility2-L19",CLASSFEATUREHEADERS,0),MATCH(($A39),CLASSNAMEHEADERS,0))))}} -> SUBCLASSABILITY2-L19
A39: Champion | C39: Soldier | D39: ClassAbility | E39: SubclassAbility2
A40: {={"FormulaRow19";(INDEX(CLASSLIST,A3,1))}} -> FormulaRow19 | B40: FILTERFORMULAOUT | C40: {={"CLASSTYPE";((INDEX(ALLCLASSDATA,MATCH("ClassType",CLASSFEATUREHEADERS,0),MATCH($A41,CLASSNAMEHEADERS,0))))}} -> CLASSTYPE | D40: {={"CLASSABILITYPTS";"ClassAbilityPts"}} -> CLASSABILITYPTS | E40: {={"SUBCLASSABILITY2";"SubclassAbility2"}} -> SUBCLASSABILITY2 | J40: {={"SUBCLASSABILITY2-L03PTS";((INDEX(ALLCLASSDATA,MATCH("SubclassAbility2-L03",CLASSFEATUREHEADERS,0),MATCH(($A41 & "Points"),CLASSNAMEHEADERS,0))))}} -> SUBCLASSABILITY2-L03PTS | L40: {={"SUBCLASSABILITY2-L05PTS";((INDEX(ALLCLASSDATA,MATCH("SubclassAbility2-L05",CLASSFEATUREHEADERS,0),MATCH(($A41 & "Points"),CLASSNAMEHEADERS,0))))}} -> SUBCLASSABILITY2-L05PTS | N40: {={"SUBCLASSABILITY2-L07PTS";((INDEX(ALLCLASSDATA,MATCH("SubclassAbility2-L07",CLASSFEATUREHEADERS,0),MATCH(($A41 & "Points"),CLASSNAMEHEADERS,0))))}} -> SUBCLASSABILITY2-L07PTS | P40: {={"SUBCLASSABILITY2-L09PTS";((INDEX(ALLCLASSDATA,MATCH("SubclassAbility2-L09",CLASSFEATUREHEADERS,0),MATCH(($A41 & "Points"),CLASSNAMEHEADERS,0))))}} -> SUBCLASSABILITY2-L09PTS | R40: {={"SUBCLASSABILITY2-L11PTS";((INDEX(ALLCLASSDATA,MATCH("SubclassAbility2-L11",CLASSFEATUREHEADERS,0),MATCH(($A41 & "Points"),CLASSNAMEHEADERS,0))))}} -> SUBCLASSABILITY2-L11PTS | T40: {={"SUBCLASSABILITY2-L13PTS";((INDEX(ALLCLASSDATA,MATCH("SubclassAbility2-L13",CLASSFEATUREHEADERS,0),MATCH(($A41 & "Points"),CLASSNAMEHEADERS,0))))}} -> SUBCLASSABILITY2-L13PTS | V40: {={"SUBCLASSABILITY2-L15PTS";((INDEX(ALLCLASSDATA,MATCH("SubclassAbility2-L15",CLASSFEATUREHEADERS,0),MATCH(($A41 & "Points"),CLASSNAMEHEADERS,0))))}} -> SUBCLASSABILITY2-L15PTS | X40: {={"SUBCLASSABILITY2-L17PTS";((INDEX(ALLCLASSDATA,MATCH("SubclassAbility2-L17",CLASSFEATUREHEADERS,0),MATCH(($A41 & "Points"),CLASSNAMEHEADERS,0))))}} -> SUBCLASSABILITY2-L17PTS | Z40: {={"SUBCLASSABILITY2-L19PTS";((INDEX(ALLCLASSDATA,MATCH("SubclassAbility2-L19",CLASSFEATUREHEADERS,0),MATCH(($A41 & "Points"),CLASSNAMEHEADERS,0))))}} -> SUBCLASSABILITY2-L19PTS | AC40: {={"SUBCLASSABILITY2 TOTAL";(sum(G41:AA41))}} -> SUBCLASSABILITY2 TOTAL
A41: Champion | C41: Soldier | D41: ClassAbilityPts | E41: SubclassAbility2 | AC41: 0
A42: {={"FormulaRow20";(INDEX(CLASSLIST,A3,1))}} -> FormulaRow20 | B42: FILTERFORMULAOUT | C42: {={"CLASSTYPE";((INDEX(ALLCLASSDATA,MATCH("ClassType",CLASSFEATUREHEADERS,0),MATCH($A43,CLASSNAMEHEADERS,0))))}} -> CLASSTYPE | D42: {={"DC";"DC"}} -> DC | E42: {={"CLASSDC";"ClassDC"}} -> CLASSDC | F42: {={"CLASSDCINITIAL";((IF(H43=10,"T",(IF(H43=50,"E","")))))}} -> CLASSDCINITIAL | G42: {={"CLASSDCINITIALPTS";((IF("00"=(INDEX(ALLCLASSDATA,MATCH("ClassDCLegendary",CLASSFEATUREHEADERS,0),MATCH($A43,CLASSNAMEHEADERS,0))),(INDEX(ALLCLASSDATA,MATCH("ClassDCLegendary",CLASSFEATUREHEADERS,0),MATCH(($A43 & "Points"),CLASSNAMEHEADERS,0))),(IF("00"=(INDEX(ALLCLASSDATA,MATCH("ClassDCMaster",CLASSFEATUREHEADERS,0),MATCH($A43,CLASSNAMEHEADERS,0))),(INDEX(ALLCLASSDATA,MATCH("ClassDCMaster",CLASSFEATUREHEADERS,0),MATCH(($A43 & "Points"),CLASSNAMEHEADERS,0))),(IF("00"=(INDEX(ALLCLASSDATA,MATCH("ClassDCExpert",CLASSFEATUREHEADERS,0),MATCH($A43,CLASSNAMEHEADERS,0))),(INDEX(ALLCLASSDATA,MATCH("ClassDCExpert",CLASSFEATUREHEADERS,0),MATCH(($A43 & "Points"),CLASSNAMEHEADERS,0))),(IF("00"=(INDEX(ALLCLASSDATA,MATCH("ClassDCTrained",CLASSFEATUREHEADERS,0),MATCH($A43,CLASSNAMEHEADERS,0))),(INDEX(ALLCLASSDATA,MATCH("ClassDCTrained",CLASSFEATUREHEADERS,0),MATCH(($A43 & "Points"),CLASSNAMEHEADERS,0))),"")))))))))}} -> CLASSDCINITIALPTS | H42: {={"CLASSDCL01";((IF("01"=(INDEX(ALLCLASSDATA,MATCH("ClassDCLegendary",CLASSFEATUREHEADERS,0),MATCH($A43,CLASSNAMEHEADERS,0))),(INDEX(ALLCLASSDATA,MATCH("ClassDCLegendary",CLASSFEATUREHEADERS,0),MATCH(($A43 & "Points"),CLASSNAMEHEADERS,0))),(IF("01"=(INDEX(ALLCLASSDATA,MATCH("ClassDCMaster",CLASSFEATUREHEADERS,0),MATCH($A43,CLASSNAMEHEADERS,0))),(INDEX(ALLCLASSDATA,MATCH("ClassDCMaster",CLASSFEATUREHEADERS,0),MATCH(($A43 & "Points"),CLASSNAMEHEADERS,0))),(IF("01"=(INDEX(ALLCLASSDATA,MATCH("ClassDCExpert",CLASSFEATUREHEADERS,0),MATCH($A43,CLASSNAMEHEADERS,0))),(INDEX(ALLCLASSDATA,MATCH("ClassDCExpert",CLASSFEATUREHEADERS,0),MATCH(($A43 & "Points"),CLASSNAMEHEADERS,0))),(IF("01"=(INDEX(ALLCLASSDATA,MATCH("ClassDCTrained",CLASSFEATUREHEADERS,0),MATCH($A43,CLASSNAMEHEADERS,0))),(INDEX(ALLCLASSDATA,MATCH("ClassDCTrained",CLASSFEATUREHEADERS,0),MATCH(($A43 & "Points"),CLASSNAMEHEADERS,0))),"")))))))))}} -> CLASSDCL01 | J42: {={"CLASSDCL03";((IF("03"=(INDEX(ALLCLASSDATA,MATCH("ClassDCLegendary",CLASSFEATUREHEADERS,0),MATCH($A43,CLASSNAMEHEADERS,0))),(INDEX(ALLCLASSDATA,MATCH("ClassDCLegendary",CLASSFEATUREHEADERS,0),MATCH(($A43 & "Points"),CLASSNAMEHEADERS,0))),(IF("03"=(INDEX(ALLCLASSDATA,MATCH("ClassDCMaster",CLASSFEATUREHEADERS,0),MATCH($A43,CLASSNAMEHEADERS,0))),(INDEX(ALLCLASSDATA,MATCH("ClassDCMaster",CLASSFEATUREHEADERS,0),MATCH(($A43 & "Points"),CLASSNAMEHEADERS,0))),(IF("03"=(INDEX(ALLCLASSDATA,MATCH("ClassDCExpert",CLASSFEATUREHEADERS,0),MATCH($A43,CLASSNAMEHEADERS,0))),(INDEX(ALLCLASSDATA,MATCH("ClassDCExpert",CLASSFEATUREHEADERS,0),MATCH(($A43 & "Points"),CLASSNAMEHEADERS,0))),(IF("03"=(INDEX(ALLCLASSDATA,MATCH("ClassDCTrained",CLASSFEATUREHEADERS,0),MATCH($A43,CLASSNAMEHEADERS,0))),(INDEX(ALLCLASSDATA,MATCH("ClassDCTrained",CLASSFEATUREHEADERS,0),MATCH(($A43 & "Points"),CLASSNAMEHEADERS,0))),"")))))))))}} -> CLASSDCL03 | L42: {={"CLASSDCL05";((IF("05"=(INDEX(ALLCLASSDATA,MATCH("ClassDCLegendary",CLASSFEATUREHEADERS,0),MATCH($A43,CLASSNAMEHEADERS,0))),(INDEX(ALLCLASSDATA,MATCH("ClassDCLegendary",CLASSFEATUREHEADERS,0),MATCH(($A43 & "Points"),CLASSNAMEHEADERS,0))),(IF("05"=(INDEX(ALLCLASSDATA,MATCH("ClassDCMaster",CLASSFEATUREHEADERS,0),MATCH($A43,CLASSNAMEHEADERS,0))),(INDEX(ALLCLASSDATA,MATCH("ClassDCMaster",CLASSFEATUREHEADERS,0),MATCH(($A43 & "Points"),CLASSNAMEHEADERS,0))),(IF("05"=(INDEX(ALLCLASSDATA,MATCH("ClassDCExpert",CLASSFEATUREHEADERS,0),MATCH($A43,CLASSNAMEHEADERS,0))),(INDEX(ALLCLASSDATA,MATCH("ClassDCExpert",CLASSFEATUREHEADERS,0),MATCH(($A43 & "Points"),CLASSNAMEHEADERS,0))),(IF("05"=(INDEX(ALLCLASSDATA,MATCH("ClassDCTrained",CLASSFEATUREHEADERS,0),MATCH($A43,CLASSNAMEHEADERS,0))),(INDEX(ALLCLASSDATA,MATCH("ClassDCTrained",CLASSFEATUREHEADERS,0),MATCH(($A43 & "Points"),CLASSNAMEHEADERS,0))),"")))))))))}} -> CLASSDCL05 | N42: {={"CLASSDCL07";((IF("07"=(INDEX(ALLCLASSDATA,MATCH("ClassDCLegendary",CLASSFEATUREHEADERS,0),MATCH($A43,CLASSNAMEHEADERS,0))),(INDEX(ALLCLASSDATA,MATCH("ClassDCLegendary",CLASSFEATUREHEADERS,0),MATCH(($A43 & "Points"),CLASSNAMEHEADERS,0))),(IF("07"=(INDEX(ALLCLASSDATA,MATCH("ClassDCMaster",CLASSFEATUREHEADERS,0),MATCH($A43,CLASSNAMEHEADERS,0))),(INDEX(ALLCLASSDATA,MATCH("ClassDCMaster",CLASSFEATUREHEADERS,0),MATCH(($A43 & "Points"),CLASSNAMEHEADERS,0))),(IF("07"=(INDEX(ALLCLASSDATA,MATCH("ClassDCExpert",CLASSFEATUREHEADERS,0),MATCH($A43,CLASSNAMEHEADERS,0))),(INDEX(ALLCLASSDATA,MATCH("ClassDCExpert",CLASSFEATUREHEADERS,0),MATCH(($A43 & "Points"),CLASSNAMEHEADERS,0))),(IF("07"=(INDEX(ALLCLASSDATA,MATCH("ClassDCTrained",CLASSFEATUREHEADERS,0),MATCH($A43,CLASSNAMEHEADERS,0))),(INDEX(ALLCLASSDATA,MATCH("ClassDCTrained",CLASSFEATUREHEADERS,0),MATCH(($A43 & "Points"),CLASSNAMEHEADERS,0))),"")))))))))}} -> CLASSDCL07 | P42: {={"CLASSDCL09";((IF("09"=(INDEX(ALLCLASSDATA,MATCH("ClassDCLegendary",CLASSFEATUREHEADERS,0),MATCH($A43,CLASSNAMEHEADERS,0))),(INDEX(ALLCLASSDATA,MATCH("ClassDCLegendary",CLASSFEATUREHEADERS,0),MATCH(($A43 & "Points"),CLASSNAMEHEADERS,0))),(IF("09"=(INDEX(ALLCLASSDATA,MATCH("ClassDCMaster",CLASSFEATUREHEADERS,0),MATCH($A43,CLASSNAMEHEADERS,0))),(INDEX(ALLCLASSDATA,MATCH("ClassDCMaster",CLASSFEATUREHEADERS,0),MATCH(($A43 & "Points"),CLASSNAMEHEADERS,0))),(IF("09"=(INDEX(ALLCLASSDATA,MATCH("ClassDCExpert",CLASSFEATUREHEADERS,0),MATCH($A43,CLASSNAMEHEADERS,0))),(INDEX(ALLCLASSDATA,MATCH("ClassDCExpert",CLASSFEATUREHEADERS,0),MATCH(($A43 & "Points"),CLASSNAMEHEADERS,0))),(IF("09"=(INDEX(ALLCLASSDATA,MATCH("ClassDCTrained",CLASSFEATUREHEADERS,0),MATCH($A43,CLASSNAMEHEADERS,0))),(INDEX(ALLCLASSDATA,MATCH("ClassDCTrained",CLASSFEATUREHEADERS,0),MATCH(($A43 & "Points"),CLASSNAMEHEADERS,0))),"")))))))))}} -> CLASSDCL09 | R42: {={"CLASSDCL11";((IF("11"=(INDEX(ALLCLASSDATA,MATCH("ClassDCLegendary",CLASSFEATUREHEADERS,0),MATCH($A43,CLASSNAMEHEADERS,0))),(INDEX(ALLCLASSDATA,MATCH("ClassDCLegendary",CLASSFEATUREHEADERS,0),MATCH(($A43 & "Points"),CLASSNAMEHEADERS,0))),(IF("11"=(INDEX(ALLCLASSDATA,MATCH("ClassDCMaster",CLASSFEATUREHEADERS,0),MATCH($A43,CLASSNAMEHEADERS,0))),(INDEX(ALLCLASSDATA,MATCH("ClassDCMaster",CLASSFEATUREHEADERS,0),MATCH(($A43 & "Points"),CLASSNAMEHEADERS,0))),(IF("11"=(INDEX(ALLCLASSDATA,MATCH("ClassDCExpert",CLASSFEATUREHEADERS,0),MATCH($A43,CLASSNAMEHEADERS,0))),(INDEX(ALLCLASSDATA,MATCH("ClassDCExpert",CLASSFEATUREHEADERS,0),MATCH(($A43 & "Points"),CLASSNAMEHEADERS,0))),(IF("11"=(INDEX(ALLCLASSDATA,MATCH("ClassDCTrained",CLASSFEATUREHEADERS,0),MATCH($A43,CLASSNAMEHEADERS,0))),(INDEX(ALLCLASSDATA,MATCH("ClassDCTrained",CLASSFEATUREHEADERS,0),MATCH(($A43 & "Points"),CLASSNAMEHEADERS,0))),"")))))))))}} -> CLASSDCL11 | T42: {={"CLASSDCL13";((IF("13"=(INDEX(ALLCLASSDATA,MATCH("ClassDCLegendary",CLASSFEATUREHEADERS,0),MATCH($A43,CLASSNAMEHEADERS,0))),(INDEX(ALLCLASSDATA,MATCH("ClassDCLegendary",CLASSFEATUREHEADERS,0),MATCH(($A43 & "Points"),CLASSNAMEHEADERS,0))),(IF("13"=(INDEX(ALLCLASSDATA,MATCH("ClassDCMaster",CLASSFEATUREHEADERS,0),MATCH($A43,CLASSNAMEHEADERS,0))),(INDEX(ALLCLASSDATA,MATCH("ClassDCMaster",CLASSFEATUREHEADERS,0),MATCH(($A43 & "Points"),CLASSNAMEHEADERS,0))),(IF("13"=(INDEX(ALLCLASSDATA,MATCH("ClassDCExpert",CLASSFEATUREHEADERS,0),MATCH($A43,CLASSNAMEHEADERS,0))),(INDEX(ALLCLASSDATA,MATCH("ClassDCExpert",CLASSFEATUREHEADERS,0),MATCH(($A43 & "Points"),CLASSNAMEHEADERS,0))),(IF("13"=(INDEX(ALLCLASSDATA,MATCH("ClassDCTrained",CLASSFEATUREHEADERS,0),MATCH($A43,CLASSNAMEHEADERS,0))),(INDEX(ALLCLASSDATA,MATCH("ClassDCTrained",CLASSFEATUREHEADERS,0),MATCH(($A43 & "Points"),CLASSNAMEHEADERS,0))),"")))))))))}} -> CLASSDCL13 | V42: {={"CLASSDCL15";((IF("15"=(INDEX(ALLCLASSDATA,MATCH("ClassDCLegendary",CLASSFEATUREHEADERS,0),MATCH($A43,CLASSNAMEHEADERS,0))),(INDEX(ALLCLASSDATA,MATCH("ClassDCLegendary",CLASSFEATUREHEADERS,0),MATCH(($A43 & "Points"),CLASSNAMEHEADERS,0))),(IF("15"=(INDEX(ALLCLASSDATA,MATCH("ClassDCMaster",CLASSFEATUREHEADERS,0),MATCH($A43,CLASSNAMEHEADERS,0))),(INDEX(ALLCLASSDATA,MATCH("ClassDCMaster",CLASSFEATUREHEADERS,0),MATCH(($A43 & "Points"),CLASSNAMEHEADERS,0))),(IF("15"=(INDEX(ALLCLASSDATA,MATCH("ClassDCExpert",CLASSFEATUREHEADERS,0),MATCH($A43,CLASSNAMEHEADERS,0))),(INDEX(ALLCLASSDATA,MATCH("ClassDCExpert",CLASSFEATUREHEADERS,0),MATCH(($A43 & "Points"),CLASSNAMEHEADERS,0))),(IF("15"=(INDEX(ALLCLASSDATA,MATCH("ClassDCTrained",CLASSFEATUREHEADERS,0),MATCH($A43,CLASSNAMEHEADERS,0))),(INDEX(ALLCLASSDATA,MATCH("ClassDCTrained",CLASSFEATUREHEADERS,0),MATCH(($A43 & "Points"),CLASSNAMEHEADERS,0))),"")))))))))}} -> CLASSDCL15 | X42: {={"CLASSDCL17";((IF("17"=(INDEX(ALLCLASSDATA,MATCH("ClassDCLegendary",CLASSFEATUREHEADERS,0),MATCH($A43,CLASSNAMEHEADERS,0))),(INDEX(ALLCLASSDATA,MATCH("ClassDCLegendary",CLASSFEATUREHEADERS,0),MATCH(($A43 & "Points"),CLASSNAMEHEADERS,0))),(IF("17"=(INDEX(ALLCLASSDATA,MATCH("ClassDCMaster",CLASSFEATUREHEADERS,0),MATCH($A43,CLASSNAMEHEADERS,0))),(INDEX(ALLCLASSDATA,MATCH("ClassDCMaster",CLASSFEATUREHEADERS,0),MATCH(($A43 & "Points"),CLASSNAMEHEADERS,0))),(IF("17"=(INDEX(ALLCLASSDATA,MATCH("ClassDCExpert",CLASSFEATUREHEADERS,0),MATCH($A43,CLASSNAMEHEADERS,0))),(INDEX(ALLCLASSDATA,MATCH("ClassDCExpert",CLASSFEATUREHEADERS,0),MATCH(($A43 & "Points"),CLASSNAMEHEADERS,0))),(IF("17"=(INDEX(ALLCLASSDATA,MATCH("ClassDCTrained",CLASSFEATUREHEADERS,0),MATCH($A43,CLASSNAMEHEADERS,0))),(INDEX(ALLCLASSDATA,MATCH("ClassDCTrained",CLASSFEATUREHEADERS,0),MATCH(($A43 & "Points"),CLASSNAMEHEADERS,0))),"")))))))))}} -> CLASSDCL17 | Z42: {={"CLASSDCL19";((IF("19"=(INDEX(ALLCLASSDATA,MATCH("ClassDCLegendary",CLASSFEATUREHEADERS,0),MATCH($A43,CLASSNAMEHEADERS,0))),(INDEX(ALLCLASSDATA,MATCH("ClassDCLegendary",CLASSFEATUREHEADERS,0),MATCH(($A43 & "Points"),CLASSNAMEHEADERS,0))),(IF("19"=(INDEX(ALLCLASSDATA,MATCH("ClassDCMaster",CLASSFEATUREHEADERS,0),MATCH($A43,CLASSNAMEHEADERS,0))),(INDEX(ALLCLASSDATA,MATCH("ClassDCMaster",CLASSFEATUREHEADERS,0),MATCH(($A43 & "Points"),CLASSNAMEHEADERS,0))),(IF("19"=(INDEX(ALLCLASSDATA,MATCH("ClassDCExpert",CLASSFEATUREHEADERS,0),MATCH($A43,CLASSNAMEHEADERS,0))),(INDEX(ALLCLASSDATA,MATCH("ClassDCExpert",CLASSFEATUREHEADERS,0),MATCH(($A43 & "Points"),CLASSNAMEHEADERS,0))),(IF("19"=(INDEX(ALLCLASSDATA,MATCH("ClassDCTrained",CLASSFEATUREHEADERS,0),MATCH($A43,CLASSNAMEHEADERS,0))),(INDEX(ALLCLASSDATA,MATCH("ClassDCTrained",CLASSFEATUREHEADERS,0),MATCH(($A43 & "Points"),CLASSNAMEHEADERS,0))),"")))))))))}} -> CLASSDCL19 | AB42: {={"CLASSDC TOTAL";(IF(COUNTBLANK(G43:AA43)=17,"L",(IF(COUNTBLANK(G43:AA43)=18,"M",(IF(COUNTBLANK(G43:AA43)=19,"E",(IF(COUNTBLANK(G43:AA43)=20,"T",""))))))))}} -> CLASSDC TOTAL | AC42: {={"CLASSDC TOTAL";(sum(G43:AA43))}} -> CLASSDC TOTAL
A43: Champion | C43: Soldier | D43: DC | E43: ClassDC | F43: T | H43: 10 | P43: 50 | X43: 110 | AB43: M | AC43: 170
